Workbook

Sheet Compare
A1: ICPC single-contest trip plans — Shenyang, Shanghai, Nanchang, Hong Kong, EC Final Hangzhou
A2: Each trip planned as if it is the only contest attended. Two to three variants per contest. Two scenarios: the UNFUNDED regional (3 contestants pay everything) and the FUNDED regional (₮12M from the university, coach travels: 4 people). University funding covers flights, trains, hotels, meals & local transport; contest fees and 'Other' are personal. Prices: Trip.com / 12306 / ChinaTicketOnline / SlickTrip / Booking.com checked 30 Sep – 22 Oct 2026. Blue = inputs; yellow = key assumptions; green = links.
A4: Shared inputs
A5: University funding – funded regional (MNT) | B5: 12000000 | C5: One regional is funded with ₮12M and the coach travels (4 people: 3 contestants + coach); used in every "4 ppl" column
A6: Travelers – unfunded regional | B6: 3 | C6: 3 contestants, one room, everyone pays
A7: Travelers – funded regional (with coach) | B7: 4 | C7: 3 contestants + coach, two rooms (or one family room for 4)
A8: USD → MNT | B8: 3598 | C8: Mid-market, Xe/Investing.com, 29–30 Sep 2026
A9: CNY → MNT | B9: 536 | C9: Mid-market, Xe/currency.wiki, late Sep 2026
A10: HKD → MNT | B10: 461 | C10: Derived from USD rate and the HKD peg (~7.8 HKD per USD)
A11: Contingency % (on university-paid part) | B11: 0.1 | C11: Buffer for fare changes, FX spread, extras
A12: University funding – unfunded regional (MNT) | B12: 0 | C12: The other regional is unfunded: the 3 contestants pay everything themselves; used in every "3 ppl" column
A13: Side-by-side (all figures incl. 10% contingency on the travel + stay part). 3 ppl = the UNFUNDED regional, 4 ppl = the FUNDED regional (₮12M, coach travels)
A14: Plan | B14: Travel + stay total – 3 ppl (unfunded: paid by the contestants) | C14: Funding left – 3 ppl (funding ₮0) | D14: Cost per person – 3 ppl (everything incl. fee) | E14: Travel + stay total – 4 ppl (funded) | F14: Left of the ₮12M – 4 ppl (negative = over) | G14: Out-of-pocket per person – 4 ppl (fee, UB taxi, insurance, eSIM) | H14: Whole trip – 3 ppl | I14: Whole trip – 4 ppl | J14: Planes & trains | K14: Door-to-door | L14: Fits ₮12M incl. 10% contingency? | M14: Left of ₮12M before contingency (4 ppl)
A15: Shenyang – Budget | B15: ='Shenyang – Budget'!H34 | C15: ='Shenyang – Budget'!H35 | D15: ='Shenyang – Budget'!H37 | E15: ='Shenyang – Budget'!K34 | F15: ='Shenyang – Budget'!K35 | G15: ='Shenyang – Budget'!K37 | H15: ='Shenyang – Budget'!H38 | I15: ='Shenyang – Budget'!K38 | J15: ='Shenyang – Budget'!H39 | K15: ='Shenyang – Budget'!D69 | L15: =IF(F15>=0,"yes","over by "&TEXT(-F15,"#,##0")&" ₮") | M15: =Compare!$B$5-E15/(1+Compare!$B$11)
A16: Shenyang – Comfort | B16: ='Shenyang – Comfort'!H33 | C16: ='Shenyang – Comfort'!H34 | D16: ='Shenyang – Comfort'!H36 | E16: ='Shenyang – Comfort'!K33 | F16: ='Shenyang – Comfort'!K34 | G16: ='Shenyang – Comfort'!K36 | H16: ='Shenyang – Comfort'!H37 | I16: ='Shenyang – Comfort'!K37 | J16: ='Shenyang – Comfort'!H38 | K16: ='Shenyang – Comfort'!D68 | L16: =IF(F16>=0,"yes","over by "&TEXT(-F16,"#,##0")&" ₮") | M16: =Compare!$B$5-E16/(1+Compare!$B$11)
A17: Shenyang – Budget (G-train) | B17: ='Shenyang – Budget (G-train)'!H35 | C17: ='Shenyang – Budget (G-train)'!H36 | D17: ='Shenyang – Budget (G-train)'!H38 | E17: ='Shenyang – Budget (G-train)'!K35 | F17: ='Shenyang – Budget (G-train)'!K36 | G17: ='Shenyang – Budget (G-train)'!K38 | H17: ='Shenyang – Budget (G-train)'!H39 | I17: ='Shenyang – Budget (G-train)'!K39 | J17: ='Shenyang – Budget (G-train)'!H40 | K17: ='Shenyang – Budget (G-train)'!D70 | L17: =IF(F17>=0,"yes","over by "&TEXT(-F17,"#,##0")&" ₮") | M17: =Compare!$B$5-E17/(1+Compare!$B$11)
A18: Shenyang – Comfort (G-train) | B18: ='Shenyang – Comfort (G-train)'!H35 | C18: ='Shenyang – Comfort (G-train)'!H36 | D18: ='Shenyang – Comfort (G-train)'!H38 | E18: ='Shenyang – Comfort (G-train)'!K35 | F18: ='Shenyang – Comfort (G-train)'!K36 | G18: ='Shenyang – Comfort (G-train)'!K38 | H18: ='Shenyang – Comfort (G-train)'!H39 | I18: ='Shenyang – Comfort (G-train)'!K39 | J18: ='Shenyang – Comfort (G-train)'!H40 | K18: ='Shenyang – Comfort (G-train)'!D71 | L18: =IF(F18>=0,"yes","over by "&TEXT(-F18,"#,##0")&" ₮") | M18: =Compare!$B$5-E18/(1+Compare!$B$11)
A19: Shenyang – Sleep first | B19: ='Shenyang – Sleep first'!H34 | C19: ='Shenyang – Sleep first'!H35 | D19: ='Shenyang – Sleep first'!H37 | E19: ='Shenyang – Sleep first'!K34 | F19: ='Shenyang – Sleep first'!K35 | G19: ='Shenyang – Sleep first'!K37 | H19: ='Shenyang – Sleep first'!H38 | I19: ='Shenyang – Sleep first'!K38 | J19: ='Shenyang – Sleep first'!H39 | K19: ='Shenyang – Sleep first'!D70 | L19: =IF(F19>=0,"yes","over by "&TEXT(-F19,"#,##0")&" ₮") | M19: =Compare!$B$5-E19/(1+Compare!$B$11)
A20: Shenyang – Sleep value | B20: ='Shenyang – Sleep value'!H34 | C20: ='Shenyang – Sleep value'!H35 | D20: ='Shenyang – Sleep value'!H37 | E20: ='Shenyang – Sleep value'!K34 | F20: ='Shenyang – Sleep value'!K35 | G20: ='Shenyang – Sleep value'!K37 | H20: ='Shenyang – Sleep value'!H38 | I20: ='Shenyang – Sleep value'!K38 | J20: ='Shenyang – Sleep value'!H39 | K20: ='Shenyang – Sleep value'!D70 | L20: =IF(F20>=0,"yes","over by "&TEXT(-F20,"#,##0")&" ₮") | M20: =Compare!$B$5-E20/(1+Compare!$B$11)
A21: Shenyang – Overland home | B21: ='Shenyang – Overland home'!H36 | C21: ='Shenyang – Overland home'!H37 | D21: ='Shenyang – Overland home'!H39 | E21: ='Shenyang – Overland home'!K36 | F21: ='Shenyang – Overland home'!K37 | G21: ='Shenyang – Overland home'!K39 | H21: ='Shenyang – Overland home'!H40 | I21: ='Shenyang – Overland home'!K40 | J21: ='Shenyang – Overland home'!H41 | K21: ='Shenyang – Overland home'!D75 | L21: =IF(F21>=0,"yes","over by "&TEXT(-F21,"#,##0")&" ₮") | M21: =Compare!$B$5-E21/(1+Compare!$B$11)
A22: Shenyang – Overland out (seats) | B22: ='Shenyang – Overland out (seats)'!H36 | C22: ='Shenyang – Overland out (seats)'!H37 | D22: ='Shenyang – Overland out (seats)'!H39 | E22: ='Shenyang – Overland out (seats)'!K36 | F22: ='Shenyang – Overland out (seats)'!K37 | G22: ='Shenyang – Overland out (seats)'!K39 | H22: ='Shenyang – Overland out (seats)'!H40 | I22: ='Shenyang – Overland out (seats)'!K40 | J22: ='Shenyang – Overland out (seats)'!H41 | K22: ='Shenyang – Overland out (seats)'!D71 | L22: =IF(F22>=0,"yes","over by "&TEXT(-F22,"#,##0")&" ₮") | M22: =Compare!$B$5-E22/(1+Compare!$B$11)
A23: Shenyang – Overland out, berths | B23: ='Shenyang – Overland out, berths'!H36 | C23: ='Shenyang – Overland out, berths'!H37 | D23: ='Shenyang – Overland out, berths'!H39 | E23: ='Shenyang – Overland out, berths'!K36 | F23: ='Shenyang – Overland out, berths'!K37 | G23: ='Shenyang – Overland out, berths'!K39 | H23: ='Shenyang – Overland out, berths'!H40 | I23: ='Shenyang – Overland out, berths'!K40 | J23: ='Shenyang – Overland out, berths'!H41 | K23: ='Shenyang – Overland out, berths'!D71 | L23: =IF(F23>=0,"yes","over by "&TEXT(-F23,"#,##0")&" ₮") | M23: =Compare!$B$5-E23/(1+Compare!$B$11)
A24: Shenyang – Manzhouli seats | B24: ='Shenyang – Manzhouli seats'!H35 | C24: ='Shenyang – Manzhouli seats'!H36 | D24: ='Shenyang – Manzhouli seats'!H38 | E24: ='Shenyang – Manzhouli seats'!K35 | F24: ='Shenyang – Manzhouli seats'!K36 | G24: ='Shenyang – Manzhouli seats'!K38 | H24: ='Shenyang – Manzhouli seats'!H39 | I24: ='Shenyang – Manzhouli seats'!K39 | J24: ='Shenyang – Manzhouli seats'!H40 | K24: ='Shenyang – Manzhouli seats'!D72 | L24: =IF(F24>=0,"yes","over by "&TEXT(-F24,"#,##0")&" ₮") | M24: =Compare!$B$5-E24/(1+Compare!$B$11)
A25: Shenyang – Hunnu Daxing + K341 | B25: ='Shenyang – Hunnu Daxing + K341'!H34 | C25: ='Shenyang – Hunnu Daxing + K341'!H35 | D25: ='Shenyang – Hunnu Daxing + K341'!H37 | E25: ='Shenyang – Hunnu Daxing + K341'!K34 | F25: ='Shenyang – Hunnu Daxing + K341'!K35 | G25: ='Shenyang – Hunnu Daxing + K341'!K37 | H25: ='Shenyang – Hunnu Daxing + K341'!H38 | I25: ='Shenyang – Hunnu Daxing + K341'!K38 | J25: ='Shenyang – Hunnu Daxing + K341'!H39 | K25: ='Shenyang – Hunnu Daxing + K341'!D68 | L25: =IF(F25>=0,"yes","over by "&TEXT(-F25,"#,##0")&" ₮") | M25: =Compare!$B$5-E25/(1+Compare!$B$11)
A26: Shenyang – MIAT 13 Nov + K341 | B26: ='Shenyang – MIAT 13 Nov + K341'!H34 | C26: ='Shenyang – MIAT 13 Nov + K341'!H35 | D26: ='Shenyang – MIAT 13 Nov + K341'!H37 | E26: ='Shenyang – MIAT 13 Nov + K341'!K34 | F26: ='Shenyang – MIAT 13 Nov + K341'!K35 | G26: ='Shenyang – MIAT 13 Nov + K341'!K37 | H26: ='Shenyang – MIAT 13 Nov + K341'!H38 | I26: ='Shenyang – MIAT 13 Nov + K341'!K38 | J26: ='Shenyang – MIAT 13 Nov + K341'!H39 | K26: ='Shenyang – MIAT 13 Nov + K341'!D68 | L26: =IF(F26>=0,"yes","over by "&TEXT(-F26,"#,##0")&" ₮") | M26: =Compare!$B$5-E26/(1+Compare!$B$11)
A27: Shenyang – Hunnu Erenhot | B27: ='Shenyang – Hunnu Erenhot'!H35 | C27: ='Shenyang – Hunnu Erenhot'!H36 | D27: ='Shenyang – Hunnu Erenhot'!H38 | E27: ='Shenyang – Hunnu Erenhot'!K35 | F27: ='Shenyang – Hunnu Erenhot'!K36 | G27: ='Shenyang – Hunnu Erenhot'!K38 | H27: ='Shenyang – Hunnu Erenhot'!H39 | I27: ='Shenyang – Hunnu Erenhot'!K39 | J27: ='Shenyang – Hunnu Erenhot'!H40 | K27: ='Shenyang – Hunnu Erenhot'!D69 | L27: =IF(F27>=0,"yes","over by "&TEXT(-F27,"#,##0")&" ₮") | M27: =Compare!$B$5-E27/(1+Compare!$B$11)
A28: Shenyang – Hohhot red-eye | B28: ='Shenyang – Hohhot red-eye'!H35 | C28: ='Shenyang – Hohhot red-eye'!H36 | D28: ='Shenyang – Hohhot red-eye'!H38 | E28: ='Shenyang – Hohhot red-eye'!K35 | F28: ='Shenyang – Hohhot red-eye'!K36 | G28: ='Shenyang – Hohhot red-eye'!K38 | H28: ='Shenyang – Hohhot red-eye'!H39 | I28: ='Shenyang – Hohhot red-eye'!K39 | J28: ='Shenyang – Hohhot red-eye'!H40 | K28: ='Shenyang – Hohhot red-eye'!D72 | L28: =IF(F28>=0,"yes","over by "&TEXT(-F28,"#,##0")&" ₮") | M28: =Compare!$B$5-E28/(1+Compare!$B$11)
A29: Shenyang – Hohhot + Spring | B29: ='Shenyang – Hohhot + Spring'!H35 | C29: ='Shenyang – Hohhot + Spring'!H36 | D29: ='Shenyang – Hohhot + Spring'!H38 | E29: ='Shenyang – Hohhot + Spring'!K35 | F29: ='Shenyang – Hohhot + Spring'!K36 | G29: ='Shenyang – Hohhot + Spring'!K38 | H29: ='Shenyang – Hohhot + Spring'!H39 | I29: ='Shenyang – Hohhot + Spring'!K39 | J29: ='Shenyang – Hohhot + Spring'!H40 | K29: ='Shenyang – Hohhot + Spring'!D70 | L29: =IF(F29>=0,"yes","over by "&TEXT(-F29,"#,##0")&" ₮") | M29: =Compare!$B$5-E29/(1+Compare!$B$11)
A30: Shanghai – Sleeper | B30: ='Shanghai – Sleeper'!H35 | C30: ='Shanghai – Sleeper'!H36 | D30: ='Shanghai – Sleeper'!H38 | E30: ='Shanghai – Sleeper'!K35 | F30: ='Shanghai – Sleeper'!K36 | G30: ='Shanghai – Sleeper'!K38 | H30: ='Shanghai – Sleeper'!H39 | I30: ='Shanghai – Sleeper'!K39 | J30: ='Shanghai – Sleeper'!H40 | K30: ='Shanghai – Sleeper'!D71 | L30: =IF(F30>=0,"yes","over by "&TEXT(-F30,"#,##0")&" ₮") | M30: =Compare!$B$5-E30/(1+Compare!$B$11)
A31: Shanghai – Spring nonstop | B31: ='Shanghai – Spring nonstop'!H31 | C31: ='Shanghai – Spring nonstop'!H32 | D31: ='Shanghai – Spring nonstop'!H34 | E31: ='Shanghai – Spring nonstop'!K31 | F31: ='Shanghai – Spring nonstop'!K32 | G31: ='Shanghai – Spring nonstop'!K34 | H31: ='Shanghai – Spring nonstop'!H35 | I31: ='Shanghai – Spring nonstop'!K35 | J31: ='Shanghai – Spring nonstop'!H36 | K31: ='Shanghai – Spring nonstop'!D65 | L31: =IF(F31>=0,"yes","over by "&TEXT(-F31,"#,##0")&" ₮") | M31: =Compare!$B$5-E31/(1+Compare!$B$11)
A32: Shanghai – Nonstop cheap rooms | B32: ='Shanghai – Nonstop cheap rooms'!H31 | C32: ='Shanghai – Nonstop cheap rooms'!H32 | D32: ='Shanghai – Nonstop cheap rooms'!H34 | E32: ='Shanghai – Nonstop cheap rooms'!K31 | F32: ='Shanghai – Nonstop cheap rooms'!K32 | G32: ='Shanghai – Nonstop cheap rooms'!K34 | H32: ='Shanghai – Nonstop cheap rooms'!H35 | I32: ='Shanghai – Nonstop cheap rooms'!K35 | J32: ='Shanghai – Nonstop cheap rooms'!H36 | K32: ='Shanghai – Nonstop cheap rooms'!D65 | L32: =IF(F32>=0,"yes","over by "&TEXT(-F32,"#,##0")&" ₮") | M32: =Compare!$B$5-E32/(1+Compare!$B$11)
A33: Shanghai – Fly out, train home | B33: ='Shanghai – Fly out, train home'!H35 | C33: ='Shanghai – Fly out, train home'!H36 | D33: ='Shanghai – Fly out, train home'!H38 | E33: ='Shanghai – Fly out, train home'!K35 | F33: ='Shanghai – Fly out, train home'!K36 | G33: ='Shanghai – Fly out, train home'!K38 | H33: ='Shanghai – Fly out, train home'!H39 | I33: ='Shanghai – Fly out, train home'!K39 | J33: ='Shanghai – Fly out, train home'!H40 | K33: ='Shanghai – Fly out, train home'!D71 | L33: =IF(F33>=0,"yes","over by "&TEXT(-F33,"#,##0")&" ₮") | M33: =Compare!$B$5-E33/(1+Compare!$B$11)
A34: Shanghai – Train (no sleeper) | B34: ='Shanghai – Train (no sleeper)'!H37 | C34: ='Shanghai – Train (no sleeper)'!H38 | D34: ='Shanghai – Train (no sleeper)'!H40 | E34: ='Shanghai – Train (no sleeper)'!K37 | F34: ='Shanghai – Train (no sleeper)'!K38 | G34: ='Shanghai – Train (no sleeper)'!K40 | H34: ='Shanghai – Train (no sleeper)'!H41 | I34: ='Shanghai – Train (no sleeper)'!K41 | J34: ='Shanghai – Train (no sleeper)'!H42 | K34: ='Shanghai – Train (no sleeper)'!D74 | L34: =IF(F34>=0,"yes","over by "&TEXT(-F34,"#,##0")&" ₮") | M34: =Compare!$B$5-E34/(1+Compare!$B$11)
A35: Nanchang – Sleeper | B35: ='Nanchang – Sleeper'!H34 | C35: ='Nanchang – Sleeper'!H35 | D35: ='Nanchang – Sleeper'!H37 | E35: ='Nanchang – Sleeper'!K34 | F35: ='Nanchang – Sleeper'!K35 | G35: ='Nanchang – Sleeper'!K37 | H35: ='Nanchang – Sleeper'!H38 | I35: ='Nanchang – Sleeper'!K38 | J35: ='Nanchang – Sleeper'!H39 | K35: ='Nanchang – Sleeper'!D70 | L35: =IF(F35>=0,"yes","over by "&TEXT(-F35,"#,##0")&" ₮") | M35: =Compare!$B$5-E35/(1+Compare!$B$11)
A36: Nanchang – Comfort | B36: ='Nanchang – Comfort'!H36 | C36: ='Nanchang – Comfort'!H37 | D36: ='Nanchang – Comfort'!H39 | E36: ='Nanchang – Comfort'!K36 | F36: ='Nanchang – Comfort'!K37 | G36: ='Nanchang – Comfort'!K39 | H36: ='Nanchang – Comfort'!H40 | I36: ='Nanchang – Comfort'!K40 | J36: ='Nanchang – Comfort'!H41 | K36: ='Nanchang – Comfort'!D72 | L36: =IF(F36>=0,"yes","over by "&TEXT(-F36,"#,##0")&" ₮") | M36: =Compare!$B$5-E36/(1+Compare!$B$11)
A37: Nanchang – Fly in (Air China) | B37: ='Nanchang – Fly in (Air China)'!H34 | C37: ='Nanchang – Fly in (Air China)'!H35 | D37: ='Nanchang – Fly in (Air China)'!H37 | E37: ='Nanchang – Fly in (Air China)'!K34 | F37: ='Nanchang – Fly in (Air China)'!K35 | G37: ='Nanchang – Fly in (Air China)'!K37 | H37: ='Nanchang – Fly in (Air China)'!H38 | I37: ='Nanchang – Fly in (Air China)'!K38 | J37: ='Nanchang – Fly in (Air China)'!H39 | K37: ='Nanchang – Fly in (Air China)'!D68 | L37: =IF(F37>=0,"yes","over by "&TEXT(-F37,"#,##0")&" ₮") | M37: =Compare!$B$5-E37/(1+Compare!$B$11)
A38: Hong Kong – Budget | B38: ='Hong Kong – Budget'!H30 | C38: ='Hong Kong – Budget'!H31 | D38: ='Hong Kong – Budget'!H33 | E38: ='Hong Kong – Budget'!K30 | F38: ='Hong Kong – Budget'!K31 | G38: ='Hong Kong – Budget'!K33 | H38: ='Hong Kong – Budget'!H34 | I38: ='Hong Kong – Budget'!K34 | J38: ='Hong Kong – Budget'!H35 | K38: ='Hong Kong – Budget'!D60 | L38: =IF(F38>=0,"yes","over by "&TEXT(-F38,"#,##0")&" ₮") | M38: =Compare!$B$5-E38/(1+Compare!$B$11)
A39: Hong Kong – Comfort | B39: ='Hong Kong – Comfort'!H30 | C39: ='Hong Kong – Comfort'!H31 | D39: ='Hong Kong – Comfort'!H33 | E39: ='Hong Kong – Comfort'!K30 | F39: ='Hong Kong – Comfort'!K31 | G39: ='Hong Kong – Comfort'!K33 | H39: ='Hong Kong – Comfort'!H34 | I39: ='Hong Kong – Comfort'!K34 | J39: ='Hong Kong – Comfort'!H35 | K39: ='Hong Kong – Comfort'!D60 | L39: =IF(F39>=0,"yes","over by "&TEXT(-F39,"#,##0")&" ₮") | M39: =Compare!$B$5-E39/(1+Compare!$B$11)
A40: Hong Kong – Value | B40: ='Hong Kong – Value'!H30 | C40: ='Hong Kong – Value'!H31 | D40: ='Hong Kong – Value'!H33 | E40: ='Hong Kong – Value'!K30 | F40: ='Hong Kong – Value'!K31 | G40: ='Hong Kong – Value'!K33 | H40: ='Hong Kong – Value'!H34 | I40: ='Hong Kong – Value'!K34 | J40: ='Hong Kong – Value'!H35 | K40: ='Hong Kong – Value'!D60 | L40: =IF(F40>=0,"yes","over by "&TEXT(-F40,"#,##0")&" ₮") | M40: =Compare!$B$5-E40/(1+Compare!$B$11)
A41: Hong Kong – Sleep first | B41: ='Hong Kong – Sleep first'!H30 | C41: ='Hong Kong – Sleep first'!H31 | D41: ='Hong Kong – Sleep first'!H33 | E41: ='Hong Kong – Sleep first'!K30 | F41: ='Hong Kong – Sleep first'!K31 | G41: ='Hong Kong – Sleep first'!K33 | H41: ='Hong Kong – Sleep first'!H34 | I41: ='Hong Kong – Sleep first'!K34 | J41: ='Hong Kong – Sleep first'!H35 | K41: ='Hong Kong – Sleep first'!D60 | L41: =IF(F41>=0,"yes","over by "&TEXT(-F41,"#,##0")&" ₮") | M41: =Compare!$B$5-E41/(1+Compare!$B$11)
A42: Hong Kong – Funded 12M | B42: ='Hong Kong – Funded 12M'!H30 | C42: ='Hong Kong – Funded 12M'!H31 | D42: ='Hong Kong – Funded 12M'!H33 | E42: ='Hong Kong – Funded 12M'!K30 | F42: ='Hong Kong – Funded 12M'!K31 | G42: ='Hong Kong – Funded 12M'!K33 | H42: ='Hong Kong – Funded 12M'!H34 | I42: ='Hong Kong – Funded 12M'!K34 | J42: ='Hong Kong – Funded 12M'!H35 | K42: ='Hong Kong – Funded 12M'!D60 | L42: =IF(F42>=0,"yes","over by "&TEXT(-F42,"#,##0")&" ₮") | M42: =Compare!$B$5-E42/(1+Compare!$B$11)
A43: Hong Kong – Sleep priority | B43: ='Hong Kong – Sleep priority'!H30 | C43: ='Hong Kong – Sleep priority'!H31 | D43: ='Hong Kong – Sleep priority'!H33 | E43: ='Hong Kong – Sleep priority'!K30 | F43: ='Hong Kong – Sleep priority'!K31 | G43: ='Hong Kong – Sleep priority'!K33 | H43: ='Hong Kong – Sleep priority'!H34 | I43: ='Hong Kong – Sleep priority'!K34 | J43: ='Hong Kong – Sleep priority'!H35 | K43: ='Hong Kong – Sleep priority'!D60 | L43: =IF(F43>=0,"yes","over by "&TEXT(-F43,"#,##0")&" ₮") | M43: =Compare!$B$5-E43/(1+Compare!$B$11)
A44: EC Final Hangzhou – Train | B44: ='EC Final Hangzhou – Train'!H34 | C44: ='EC Final Hangzhou – Train'!H35 | D44: ='EC Final Hangzhou – Train'!H37 | E44: ='EC Final Hangzhou – Train'!K34 | F44: ='EC Final Hangzhou – Train'!K35 | G44: ='EC Final Hangzhou – Train'!K37 | H44: ='EC Final Hangzhou – Train'!H38 | I44: ='EC Final Hangzhou – Train'!K38 | J44: ='EC Final Hangzhou – Train'!H39 | K44: ='EC Final Hangzhou – Train'!D70 | L44: =IF(F44>=0,"yes","over by "&TEXT(-F44,"#,##0")&" ₮") | M44: =Compare!$B$5-E44/(1+Compare!$B$11)
A45: EC Final Hangzhou – Fly | B45: ='EC Final Hangzhou – Fly'!H33 | C45: ='EC Final Hangzhou – Fly'!H34 | D45: ='EC Final Hangzhou – Fly'!H36 | E45: ='EC Final Hangzhou – Fly'!K33 | F45: ='EC Final Hangzhou – Fly'!K34 | G45: ='EC Final Hangzhou – Fly'!K36 | H45: ='EC Final Hangzhou – Fly'!H37 | I45: ='EC Final Hangzhou – Fly'!K37 | J45: ='EC Final Hangzhou – Fly'!H38 | K45: ='EC Final Hangzhou – Fly'!D70 | L45: =IF(F45>=0,"yes","over by "&TEXT(-F45,"#,##0")&" ₮") | M45: =Compare!$B$5-E45/(1+Compare!$B$11)
A47: Recommended picks (not the expensive ones)
A48: Likely pairing (your answer) | B48: Funded = Hong Kong (₮12M, coach): lead with 'Hong Kong – Sleep priority' – MIAT nonstop, 2 rooms with 4 separate twin beds and private bathrooms at Good Fortune Inn (8.6, 715 reviews, ~35–40 min MTR to HKU), airport bus: ₮11.33M before the 10% contingency (₮0.67M spare), ₮12.47M with it. Walking alternative: 'Funded 12M' (Best Western Plus, ~540 m to HKU) ₮11.70M before contingency (₮0.30M spare). Unfunded = Shenyang, sleep first and cheap after: 'Shenyang – Sleep value' ₮2.69M per person (no early start, a bed each, home 16 Nov) or 'Shenyang – Overland home' ₮2.37M per person (same before the contest, night trains home via Erenhot, home 18 Nov); Budget ₮2.14M per person is cheaper but puts a sleeper the night before day 1. The HK 2026 host may not be HKU (2025 was HKUST), which favours sleeping well and staying on the MTR over a hotel next to one campus.
A49: Unfunded regional (3 ppl pay) | B49: Cheapest sleep-safe plans per person incl. fee, taxi, insurance, eSIM and 10% contingency: Shenyang – Overland out (seats) ₮1.70M per person (cheapest of all, but two seated train nights before day 1); Shenyang – Budget ₮2.14M per person (soft sleeper before day 1); Shenyang – Overland home ₮2.37M per person (no early start, a bed each, overland home); Shenyang – Comfort ₮2.46M per person; Nanchang – Sleeper ₮2.50M per person; Shenyang – Sleep value ₮2.69M / Sleep first ₮2.89M per person (no early start, a bed each, fly home); Shanghai – Sleeper ₮2.78M per person (Shanghai nonstop with cheap rooms ₮2.90M); Hong Kong – Budget ₮3.43M per person; EC Final – Train ₮3.14M per person. Shenyang and Nanchang are the cheap ones to pay yourselves.
A50: Funded regional (₮12M, coach) | B50: Fits ₮12M incl. contingency: Shenyang – Comfort ₮8.04M (fits, ₮3.96M left); Shanghai – Sleeper ₮9.23M (fits, ₮2.77M left; the nonstop with cheap rooms ₮9.48M and 'Fly out, train home' ₮9.28M also fit); Nanchang – Sleeper ₮8.19M (fits, ₮3.81M left); EC Final – Train ₮11.12M (fits, ₮0.88M left). Hong Kong only fits before the 10% contingency (the flights are ₮8.4M of it): Budget ₮11.02M, Value ₮11.26M, Sleep priority ₮11.33M, Funded 12M ₮11.70M, Comfort ₮11.96M; Sleep first ₮13.14M and EC Final – Fly do not fit at all. Use the funded trip for the dearest contest you must attend and pay the cheap one yourselves.
A51: Regional – Shenyang (14–15 Nov) | B51: Sleep first, cheapest after (22 Oct prices): Air China 11:50 out (¥1,291 on Ctrip; no 04:00 wake-up) + G153, two twin rooms for 3 nights, K28 hard seat + Air China 12:55 home. Sleep first (NEU International, 580 m, 9.7) ₮7.47M / ₮9.47M; Sleep value (Ji Hotel twins, ~15 min walk, 9.0) ₮6.88M / ₮8.87M; Overland home (Sleep value out, K1568 + 4652 night trains, jeep at Erenhot, UBTZ 275, home 18 Nov) ₮5.97M / ₮7.67M (3 / 4 ppl). Older: Comfort (MIAT 07:30, RiCH family room, K54) ₮6.18M / ₮8.04M; no sleepers: G-train Comfort ₮6.72M / ₮8.84M, G-train Budget ₮6.05M / ₮8.27M. Cheap way out instead (22 Oct; sheet 'Shenyang – Way out', rest of the trip as Sleep value): Overland out (UBTZ 276 + jeep + 4654 + T301, seats) ₮3.96M / ₮5.19M, per person ₮1.70M; with berths ₮1.79M per person; Hunnu Daxing + K341 ₮2.08M; MIAT 13 Nov + K341 ₮2.10M; Hunnu Erenhot ₮2.14M; Manzhouli seats ₮2.27M (sleep OK); Hohhot red-eye ₮2.34M (WATCH). Hohhot + Spring (Air China CA758 + Spring 9C6782, two tickets, no night train, BEST) ₮6.56M / ₮8.46M, ₮2.59M per person – ₮0.11M less than Sleep value (27 Oct: Spring ¥220 fare + ¥140 airport fee and fuel surcharge; 20 kg bag +¥120). All others are POOR for sleep: a seated night right before day 1.
A52: Regional – Shanghai (5–6 Dec) | B52: Sleeper: MIAT $151 + G17 out on 3 Dec, 2 cheap rooms 3 nights at Hi Inn (1.8 km, 8.9), D8 overnight seat back, Air China 12:55 $172 on 7 Dec: ₮7.15M / ₮9.23M. Spring nonstop with the same cheap rooms (Tue 1 → Tue 8 Dec, 7 nights) ₮7.50M / ₮9.48M (was ₮8.21M / ₮10.73M with the apartment); 'Fly out, train home' (Spring out, D10 seat ¥294 after the awards, Air China 7 Dec, no hotel nights after the contest) ₮7.27M / ₮9.28M. Wildcard: email shu_icpc@163.com now.
A53: Regional – Nanchang (19–20 Dec) | B53: Sleeper: Air China $157 + Z111 hard sleeper (arrive 11:52 on 18 Dec), Orange Hotel 2 nights, D136 seat back, Air China 12:55 $172. Comfort (daytime G-train, 3 hotel nights) ₮7.96M / ₮10.32M; Fly in (Air China through ticket $356) ₮8.41M / ₮10.95M.
A54: Regional – Hong Kong (9–10 Jan) | B54: MIAT nonstop ($586 return on Trip.com, low against the usual $708–900) is the cheapest way in; flights are ₮8.4M of the 4-person cost. With sleep prioritised over distance: Sleep priority (Good Fortune Inn, 4 twin beds, ~35–40 min MTR) ₮9.14M / ₮12.47M, Funded 12M (BW Plus, 2 rooms, walk to HKU) ₮9.35M / ₮12.87M, Budget guesthouse ₮9.08M / ₮12.12M, Value (Kusa Inn 9.6) ₮9.08M / ₮12.38M, Sleep first (2 rooms in Sheung Wan) ₮11.63M / ₮14.45M (3 / 4 ppl). No route or date is cheaper (checked 10 Oct).
A55: EC Final (only if qualified) | B55: Train: MIAT to Beijing, D17 overnight sleeper Beijing 19:10 → Hangzhou 09:15 (¥491), Air China through ticket Hangzhou → UB on 29 Jan: ₮11.12M (fits, ₮0.88M left) for 4 ppl, ₮3.14M per person for 3. Fly (Aero Mongolia + Xiamen via Hohhot) is ₮14.82M (over by ₮2.82M) – does not fit ₮12M. Buy D17 on 12306 at 10:00 on 11 Jan.
A57: Note | B57: Dates are provisional (ICPC Beijing HQ summary, 5 Aug 2026). Hong Kong host (HKU) and EC Final venue (HZNU Cangqian) are from secondary sources; Shanghai (Shanghai University Baoshan) follows the 2025 invitation and Nanchang (Jiangxi Normal University Yaohu campus) the 2019 handbook – confirm each invitation.
A58: Note | B58: EC Final is qualification-only: plan it only once the team has earned a slot at a regional.
A59: Note | B59: 4-person plans use whatever split is cheapest on Trip.com/Booking.com: one family room for 4 (Shenyang RiCH, Nanchang Orange Hotel), or two rooms. Taxi costs assume one car; with luggage 4 people may need an XL car.
A60: Note | B60: Sleep rule (see the 'Sleep check' sheet): the two nights before each contest day are in a quiet bed near the venue; sleepers, early flights and red-eyes are only used before day 1 (soft sleeper) or after the contest (anything goes). Sleeper trains replace hotel nights in the Shenyang, Shanghai (D8 seat), Nanchang (Z111 / D136 seat) and EC Final (D17) plans; the 'G-train' / 'no sleeper' variants cost more per trip. Chinese train tickets go on sale 14 days ahead – dates are in the '12306 & ChinaTicketOnline' and '10 Oct' sheets of the fares workbook.
A61: Note | B61: Sources (10 Oct): Trip.com (flights and hotels, built-in browser), 12306 (official train fares), ChinaTicketOnline (timetable and sale-date check; 30–70% dearer than 12306, not used for booking), SlickTrip (MIAT / Spring fares; by 22 Oct it prices Air China, but $90–180 above Trip.com), UBTZ e-ticket (Zamyn-Uud → Ulaanbaatar train, 22 Oct), Ctrip / Kiwi / Google Flights (22 Oct cross-check of the Shenyang flights; Ctrip had the cheapest Air China fare).

Sheet Sleep check
A1: Sleep check – protect the nights before the contest, spend nothing on comfort after it
A2: Rules used: (1) the two nights before the contest day are in a real bed, quiet, ≤30 min from the venue, ≥7.5 h in bed and no wake-up before ~06:00 on contest morning; (2) no overnight train or flight on the contest eve; a sleeper before day 1 only if it is a soft sleeper that arrives by midday and there is a bed night in between; (3) flights before 08:00 only ≥2 nights before the contest; (4) after the contest anything goes – hard sleepers, seats, red-eye trains, 04:30 airport runs – so the cheapest option is used. No time-zone effect: Mongolia, China and Hong Kong are all UTC+8.
A4: Plan | B4: Contest day / day 1 | C4: Night −3 | D4: Night −2 (before day 1) | E4: Night −1 (contest eve) | F4: Contest morning | G4: Verdict | H4: Sleep fix / what changed
A5: Shenyang – Comfort | B5: Sun 15 Nov / Sat 14 Nov | C5: 12 Nov RiCH hotel (after a 04:30 start for MIAT 07:30; nap in the afternoon) | D5: 13 Nov RiCH, free rest day | E5: 14 Nov RiCH, family room, quiet | F5: Walk 18 min, wake ~07:00 | G5: BEST | H5: Sleeper K54 is after the contest, so it is now a hard sleeper (soft was ¥263): saves ~₮0.16M (₮6.2M total).
A6: Shenyang – Budget | B6: Sun 15 Nov / Sat 14 Nov | C6: 12 Nov at home | D6: 13 Nov K53 soft sleeper 22:35–07:00 (was hard): ~5–6 h, then day-1 registration | E6: 14 Nov Bestay hotel (8.2, budget chain) | F6: Metro 25 min, wake ~06:30 | G6: WATCH | H6: K53 is the night before day 1, so it is now a soft sleeper (+¥92 pp, +₮0.16M; ₮5.2M total). Nap on arrival; the contest eve is in a bed. Safer: Comfort or either G-train variant.
A7: Shenyang – Comfort (G-train) | B7: Sun 15 Nov / Sat 14 Nov | C7: 12 Nov RiCH hotel | D7: 13 Nov RiCH | E7: 14 Nov RiCH | F7: Walk 18 min, wake ~07:00 | G7: BEST | H7: All beds before the contest; the Beijing hotel night (Dequan) is after it. +0.5M vs the sleeper plan.
A8: Shenyang – Budget (G-train) | B8: Sun 15 Nov / Sat 14 Nov | C8: 12 Nov at home | D8: 13 Nov Dequan hotel Beijing, wake 05:45 for G101 08:00 (~6.5 h) | E8: 14 Nov Bestay hotel | F8: Metro 25 min, wake ~06:30 | G8: OK | H8: Two nights in beds; one early wake two nights before the contest. Cheapest plan with no sleeper before the contest.
A9: Shenyang – Sleep first | B9: Sun 15 Nov / Sat 14 Nov | C9: 12 Nov NEU International (normal wake-up ~08:00 for Air China 11:50; bed ~23:00) | D9: 13 Nov same room, free rest day, no alarm | E9: 14 Nov same room, twin room, 580 m | F9: Walk 7 min, wake ~07:00 | G9: BEST | H9: No alarm before ~08:00 on any day before the contest (Air China 11:50 instead of MIAT 07:30, ¥195 ≈ ₮0.10M pp more on Ctrip), three nights in the same room and a bed each (2 twin rooms, 38 m², 9.7). After the contest the cheapest: K28 hard seat + Air China 12:55. ₮2.89M per person (3 ppl).
A10: Shenyang – Sleep value | B10: Sun 15 Nov / Sat 14 Nov | C10: 12 Nov Ji Hotel (normal wake-up ~08:00 for Air China 11:50; bed ~23:00) | D10: 13 Nov same room, free rest day, no alarm | E10: 14 Nov same room, twin room, ~15 min walk | F10: Walk ~15 min, wake ~06:50 | G10: BEST | H10: Same timing and a bed each (2 twin rooms, King Koil mattresses, 9.0); smaller rooms and a ~15 min walk. ₮2.69M per person – ₮0.20M less than Sleep first.
A11: Shenyang – Overland home | B11: Sun 15 Nov / Sat 14 Nov | C11: 12 Nov Ji Hotel (normal wake-up ~08:00 for Air China 11:50; bed ~23:00) | D11: 13 Nov same room, free rest day, no alarm | E11: 14 Nov same room, twin room, ~15 min walk | F11: Walk ~15 min, wake ~06:50 | G11: BEST | H11: Identical to Sleep value before the contest. After it: K1568 + 4652 hard sleepers, jeep across the border at Erenhot, UBTZ 275 platskart, home 18 Nov 09:20. ₮2.37M per person – the cheapest Shenyang plan without an early start or a sleeper before the contest.
A12: Shenyang – Overland out (seats) | B12: Sun 15 Nov / Sat 14 Nov | C12: 12 Nov UBTZ 276 seat | D12: 13 Nov T301 hard seat 19:30–10:16, then registration | E12: 14 Nov Ji Hotel, twin room | F12: Walk ~15 min, wake ~06:50 | G12: POOR | H12: Two seated train nights back to back before day 1. Leaving on 10 Nov instead adds two hotel nights (~₮0.16M pp) and turns this into OK. Berths: see 'Overland out, berths'.
A13: Shenyang – Overland out, berths | B13: Sun 15 Nov / Sat 14 Nov | C13: 12 Nov UBTZ 276 platskart berth | D13: 13 Nov T301 hard sleeper, then registration | E13: 14 Nov Ji Hotel, twin room | F13: Walk ~15 min, wake ~06:50 | G13: POOR | H13: Lying down both nights, but still two train nights in a row before day 1. +₮0.09M pp over seats.
A14: Shenyang – Manzhouli seats | B14: Sun 15 Nov / Sat 14 Nov | C14: 12 Nov Ji Hotel (after a night sitting up on K7092; arrive 14:32) | D14: 13 Nov Ji Hotel, free rest day | E14: 14 Nov Ji Hotel, twin room | F14: Walk ~15 min, wake ~06:50 | G14: OK | H14: The seated night is four nights before the contest and three hotel nights follow. Soft sleeper on K7092 (+¥205 pp) makes it BEST.
A15: Shenyang – Hunnu Daxing + K341 | B15: Sun 15 Nov / Sat 14 Nov | C15: 12 Nov at home | D15: 13 Nov K341 hard seat 23:00–08:47, then registration | E15: 14 Nov Ji Hotel, twin room | F15: Walk ~15 min, wake ~06:50 | G15: POOR | H15: Seated night right before day 1. K341 hard sleeper (+¥82 pp) or K53 22:35 soft sleeper (¥263) brings it to WATCH.
... A36: Nanjing + Shenyang (older workbook A / B) | B36: Nanjing Sun 8 Nov; Shenyang Sun 15 Nov | C36: 6 Nov Beijing hotel after MIAT lands 19:30, wake ~06:00 for the G-train | D36: 7 Nov Nanjing hotel (A 1 km, B 15 min metro) | E36: Shenyang: Z366 sleeper 12 Nov → hotels 13 and 14 Nov | F36: Nanjing walk / Shenyang walk | G36: OK | H36: K54 home after the Shenyang contest is now a hard sleeper (soft was ¥263). Plan C (home between) uses K53 soft sleeper on 13 Nov = night before day 1 (WATCH).
A37: One regional is funded with ₮12M (coach travels, 4 people); the other is unfunded (3 contestants pay). The funded trip has little headroom (Hong Kong does not fit), and the unfunded trip pays for every hotel night, so protect sleep with timing and location first: arrive a day early only where it is cheap (Shenyang, Nanchang), pick the hotel closest to the venue, and take the cheap-but-bad options only after the contest.
A38: Where the money goes (use the headroom on sleep)
A39: One regional is funded with ₮12M (coach travels, 4 people); the other is unfunded (3 contestants pay). The funded trip has little headroom (Hong Kong does not fit), and the unfunded trip pays for every hotel night, so protect sleep with timing and location first: arrive a day early only where it is cheap (Shenyang, Nanchang), pick the hotel closest to the venue, and take the cheap-but-bad options only after the contest.
A40: Pre-contest upgrades applied: Shenyang Budget K53 hard → soft; Hong Kong Sleep first (2 rooms near HKU). Post-contest downgrades applied: Shenyang K54 soft → hard, Shanghai D8 sleeper → seat, Nanchang D136 sleeper → seat.
A41: Cheapest post-contest options if you want to go further: Nanchang Z182 20:01 → 08:46 hard seat (¥173.5 vs ¥271); Shanghai G808 17:25 is too early after the awards, so the D8 seat stays.
A42: Contest-day wake-up rule of thumb: bed by 22:30–23:00, up by 06:00–06:30 for a 09:00 start; avoid alcohol and late team dinners; no phone-based all-nighters on day 1.

Sheet Shenyang – Budget
A1: Shenyang – Budget
A2: Overnight sleeper trains Beijing ⇄ Shenyang (no Beijing hotel nights), budget room, one night in Shenyang.
A4: Days in destination (meals & local transport) | B4: 3 | C4: Evening 13 Nov → midday 16 Nov
A5: Shared inputs are on the Compare sheet. Scroll down for the day-by-day plan and door-to-door travel times.
A7: Category | B7: Item | C7: Date | D7: Travel time | E7: Unit cost (3 ppl) | F7: Currency | G7: Qty (3 ppl) | H7: Total MNT – 3 people | I7: Unit cost (4 ppl) | J7: Qty (4 ppl) | K7: Total MNT – 4 people | L7: Source / notes
A8: PAID BY UNIVERSITY
A9: Flights
B10: MIAT OM223 Ulaanbaatar → Beijing (PEK), 17:15–19:30 | C10: 13 Nov | D10: 0.09375 | E10: 150 | F10: USD | G10: =Compare!$B$6 | H10: =E10*G10*IF(F10="USD",Compare!$B$8,IF(F10="CNY",Compare!$B$9,IF(F10="HKD",Compare!$B$10,1))) | I10: =E10 | J10: =Compare!$B$7 | K10: =I10*J10*IF(F10="USD",Compare!$B$8,IF(F10="CNY",Compare!$B$9,IF(F10="HKD",Compare!$B$10,1))) | L10: Trip.com 1 Oct: MIAT 17:15–19:30 $150 pp (SlickTrip 30 Sep: $154)
B11: Air China Beijing (PEK) → Ulaanbaatar, nonstop 12:55–15:05 | C11: 16 Nov | D11: 0.090277778 | E11: 171 | F11: USD | G11: =Compare!$B$6 | H11: =E11*G11*IF(F11="USD",Compare!$B$8,IF(F11="CNY",Compare!$B$9,IF(F11="HKD",Compare!$B$10,1))) | I11: =E11 | J11: =Compare!$B$7 | K11: =I11*J11*IF(F11="USD",Compare!$B$8,IF(F11="CNY",Compare!$B$9,IF(F11="HKD",Compare!$B$10,1))) | L11: Trip.com 30 Sep: Air China nonstop $171 pp (MIAT OM224 11:30 was $194 on Trip.com, $196.33 on SlickTrip)
A12: Trains
B13: Overnight train K53 Beijing 22:35 → Shenyang North 07:00, soft sleeper (4-berth cabin; night before day 1) | C13: 13 Nov (night) | D13: 0.35069444 | E13: 263 | F13: CNY | G13: =Compare!$B$6 | H13: =E13*G13*IF(F13="USD",Compare!$B$8,IF(F13="CNY",Compare!$B$9,IF(F13="HKD",Compare!$B$10,1))) | I13: =E13 | J13: =Compare!$B$7 | K13: =I13*J13*IF(F13="USD",Compare!$B$8,IF(F13="CNY",Compare!$B$9,IF(F13="HKD",Compare!$B$10,1))) | L13: Ctrip 1 Oct / 12306 3 Oct: K53 soft sleeper ¥263 (hard ¥171). Soft on purpose: it is the night before the day-1 warm-up, so sleep matters. Replaces the Beijing night + morning G-train (¥339). MIAT lands 19:30, so ~1 h 20 min spare; if MIAT is late, use the one free change to a 14 Nov G-train. Sales open 30 Oct 10:00.
B14: Overnight train K54 Shenyang North 22:00 → Beijing 06:58, hard sleeper | C14: 15 Nov (night) | D14: 0.37361111 | E14: 171 | F14: CNY | G14: =Compare!$B$6 | H14: =E14*G14*IF(F14="USD",Compare!$B$8,IF(F14="CNY",Compare!$B$9,IF(F14="HKD",Compare!$B$10,1))) | I14: =E14 | J14: =Compare!$B$7 | K14: =I14*J14*IF(F14="USD",Compare!$B$8,IF(F14="CNY",Compare!$B$9,IF(F14="HKD",Compare!$B$10,1))) | L14: Ctrip 1 Oct: K54 hard sleeper ¥171, soft sleeper ¥263 (4-berth cabin). Leaves 22:00, so a late closing ceremony is fine; replaces the evening G-train (¥339) + a Beijing hotel night. Air China through ticket SHE 09:00 → UB 15:05 ($286) is the fallback. 12306 3 Oct: same official fares; sales open 1 Nov 09:00 (Shenyang North).
A15: Accommodation
B17: Bestay Hotel Express Shenyang (Huaiyuanmen; ~25 min metro to NEU Nanhu) | C17: 14 Nov (1 night) | E17: 86 | F17: CNY | G17: 1 | H17: =E17*G17*IF(F17="USD",Compare!$B$8,IF(F17="CNY",Compare!$B$9,IF(F17="HKD",Compare!$B$10,1))) | I17: 134 | J17: 1 | K17: =I17*J17*IF(F17="USD",Compare!$B$8,IF(F17="CNY",Compare!$B$9,IF(F17="HKD",Compare!$B$10,1))) | L17: Booking.com: 86/night (3 ppl, 1 room); 134 CNY for 2 rooms on 14 Nov.. Trip.com 1 Oct: rated 8.2 from 1,062 reviews (¥284 for 2 rooms × 2 nights) – the low price is real. Arrive 07:00 off the sleeper: leave bags until check-in
A19: Meals & local transport
B20: Meals | C20: in destination | E20: 80 | F20: CNY | G20: =Compare!$B$6*$B$4 | H20: =E20*G20*IF(F20="USD",Compare!$B$8,IF(F20="CNY",Compare!$B$9,IF(F20="HKD",Compare!$B$10,1))) | I20: =E20 | J20: =Compare!$B$7*$B$4 | K20: =I20*J20*IF(F20="USD",Compare!$B$8,IF(F20="CNY",Compare!$B$9,IF(F20="HKD",Compare!$B$10,1))) | L20: ASSUMPTION 80 CNY/person/day; hosts usually provide some meals on contest days
B21: Local transport (metro, taxis) | C21: in destination | E21: 30 | F21: CNY | G21: =Compare!$B$6*$B$4 | H21: =E21*G21*IF(F21="USD",Compare!$B$8,IF(F21="CNY",Compare!$B$9,IF(F21="HKD",Compare!$B$10,1))) | I21: =E21 | J21: =Compare!$B$7*$B$4 | K21: =I21*J21*IF(F21="USD",Compare!$B$8,IF(F21="CNY",Compare!$B$9,IF(F21="HKD",Compare!$B$10,1))) | L21: ASSUMPTION 30 CNY/person/day
A22: PAID PERSONALLY (university won't cover)
A23: Contest fee
B24: Shenyang regional registration fee (per team) | C24: pay by mid-Oct | E24: 1500 | F24: CNY | G24: 1 | H24: =E24*G24*IF(F24="USD",Compare!$B$8,IF(F24="CNY",Compare!$B$9,IF(F24="HKD",Compare!$B$10,1))) | I24: =E24 | J24: 1 | K24: =I24*J24*IF(F24="USD",Compare!$B$8,IF(F24="CNY",Compare!$B$9,IF(F24="HKD",Compare!$B$10,1))) | L24: ASSUMPTION: 1,500 CNY/team like recent EC regionals; 2026 Shenyang invitation not yet out
A25: Other
B26: Taxi to/from Chinggis Khaan airport (UB), per trip | C26: out & back | D26: 0.041666667 | E26: 100000 | F26: MNT | G26: 2 | H26: =E26*G26*IF(F26="USD",Compare!$B$8,IF(F26="CNY",Compare!$B$9,IF(F26="HKD",Compare!$B$10,1))) | I26: =E26 | J26: 2 | K26: =I26*J26*IF(F26="USD",Compare!$B$8,IF(F26="CNY",Compare!$B$9,IF(F26="HKD",Compare!$B$10,1))) | L26: ASSUMPTION 100k MNT per trip for the group
B27: Travel medical insurance | E27: 30000 | F27: MNT | G27: =Compare!$B$6 | H27: =E27*G27*IF(F27="USD",Compare!$B$8,IF(F27="CNY",Compare!$B$9,IF(F27="HKD",Compare!$B$10,1))) | I27: =E27 | J27: =Compare!$B$7 | K27: =I27*J27*IF(F27="USD",Compare!$B$8,IF(F27="CNY",Compare!$B$9,IF(F27="HKD",Compare!$B$10,1))) | L27: ASSUMPTION ~30k MNT per person, Mongolian insurer
B28: Mobile data eSIM | E28: 10 | F28: USD | G28: =Compare!$B$6 | H28: =E28*G28*IF(F28="USD",Compare!$B$8,IF(F28="CNY",Compare!$B$9,IF(F28="HKD",Compare!$B$10,1))) | I28: =E28 | J28: =Compare!$B$7 | K28: =I28*J28*IF(F28="USD",Compare!$B$8,IF(F28="CNY",Compare!$B$9,IF(F28="HKD",Compare!$B$10,1))) | L28: ASSUMPTION ~$10 pp
B29: Visa | E29: 0 | F29: MNT | G29: =Compare!$B$6 | H29: =E29*G29*IF(F29="USD",Compare!$B$8,IF(F29="CNY",Compare!$B$9,IF(F29="HKD",Compare!$B$10,1))) | I29: =E29 | J29: =Compare!$B$7 | K29: =I29*J29*IF(F29="USD",Compare!$B$8,IF(F29="CNY",Compare!$B$9,IF(F29="HKD",Compare!$B$10,1))) | L29: Mongolian passports: visa-free (mainland China up to 30 days; Hong Kong up to 14 days)
H31: 3 people – UNFUNDED | K31: 4 people – FUNDED ₮12M
G32: University-paid subtotal | H32: =SUM(H9:H21) | K32: =SUM(K9:K21)
G33: Contingency | H33: =H32*Compare!$B$11 | K33: =K32*Compare!$B$11
G34: University-paid total incl. contingency | H34: =H32+H33 | K34: =K32+K33
G35: Funding left (negative = over) | H35: =Compare!$B$12-H34 | K35: =Compare!$B$5-K34
G36: Personal costs – team | H36: =SUM(H23:H29) | K36: =SUM(K23:K29)
G37: Out-of-pocket per person (personal + any overrun) | H37: =(H36+MAX(0,-H35))/Compare!$B$6 | K37: =(K36+MAX(0,-K35))/Compare!$B$7
G38: Whole trip cost (university + personal) | H38: =H34+H36 | K38: =K34+K36
G39: Time in planes & trains | H39: =SUM(D10:D11)+SUM(D13:D14) | K39: =SUM(D10:D11)+SUM(D13:D14)
A41: Key facts
A42: Contest | B42: Asia Shenyang Regional, 14–15 Nov 2026 (provisional), Northeastern University – 2025 edition was on the Nanhu campus.
A43: Why this route | B43: Cheapest way from UB: MIAT to Beijing ($150) + overnight sleeper trains (¥171 each way, no Beijing hotel), Air China home ($171). Flying UB→Shenyang direct means an overnight in Seoul (~$514 pp one way) or a 1-stop via Beijing/Hohhot ($219–233, 8–15 h).
A44: Trade-off | B44: Two nights on sleeper trains (6-berth hard sleeper); very basic room; ~25 min metro to the venue.
A46: Day-by-day plan
A47: Date | B47: Sleep in | C47: What happens
A48: Fri 13 Nov | B48: Train | C48: Fly MIAT OM223 UB 17:15 → Beijing Capital 19:30. Airport Express + metro to Beijing station; K53 soft sleeper 22:35 → Shenyang North 07:00.
A49: Sat 14 Nov | B49: Shenyang | C49: Arrive Shenyang North 07:00; leave bags at Bestay. Registration & practice at Northeastern University Nanhu campus.
A50: Sun 15 Nov | B50: Train | C50: SHENYANG REGIONAL contest day. K54 sleeper Shenyang North 22:00 → Beijing 06:58 (no rush after the closing ceremony).
A51: Mon 16 Nov | B51: Home | C51: Beijing station → PEK by metro + Airport Express. Air China Beijing Capital 12:55 → UB 15:05 (nonstop).
A53: Door-to-door travel times
A54: Date | B54: Leg | C54: Mode | D54: Expected time | E54: Notes
A55: 13 Nov | B55: Home → Chinggis Khaan airport | C55: Taxi (~50 km) | D55: 0.041666667 | E55: Leave ~14:15
A56: 13 Nov | B56: Ulaanbaatar → Beijing (PEK) | C56: MIAT OM223 17:15–19:30 | D56: 0.09375
A57: 13 Nov | B57: PEK arrival: immigration, bags | C57: — | D57: 0.03125 | E57: Estimate
A58: 13 Nov | B58: PEK → Beijing station | C58: Airport Express + metro line 2 | D58: 0.041666667 | E58: Aim to be there by ~21:30
A59: 13–14 Nov | B59: Beijing → Shenyang North | C59: K53 soft sleeper 22:35–07:00 | D59: 0.35069444 | E59: Overnight
A60: 14 Nov | B60: Shenyang North → Bestay hotel / NEU Nanhu | C60: Metro / taxi | D60: 0.017361111 | E60: Estimate
A61: 14–15 Nov | B61: Bestay hotel ↔ NEU Nanhu (each way) | C61: Metro | D61: daily | E61: ~25 min
A62: 15 Nov | B62: NEU Nanhu → Shenyang North | C62: Taxi | D62: 0.017361111 | E62: Estimate
A63: 15–16 Nov | B63: Shenyang North → Beijing | C63: K54 hard sleeper 22:00–06:58 | D63: 0.37361111 | E63: Overnight
A64: 16 Nov | B64: Beijing station → PEK | C64: Metro line 2 + Airport Express | D64: 0.041666667 | E64: Be at PEK by ~10:55
A65: 16 Nov | B65: Beijing (PEK) → Ulaanbaatar | C65: Air China 12:55–15:05 | D65: 0.090277778
A66: 16 Nov | B66: Chinggis Khaan airport → home | C66: Taxi | D66: 0.041666667
C69: Total door-to-door | D69: =SUM(D55:D68)

Sheet Shenyang – Comfort
A1: Shenyang – Comfort
A2: Arrive a day early for rest, family room near the venue, MIAT + fast train out, overnight soft sleeper back to Beijing.
A4: Days in destination (meals & local transport) | B4: 4.5 | C4: 12 Nov morning → midday 16 Nov
A5: Shared inputs are on the Compare sheet. Scroll down for the day-by-day plan and door-to-door travel times.
A7: Category | B7: Item | C7: Date | D7: Travel time | E7: Unit cost (3 ppl) | F7: Currency | G7: Qty (3 ppl) | H7: Total MNT – 3 people | I7: Unit cost (4 ppl) | J7: Qty (4 ppl) | K7: Total MNT – 4 people | L7: Source / notes
A8: PAID BY UNIVERSITY
A9: Flights
B10: MIAT OM223 Ulaanbaatar → Beijing (PEK), 07:30–09:45 | C10: 12 Nov | D10: 0.09375 | E10: 151 | F10: USD | G10: =Compare!$B$6 | H10: =E10*G10*IF(F10="USD",Compare!$B$8,IF(F10="CNY",Compare!$B$9,IF(F10="HKD",Compare!$B$10,1))) | I10: =E10 | J10: =Compare!$B$7 | K10: =I10*J10*IF(F10="USD",Compare!$B$8,IF(F10="CNY",Compare!$B$9,IF(F10="HKD",Compare!$B$10,1))) | L10: Trip.com 30 Sep: MIAT 07:30–09:45 $151 pp (SlickTrip 30 Sep: $154)
B11: Air China Beijing (PEK) → Ulaanbaatar, nonstop 12:55–15:05 | C11: 16 Nov | D11: 0.090277778 | E11: 171 | F11: USD | G11: =Compare!$B$6 | H11: =E11*G11*IF(F11="USD",Compare!$B$8,IF(F11="CNY",Compare!$B$9,IF(F11="HKD",Compare!$B$10,1))) | I11: =E11 | J11: =Compare!$B$7 | K11: =I11*J11*IF(F11="USD",Compare!$B$8,IF(F11="CNY",Compare!$B$9,IF(F11="HKD",Compare!$B$10,1))) | L11: Trip.com 30 Sep: Air China nonstop $171 pp (MIAT OM224 11:30 was $194 on Trip.com, $196.33 on SlickTrip)
A12: Trains
B13: High-speed rail Beijing Chaoyang → Shenyang North, 2nd class | C13: 12 Nov (midday) | D13: 0.11388889 | E13: 339 | F13: CNY | G13: =Compare!$B$6 | H13: =E13*G13*IF(F13="USD",Compare!$B$8,IF(F13="CNY",Compare!$B$9,IF(F13="HKD",Compare!$B$10,1))) | I13: =E13 | J13: =Compare!$B$7 | K13: =I13*J13*IF(F13="USD",Compare!$B$8,IF(F13="CNY",Compare!$B$9,IF(F13="HKD",Compare!$B$10,1))) | L13: 12306: 339 CNY; fastest 2 h 44 min
B14: Overnight train K54 Shenyang North 22:00 → Beijing 06:58, hard sleeper (after the contest) | C14: 15 Nov (night) | D14: 0.37361111 | E14: 171 | F14: CNY | G14: =Compare!$B$6 | H14: =E14*G14*IF(F14="USD",Compare!$B$8,IF(F14="CNY",Compare!$B$9,IF(F14="HKD",Compare!$B$10,1))) | I14: =E14 | J14: =Compare!$B$7 | K14: =I14*J14*IF(F14="USD",Compare!$B$8,IF(F14="CNY",Compare!$B$9,IF(F14="HKD",Compare!$B$10,1))) | L14: Ctrip 1 Oct / 12306 3 Oct: K54 hard sleeper ¥171 (soft ¥263). Hard on purpose: it is after the contest, so sleep no longer matters (saves ¥92 pp). Leaves 22:00, so a late closing ceremony is fine; replaces the evening G-train (¥339) + a Beijing hotel night. Air China through ticket SHE 09:00 → UB 15:05 ($286) is the fallback. Sales open 1 Nov 09:00.
A15: Accommodation
B16: Shenyang RiCH Hotel, Sanhao St (~1.3 km to NEU Nanhu; Family Room sleeps 4, so one room for 3 or 4 ppl) | C16: 12–15 Nov (3 nights) | E16: 325.33 | F16: CNY | G16: 3 | H16: =E16*G16*IF(F16="USD",Compare!$B$8,IF(F16="CNY",Compare!$B$9,IF(F16="HKD",Compare!$B$10,1))) | I16: 325.33 | J16: 3 | K16: =I16*J16*IF(F16="USD",Compare!$B$8,IF(F16="CNY",Compare!$B$9,IF(F16="HKD",Compare!$B$10,1))) | L16: Trip.com 1 Oct: Family Room ¥976 for 3 nights, same price for 3 or 4 adults; rated 9.6 (1,802 reviews). Was Atour ¥527/night (3 ppl) / Mehood Lestie ¥718 (4 ppl, 2 rooms) on Booking.com
A18: Meals & local transport
B19: Meals | C19: in destination | E19: 80 | F19: CNY | G19: =Compare!$B$6*$B$4 | H19: =E19*G19*IF(F19="USD",Compare!$B$8,IF(F19="CNY",Compare!$B$9,IF(F19="HKD",Compare!$B$10,1))) | I19: =E19 | J19: =Compare!$B$7*$B$4 | K19: =I19*J19*IF(F19="USD",Compare!$B$8,IF(F19="CNY",Compare!$B$9,IF(F19="HKD",Compare!$B$10,1))) | L19: ASSUMPTION 80 CNY/person/day; hosts usually provide some meals on contest days
B20: Local transport (metro, taxis) | C20: in destination | E20: 30 | F20: CNY | G20: =Compare!$B$6*$B$4 | H20: =E20*G20*IF(F20="USD",Compare!$B$8,IF(F20="CNY",Compare!$B$9,IF(F20="HKD",Compare!$B$10,1))) | I20: =E20 | J20: =Compare!$B$7*$B$4 | K20: =I20*J20*IF(F20="USD",Compare!$B$8,IF(F20="CNY",Compare!$B$9,IF(F20="HKD",Compare!$B$10,1))) | L20: ASSUMPTION 30 CNY/person/day
A21: PAID PERSONALLY (university won't cover)
A22: Contest fee
B23: Shenyang regional registration fee (per team) | C23: pay by mid-Oct | E23: 1500 | F23: CNY | G23: 1 | H23: =E23*G23*IF(F23="USD",Compare!$B$8,IF(F23="CNY",Compare!$B$9,IF(F23="HKD",Compare!$B$10,1))) | I23: =E23 | J23: 1 | K23: =I23*J23*IF(F23="USD",Compare!$B$8,IF(F23="CNY",Compare!$B$9,IF(F23="HKD",Compare!$B$10,1))) | L23: ASSUMPTION: 1,500 CNY/team like recent EC regionals; 2026 Shenyang invitation not yet out
A24: Other
B25: Taxi to/from Chinggis Khaan airport (UB), per trip | C25: out & back | D25: 0.041666667 | E25: 100000 | F25: MNT | G25: 2 | H25: =E25*G25*IF(F25="USD",Compare!$B$8,IF(F25="CNY",Compare!$B$9,IF(F25="HKD",Compare!$B$10,1))) | I25: =E25 | J25: 2 | K25: =I25*J25*IF(F25="USD",Compare!$B$8,IF(F25="CNY",Compare!$B$9,IF(F25="HKD",Compare!$B$10,1))) | L25: ASSUMPTION 100k MNT per trip for the group
B26: Travel medical insurance | E26: 30000 | F26: MNT | G26: =Compare!$B$6 | H26: =E26*G26*IF(F26="USD",Compare!$B$8,IF(F26="CNY",Compare!$B$9,IF(F26="HKD",Compare!$B$10,1))) | I26: =E26 | J26: =Compare!$B$7 | K26: =I26*J26*IF(F26="USD",Compare!$B$8,IF(F26="CNY",Compare!$B$9,IF(F26="HKD",Compare!$B$10,1))) | L26: ASSUMPTION ~30k MNT per person, Mongolian insurer
B27: Mobile data eSIM | E27: 10 | F27: USD | G27: =Compare!$B$6 | H27: =E27*G27*IF(F27="USD",Compare!$B$8,IF(F27="CNY",Compare!$B$9,IF(F27="HKD",Compare!$B$10,1))) | I27: =E27 | J27: =Compare!$B$7 | K27: =I27*J27*IF(F27="USD",Compare!$B$8,IF(F27="CNY",Compare!$B$9,IF(F27="HKD",Compare!$B$10,1))) | L27: ASSUMPTION ~$10 pp
B28: Visa | E28: 0 | F28: MNT | G28: =Compare!$B$6 | H28: =E28*G28*IF(F28="USD",Compare!$B$8,IF(F28="CNY",Compare!$B$9,IF(F28="HKD",Compare!$B$10,1))) | I28: =E28 | J28: =Compare!$B$7 | K28: =I28*J28*IF(F28="USD",Compare!$B$8,IF(F28="CNY",Compare!$B$9,IF(F28="HKD",Compare!$B$10,1))) | L28: Mongolian passports: visa-free (mainland China up to 30 days; Hong Kong up to 14 days)
H30: 3 people – UNFUNDED | K30: 4 people – FUNDED ₮12M
G31: University-paid subtotal | H31: =SUM(H9:H20) | K31: =SUM(K9:K20)
G32: Contingency | H32: =H31*Compare!$B$11 | K32: =K31*Compare!$B$11
G33: University-paid total incl. contingency | H33: =H31+H32 | K33: =K31+K32
G34: Funding left (negative = over) | H34: =Compare!$B$12-H33 | K34: =Compare!$B$5-K33
G35: Personal costs – team | H35: =SUM(H22:H28) | K35: =SUM(K22:K28)
G36: Out-of-pocket per person (personal + any overrun) | H36: =(H35+MAX(0,-H34))/Compare!$B$6 | K36: =(K35+MAX(0,-K34))/Compare!$B$7
G37: Whole trip cost (university + personal) | H37: =H33+H35 | K37: =K33+K35
G38: Time in planes & trains | H38: =SUM(D10:D11)+SUM(D13:D14) | K38: =SUM(D10:D11)+SUM(D13:D14)
A40: Key facts
A41: Contest | B41: Asia Shenyang Regional, 14–15 Nov 2026 (provisional), Northeastern University Nanhu campus (2025 venue).
A42: Why this plan | B42: A full rest day before registration, hotel close to the venue, same cheap MIAT + rail route.
A43: Trade-off | B43: Two extra hotel nights and meals; very early flight from UB on 12 Nov; one night on the train back.
A45: Day-by-day plan
A46: Date | B46: Sleep in | C46: What happens
A47: Thu 12 Nov | B47: Shenyang | C47: MIAT OM223 UB 07:30 → Beijing 09:45; G-train Beijing Chaoyang → Shenyang North (~12:30 → ~15:15). RiCH Hotel near NEU.
A48: Fri 13 Nov | B48: Shenyang | C48: Rest / practice day in Shenyang.
A49: Sat 14 Nov | B49: Shenyang | C49: Registration & practice at NEU Nanhu (walkable from hotel).
A50: Sun 15 Nov | B50: Train | C50: SHENYANG REGIONAL contest day. K54 hard sleeper Shenyang North 22:00 → Beijing 06:58.
A51: Mon 16 Nov | B51: Home | C51: Beijing station → PEK by metro + Airport Express. Air China Beijing Capital 12:55 → UB 15:05 (nonstop).
A53: Door-to-door travel times
A54: Date | B54: Leg | C54: Mode | D54: Expected time | E54: Notes
A55: 12 Nov | B55: Home → Chinggis Khaan airport | C55: Taxi (~50 km) | D55: 0.041666667 | E55: Leave ~04:30 for 07:30 flight
A56: 12 Nov | B56: Ulaanbaatar → Beijing (PEK) | C56: MIAT OM223 07:30–09:45 | D56: 0.09375
A57: 12 Nov | B57: PEK arrival: immigration, bags | C57: — | D57: 0.03125 | E57: Estimate
A58: 12 Nov | B58: PEK → Beijing Chaoyang station | C58: Taxi (~20 km) | D58: 0.027777778 | E58: Estimate
A59: 12 Nov | B59: Beijing Chaoyang → Shenyang North | C59: G-train 2nd class | D59: 0.11388889
A60: 12 Nov | B60: Shenyang North → hotel near NEU | C60: Taxi | D60: 0.017361111 | E60: Estimate
A61: 13–15 Nov | B61: Hotel ↔ NEU Nanhu (each way) | C61: Walk | D61: daily | E61: ~18 min walk (RiCH Hotel, 1.3 km)
A62: 15 Nov | B62: NEU Nanhu → Shenyang North | C62: Taxi | D62: 0.017361111
A63: 15–16 Nov | B63: Shenyang North → Beijing | C63: K54 hard sleeper 22:00–06:58 | D63: 0.37361111 | E63: Overnight
A64: 16 Nov | B64: Beijing station → PEK | C64: Metro line 2 + Airport Express | D64: 0.041666667 | E64: Be at PEK by ~10:55
A65: 16 Nov | B65: Beijing (PEK) → Ulaanbaatar | C65: Air China 12:55–15:05 | D65: 0.090277778
A66: 16 Nov | B66: Chinggis Khaan airport → home | C66: Taxi | D66: 0.041666667
C68: Total door-to-door | D68: =SUM(D55:D67)

Sheet Shenyang – Budget (G-train)
A1: Shenyang – Budget (G-train)
A2: No sleeper trains: MIAT in the evening, Beijing hotel night, morning G-train, cheap budget hotel, evening G-train back and another Beijing night.
A4: Days in destination (meals & local transport) | B4: 3 | C4: Evening 13 Nov → midday 16 Nov
A5: Shared inputs are on the Compare sheet. Scroll down for the day-by-day plan and door-to-door travel times.
A7: Category | B7: Item | C7: Date | D7: Travel time | E7: Unit cost (3 ppl) | F7: Currency | G7: Qty (3 ppl) | H7: Total MNT – 3 people | I7: Unit cost (4 ppl) | J7: Qty (4 ppl) | K7: Total MNT – 4 people | L7: Source / notes
A8: PAID BY UNIVERSITY
A9: Flights
B10: MIAT OM223 Ulaanbaatar → Beijing (PEK), 17:15–19:30 | C10: 13 Nov | D10: 0.09375 | E10: 150 | F10: USD | G10: =Compare!$B$6 | H10: =E10*G10*IF(F10="USD",Compare!$B$8,IF(F10="CNY",Compare!$B$9,IF(F10="HKD",Compare!$B$10,1))) | I10: =E10 | J10: =Compare!$B$7 | K10: =I10*J10*IF(F10="USD",Compare!$B$8,IF(F10="CNY",Compare!$B$9,IF(F10="HKD",Compare!$B$10,1))) | L10: Trip.com 1 Oct: MIAT 17:15–19:30 $150 pp (SlickTrip 30 Sep: $154)
B11: Air China Beijing (PEK) → Ulaanbaatar, nonstop 12:55–15:05 | C11: 16 Nov | D11: 0.090277778 | E11: 171 | F11: USD | G11: =Compare!$B$6 | H11: =E11*G11*IF(F11="USD",Compare!$B$8,IF(F11="CNY",Compare!$B$9,IF(F11="HKD",Compare!$B$10,1))) | I11: =E11 | J11: =Compare!$B$7 | K11: =I11*J11*IF(F11="USD",Compare!$B$8,IF(F11="CNY",Compare!$B$9,IF(F11="HKD",Compare!$B$10,1))) | L11: Trip.com 30 Sep: Air China nonstop $171 pp (MIAT OM224 11:30 was $194 on Trip.com, $196.33 on SlickTrip)
A12: Trains
B13: High-speed rail Beijing Chaoyang 08:00 → Shenyang North 10:29 (G101), 2nd class | C13: 14 Nov (morning) | D13: 0.10347222 | E13: 355 | F13: CNY | G13: =Compare!$B$6 | H13: =E13*G13*IF(F13="USD",Compare!$B$8,IF(F13="CNY",Compare!$B$9,IF(F13="HKD",Compare!$B$10,1))) | I13: =E13 | J13: =Compare!$B$7 | K13: =I13*J13*IF(F13="USD",Compare!$B$8,IF(F13="CNY",Compare!$B$9,IF(F13="HKD",Compare!$B$10,1))) | L13: 12306 (queried 10 Oct for 20 Oct; fares fixed): G101 / G103 08:05 / G105 08:55 ¥355; slower G3503 08:25 → 11:56 ¥296
B14: High-speed rail Shenyang North 19:51 → Beijing Chaoyang 22:30 (G142), 2nd class | C14: 15 Nov (evening) | D14: 0.11041667 | E14: 268 | F14: CNY | G14: =Compare!$B$6 | H14: =E14*G14*IF(F14="USD",Compare!$B$8,IF(F14="CNY",Compare!$B$9,IF(F14="HKD",Compare!$B$10,1))) | I14: =E14 | J14: =Compare!$B$7 | K14: =I14*J14*IF(F14="USD",Compare!$B$8,IF(F14="CNY",Compare!$B$9,IF(F14="HKD",Compare!$B$10,1))) | L14: 12306 (queried 10 Oct for 20 Oct; fares fixed): G142 / G156 (Shenyang stn 19:05) / G3522 19:21 → 22:36 ¥268; G122 / G126 ¥344. Awards end ~17:00, so 19:51 leaves a safe margin
A15: Accommodation
B16: Dequan Railway Station Hotel, Beijing (~1 km from Beijing Chaoyang station; 3 ppl 1 room; 4 ppl 2 rooms) | C16: 13 & 15 Nov (2 nights) | E16: 304 | F16: CNY | G16: 2 | H16: =E16*G16*IF(F16="USD",Compare!$B$8,IF(F16="CNY",Compare!$B$9,IF(F16="HKD",Compare!$B$10,1))) | I16: 608 | J16: 2 | K16: =I16*J16*IF(F16="USD",Compare!$B$8,IF(F16="CNY",Compare!$B$9,IF(F16="HKD",Compare!$B$10,1))) | L16: Booking.com 9 Oct: ¥304 for 3 adults, 1 room per night; rated 8.7 (65 reviews). 4 ppl: ASSUMPTION 2 × ¥304 (rooms not searched)
B17: Bestay Hotel Express Shenyang (Huaiyuanmen; ~25 min metro to NEU Nanhu) | C17: 14 Nov (1 night) | E17: 86 | F17: CNY | G17: 1 | H17: =E17*G17*IF(F17="USD",Compare!$B$8,IF(F17="CNY",Compare!$B$9,IF(F17="HKD",Compare!$B$10,1))) | I17: 134 | J17: 1 | K17: =I17*J17*IF(F17="USD",Compare!$B$8,IF(F17="CNY",Compare!$B$9,IF(F17="HKD",Compare!$B$10,1))) | L17: Booking.com: 86/night (3 ppl, 1 room); 134 CNY for 2 rooms on 14 Nov. Trip.com 1 Oct confirms the price (rated 8.2, 1,062 reviews)
A18: Meals & local transport
B19: Meals | C19: in destination | E19: 80 | F19: CNY | G19: =Compare!$B$6*$B$4 | H19: =E19*G19*IF(F19="USD",Compare!$B$8,IF(F19="CNY",Compare!$B$9,IF(F19="HKD",Compare!$B$10,1))) | I19: =E19 | J19: =Compare!$B$7*$B$4 | K19: =I19*J19*IF(F19="USD",Compare!$B$8,IF(F19="CNY",Compare!$B$9,IF(F19="HKD",Compare!$B$10,1))) | L19: ASSUMPTION 80 CNY/person/day; hosts usually provide some meals on contest days
B20: Local transport (metro, taxis) | C20: in destination | E20: 30 | F20: CNY | G20: =Compare!$B$6*$B$4 | H20: =E20*G20*IF(F20="USD",Compare!$B$8,IF(F20="CNY",Compare!$B$9,IF(F20="HKD",Compare!$B$10,1))) | I20: =E20 | J20: =Compare!$B$7*$B$4 | K20: =I20*J20*IF(F20="USD",Compare!$B$8,IF(F20="CNY",Compare!$B$9,IF(F20="HKD",Compare!$B$10,1))) | L20: ASSUMPTION 30 CNY/person/day
B21: Taxi PEK → Beijing Chaoyang area (Dequan hotel) | C21: 13 Nov | E21: 120 | F21: CNY | G21: 1 | H21: =E21*G21*IF(F21="USD",Compare!$B$8,IF(F21="CNY",Compare!$B$9,IF(F21="HKD",Compare!$B$10,1))) | I21: =E21 | J21: 1 | K21: =I21*J21*IF(F21="USD",Compare!$B$8,IF(F21="CNY",Compare!$B$9,IF(F21="HKD",Compare!$B$10,1))) | L21: ASSUMPTION ~120 CNY per car, ~35 km at night (4 ppl may need an XL car)
B22: Taxi Dequan hotel → PEK | C22: 16 Nov | E22: 120 | F22: CNY | G22: 1 | H22: =E22*G22*IF(F22="USD",Compare!$B$8,IF(F22="CNY",Compare!$B$9,IF(F22="HKD",Compare!$B$10,1))) | I22: =E22 | J22: 1 | K22: =I22*J22*IF(F22="USD",Compare!$B$8,IF(F22="CNY",Compare!$B$9,IF(F22="HKD",Compare!$B$10,1))) | L22: ASSUMPTION ~120 CNY per car, ~35 km, leave ~09:00
A23: PAID PERSONALLY (university won't cover)
A24: Contest fee
B25: Shenyang regional registration fee (per team) | C25: pay by mid-Oct | E25: 1500 | F25: CNY | G25: 1 | H25: =E25*G25*IF(F25="USD",Compare!$B$8,IF(F25="CNY",Compare!$B$9,IF(F25="HKD",Compare!$B$10,1))) | I25: =E25 | J25: 1 | K25: =I25*J25*IF(F25="USD",Compare!$B$8,IF(F25="CNY",Compare!$B$9,IF(F25="HKD",Compare!$B$10,1))) | L25: ASSUMPTION: 1,500 CNY/team like recent EC regionals; 2026 Shenyang invitation not seen
A26: Other
B27: Taxi to/from Chinggis Khaan airport (UB), per trip | C27: out & back | D27: 0.041666667 | E27: 100000 | F27: MNT | G27: 2 | H27: =E27*G27*IF(F27="USD",Compare!$B$8,IF(F27="CNY",Compare!$B$9,IF(F27="HKD",Compare!$B$10,1))) | I27: =E27 | J27: 2 | K27: =I27*J27*IF(F27="USD",Compare!$B$8,IF(F27="CNY",Compare!$B$9,IF(F27="HKD",Compare!$B$10,1))) | L27: ASSUMPTION 100k MNT per trip for the group
B28: Travel medical insurance | E28: 30000 | F28: MNT | G28: =Compare!$B$6 | H28: =E28*G28*IF(F28="USD",Compare!$B$8,IF(F28="CNY",Compare!$B$9,IF(F28="HKD",Compare!$B$10,1))) | I28: =E28 | J28: =Compare!$B$7 | K28: =I28*J28*IF(F28="USD",Compare!$B$8,IF(F28="CNY",Compare!$B$9,IF(F28="HKD",Compare!$B$10,1))) | L28: ASSUMPTION ~30k MNT per person, Mongolian insurer
B29: Mobile data eSIM | E29: 10 | F29: USD | G29: =Compare!$B$6 | H29: =E29*G29*IF(F29="USD",Compare!$B$8,IF(F29="CNY",Compare!$B$9,IF(F29="HKD",Compare!$B$10,1))) | I29: =E29 | J29: =Compare!$B$7 | K29: =I29*J29*IF(F29="USD",Compare!$B$8,IF(F29="CNY",Compare!$B$9,IF(F29="HKD",Compare!$B$10,1))) | L29: ASSUMPTION ~$10 pp
B30: Visa | E30: 0 | F30: MNT | G30: =Compare!$B$6 | H30: =E30*G30*IF(F30="USD",Compare!$B$8,IF(F30="CNY",Compare!$B$9,IF(F30="HKD",Compare!$B$10,1))) | I30: =E30 | J30: =Compare!$B$7 | K30: =I30*J30*IF(F30="USD",Compare!$B$8,IF(F30="CNY",Compare!$B$9,IF(F30="HKD",Compare!$B$10,1))) | L30: Mongolian passports: visa-free (mainland China up to 30 days; Hong Kong up to 14 days)
H32: 3 people – UNFUNDED | K32: 4 people – FUNDED ₮12M
G33: University-paid subtotal | H33: =SUM(H9:H22) | K33: =SUM(K9:K22)
G34: Contingency | H34: =H33*Compare!$B$11 | K34: =K33*Compare!$B$11
G35: University-paid total incl. contingency | H35: =H33+H34 | K35: =K33+K34
G36: Funding left (negative = over) | H36: =Compare!$B$12-H35 | K36: =Compare!$B$5-K35
G37: Personal costs – team | H37: =SUM(H24:H30) | K37: =SUM(K24:K30)
G38: Out-of-pocket per person (personal + any overrun) | H38: =(H37+MAX(0,-H36))/Compare!$B$6 | K38: =(K37+MAX(0,-K36))/Compare!$B$7
G39: Whole trip cost (university + personal) | H39: =H35+H37 | K39: =K35+K37
G40: Time in planes & trains | H40: =D10+D11+D13+D14 | K40: =D10+D11+D13+D14
A42: Key facts
A43: Contest | B43: Asia Shenyang Regional, 14–15 Nov 2026 (provisional), Northeastern University Nanhu campus
A44: Why this plan | B44: Cheapest plan without overnight trains: two nights at Dequan (¥304 each), one at Bestay (¥86), MIAT evening flight, G101 at 08:00 reaches Shenyang before the registration desk opens.
A45: Trade-off | B45: Two Beijing night stops and a metro commute to NEU on contest day; ~25 min metro each way. About ₮0.84M more than the sleeper-train budget plan (3 ppl).
A47: Day-by-day plan
A48: Date | B48: Sleep in | C48: What happens
A49: Fri 13 Nov | B49: Beijing | C49: MIAT OM223 UB 17:15 → Beijing 19:30. Taxi to Dequan Railway Station Hotel near Beijing Chaoyang.
A50: Sat 14 Nov | B50: Shenyang | C50: G101 Beijing Chaoyang 08:00 → Shenyang North 10:29; Bestay Hotel; registration & practice at NEU Nanhu (metro).
A51: Sun 15 Nov | B51: Beijing | C51: SHENYANG REGIONAL contest day. G142 19:51 → Beijing Chaoyang 22:30; Dequan hotel.
A52: Mon 16 Nov | B52: Home | C52: Taxi to PEK. Air China Beijing Capital 12:55 → UB 15:05 (nonstop).
A54: Door-to-door travel times
A55: Date | B55: Leg | C55: Mode | D55: Expected time | E55: Notes
A56: 13 Nov | B56: Home → Chinggis Khaan airport | C56: Taxi (~50 km) | D56: 0.041666667 | E56: Leave ~14:15 for 17:15 flight
A57: 13 Nov | B57: Ulaanbaatar → Beijing (PEK) | C57: MIAT OM223 17:15–19:30 | D57: 0.09375
A58: 13 Nov | B58: PEK arrival: immigration, bags | C58: — | D58: 0.03125 | E58: Estimate
A59: 13 Nov | B59: PEK → Dequan hotel (Chaoyang station) | C59: Taxi (~35 km) | D59: 0.034722222 | E59: Estimate
A60: 14 Nov | B60: Beijing Chaoyang → Shenyang North | C60: G101 08:00–10:29 | D60: 0.10347222
A61: 14 Nov | B61: Shenyang North → Bestay hotel | C61: Metro | D61: 0.020833333 | E61: Estimate
A62: 14–15 Nov | B62: Hotel ↔ NEU Nanhu (each way) | C62: Metro | D62: daily | E62: ~25 min metro
A63: 15 Nov | B63: NEU Nanhu → Shenyang North | C63: Taxi | D63: 0.017361111
A64: 15 Nov | B64: Shenyang North → Beijing Chaoyang | C64: G142 19:51–22:30 | D64: 0.11041667
A65: 15 Nov | B65: Beijing Chaoyang station → Dequan hotel | C65: Walk / taxi (~1 km) | D65: 0.010416667 | E65: Estimate
A66: 16 Nov | B66: Hotel → PEK | C66: Taxi | D66: 0.034722222 | E66: Be at PEK by ~10:55
A67: 16 Nov | B67: Beijing (PEK) → Ulaanbaatar | C67: Air China 12:55–15:05 | D67: 0.090277778
A68: 16 Nov | B68: Chinggis Khaan airport → home | C68: Taxi | D68: 0.041666667
C70: Total door-to-door | D70: =SUM(D56:D68)

Sheet Shenyang – Comfort (G-train)
A1: Shenyang – Comfort (G-train)
A2: No sleeper trains: MIAT + high-speed rail out, evening G-train back to Beijing and a hotel night near Chaoyang station; rest day and family room near the venue.
A4: Days in destination (meals & local transport) | B4: 4.5 | C4: 12 Nov morning → midday 16 Nov
A5: Shared inputs are on the Compare sheet. Scroll down for the day-by-day plan and door-to-door travel times.
A7: Category | B7: Item | C7: Date | D7: Travel time | E7: Unit cost (3 ppl) | F7: Currency | G7: Qty (3 ppl) | H7: Total MNT – 3 people | I7: Unit cost (4 ppl) | J7: Qty (4 ppl) | K7: Total MNT – 4 people | L7: Source / notes
A8: PAID BY UNIVERSITY
A9: Flights
B10: MIAT OM223 Ulaanbaatar → Beijing (PEK), 07:30–09:45 | C10: 12 Nov | D10: 0.09375 | E10: 151 | F10: USD | G10: =Compare!$B$6 | H10: =E10*G10*IF(F10="USD",Compare!$B$8,IF(F10="CNY",Compare!$B$9,IF(F10="HKD",Compare!$B$10,1))) | I10: =E10 | J10: =Compare!$B$7 | K10: =I10*J10*IF(F10="USD",Compare!$B$8,IF(F10="CNY",Compare!$B$9,IF(F10="HKD",Compare!$B$10,1))) | L10: Trip.com 30 Sep: MIAT 07:30–09:45 $151 pp (SlickTrip 30 Sep: $154)
B11: Air China Beijing (PEK) → Ulaanbaatar, nonstop 12:55–15:05 | C11: 16 Nov | D11: 0.090277778 | E11: 171 | F11: USD | G11: =Compare!$B$6 | H11: =E11*G11*IF(F11="USD",Compare!$B$8,IF(F11="CNY",Compare!$B$9,IF(F11="HKD",Compare!$B$10,1))) | I11: =E11 | J11: =Compare!$B$7 | K11: =I11*J11*IF(F11="USD",Compare!$B$8,IF(F11="CNY",Compare!$B$9,IF(F11="HKD",Compare!$B$10,1))) | L11: Trip.com 30 Sep: Air China nonstop $171 pp (MIAT OM224 11:30 was $194 on Trip.com, $196.33 on SlickTrip)
A12: Trains
B13: High-speed rail Beijing Chaoyang 12:19 → Shenyang North 14:48 (G149), 2nd class | C13: 12 Nov (midday) | D13: 0.10347222 | E13: 369 | F13: CNY | G13: =Compare!$B$6 | H13: =E13*G13*IF(F13="USD",Compare!$B$8,IF(F13="CNY",Compare!$B$9,IF(F13="HKD",Compare!$B$10,1))) | I13: =E13 | J13: =Compare!$B$7 | K13: =I13*J13*IF(F13="USD",Compare!$B$8,IF(F13="CNY",Compare!$B$9,IF(F13="HKD",Compare!$B$10,1))) | L13: 12306 (queried 10 Oct for 20 Oct; fares fixed): G149 ¥369; G3539 11:43 → 15:34 ¥355; slower 3 h 15–3 h 35 trains ¥296–317. MIAT lands 09:45, so a ~12:00 train is realistic (the old ¥339 in Shenyang – Comfort is not on the 12306 list)
B14: High-speed rail Shenyang North 19:51 → Beijing Chaoyang 22:30 (G142), 2nd class | C14: 15 Nov (evening) | D14: 0.11041667 | E14: 268 | F14: CNY | G14: =Compare!$B$6 | H14: =E14*G14*IF(F14="USD",Compare!$B$8,IF(F14="CNY",Compare!$B$9,IF(F14="HKD",Compare!$B$10,1))) | I14: =E14 | J14: =Compare!$B$7 | K14: =I14*J14*IF(F14="USD",Compare!$B$8,IF(F14="CNY",Compare!$B$9,IF(F14="HKD",Compare!$B$10,1))) | L14: 12306 (queried 10 Oct for 20 Oct; fares fixed): G142 / G156 (Shenyang stn 19:05) / G3522 19:21 → 22:36 ¥268; G122 / G126 ¥344. Awards end ~17:00, so 19:51 leaves a safe margin
A15: Accommodation
B16: Shenyang RiCH Hotel, Sanhao St (~1.3 km to NEU Nanhu; Family Room sleeps 4, so one room for 3 or 4) | C16: 12–15 Nov (3 nights) | E16: 325.33 | F16: CNY | G16: 3 | H16: =E16*G16*IF(F16="USD",Compare!$B$8,IF(F16="CNY",Compare!$B$9,IF(F16="HKD",Compare!$B$10,1))) | I16: 325.33 | J16: 3 | K16: =I16*J16*IF(F16="USD",Compare!$B$8,IF(F16="CNY",Compare!$B$9,IF(F16="HKD",Compare!$B$10,1))) | L16: Trip.com 1 Oct: Family Room ¥976 for 3 nights, same price for 3 or 4 adults; rated 9.6 (1,802 reviews)
B17: Dequan Railway Station Hotel, Beijing (~1 km from Beijing Chaoyang station; 3 ppl 1 room; 4 ppl 2 rooms) | C17: 15 Nov (1 night) | E17: 304 | F17: CNY | G17: 1 | H17: =E17*G17*IF(F17="USD",Compare!$B$8,IF(F17="CNY",Compare!$B$9,IF(F17="HKD",Compare!$B$10,1))) | I17: 608 | J17: 1 | K17: =I17*J17*IF(F17="USD",Compare!$B$8,IF(F17="CNY",Compare!$B$9,IF(F17="HKD",Compare!$B$10,1))) | L17: Booking.com 9 Oct: ¥304 for 3 adults, 1 room per night; rated 8.7 (65 reviews). 4 ppl: ASSUMPTION 2 × ¥304 (rooms not searched)
A18: Meals & local transport
B19: Meals | C19: in destination | E19: 80 | F19: CNY | G19: =Compare!$B$6*$B$4 | H19: =E19*G19*IF(F19="USD",Compare!$B$8,IF(F19="CNY",Compare!$B$9,IF(F19="HKD",Compare!$B$10,1))) | I19: =E19 | J19: =Compare!$B$7*$B$4 | K19: =I19*J19*IF(F19="USD",Compare!$B$8,IF(F19="CNY",Compare!$B$9,IF(F19="HKD",Compare!$B$10,1))) | L19: ASSUMPTION 80 CNY/person/day; hosts usually provide some meals on contest days
B20: Local transport (metro, taxis) | C20: in destination | E20: 30 | F20: CNY | G20: =Compare!$B$6*$B$4 | H20: =E20*G20*IF(F20="USD",Compare!$B$8,IF(F20="CNY",Compare!$B$9,IF(F20="HKD",Compare!$B$10,1))) | I20: =E20 | J20: =Compare!$B$7*$B$4 | K20: =I20*J20*IF(F20="USD",Compare!$B$8,IF(F20="CNY",Compare!$B$9,IF(F20="HKD",Compare!$B$10,1))) | L20: ASSUMPTION 30 CNY/person/day
B21: Taxi PEK → Beijing Chaoyang station | C21: 12 Nov | E21: 120 | F21: CNY | G21: 1 | H21: =E21*G21*IF(F21="USD",Compare!$B$8,IF(F21="CNY",Compare!$B$9,IF(F21="HKD",Compare!$B$10,1))) | I21: =E21 | J21: 1 | K21: =I21*J21*IF(F21="USD",Compare!$B$8,IF(F21="CNY",Compare!$B$9,IF(F21="HKD",Compare!$B$10,1))) | L21: ASSUMPTION ~120 CNY per car, ~40 km (4 ppl may need an XL car)
B22: Taxi Dequan hotel → PEK | C22: 16 Nov | E22: 120 | F22: CNY | G22: 1 | H22: =E22*G22*IF(F22="USD",Compare!$B$8,IF(F22="CNY",Compare!$B$9,IF(F22="HKD",Compare!$B$10,1))) | I22: =E22 | J22: 1 | K22: =I22*J22*IF(F22="USD",Compare!$B$8,IF(F22="CNY",Compare!$B$9,IF(F22="HKD",Compare!$B$10,1))) | L22: ASSUMPTION ~120 CNY per car, ~35 km, leave ~09:00
A23: PAID PERSONALLY (university won't cover)
A24: Contest fee
B25: Shenyang regional registration fee (per team) | C25: pay by mid-Oct | E25: 1500 | F25: CNY | G25: 1 | H25: =E25*G25*IF(F25="USD",Compare!$B$8,IF(F25="CNY",Compare!$B$9,IF(F25="HKD",Compare!$B$10,1))) | I25: =E25 | J25: 1 | K25: =I25*J25*IF(F25="USD",Compare!$B$8,IF(F25="CNY",Compare!$B$9,IF(F25="HKD",Compare!$B$10,1))) | L25: ASSUMPTION: 1,500 CNY/team like recent EC regionals; 2026 Shenyang invitation not seen
A26: Other
B27: Taxi to/from Chinggis Khaan airport (UB), per trip | C27: out & back | D27: 0.041666667 | E27: 100000 | F27: MNT | G27: 2 | H27: =E27*G27*IF(F27="USD",Compare!$B$8,IF(F27="CNY",Compare!$B$9,IF(F27="HKD",Compare!$B$10,1))) | I27: =E27 | J27: 2 | K27: =I27*J27*IF(F27="USD",Compare!$B$8,IF(F27="CNY",Compare!$B$9,IF(F27="HKD",Compare!$B$10,1))) | L27: ASSUMPTION 100k MNT per trip for the group
B28: Travel medical insurance | E28: 30000 | F28: MNT | G28: =Compare!$B$6 | H28: =E28*G28*IF(F28="USD",Compare!$B$8,IF(F28="CNY",Compare!$B$9,IF(F28="HKD",Compare!$B$10,1))) | I28: =E28 | J28: =Compare!$B$7 | K28: =I28*J28*IF(F28="USD",Compare!$B$8,IF(F28="CNY",Compare!$B$9,IF(F28="HKD",Compare!$B$10,1))) | L28: ASSUMPTION ~30k MNT per person, Mongolian insurer
B29: Mobile data eSIM | E29: 10 | F29: USD | G29: =Compare!$B$6 | H29: =E29*G29*IF(F29="USD",Compare!$B$8,IF(F29="CNY",Compare!$B$9,IF(F29="HKD",Compare!$B$10,1))) | I29: =E29 | J29: =Compare!$B$7 | K29: =I29*J29*IF(F29="USD",Compare!$B$8,IF(F29="CNY",Compare!$B$9,IF(F29="HKD",Compare!$B$10,1))) | L29: ASSUMPTION ~$10 pp
B30: Visa | E30: 0 | F30: MNT | G30: =Compare!$B$6 | H30: =E30*G30*IF(F30="USD",Compare!$B$8,IF(F30="CNY",Compare!$B$9,IF(F30="HKD",Compare!$B$10,1))) | I30: =E30 | J30: =Compare!$B$7 | K30: =I30*J30*IF(F30="USD",Compare!$B$8,IF(F30="CNY",Compare!$B$9,IF(F30="HKD",Compare!$B$10,1))) | L30: Mongolian passports: visa-free (mainland China up to 30 days; Hong Kong up to 14 days)
H32: 3 people – UNFUNDED | K32: 4 people – FUNDED ₮12M
G33: University-paid subtotal | H33: =SUM(H9:H22) | K33: =SUM(K9:K22)
G34: Contingency | H34: =H33*Compare!$B$11 | K34: =K33*Compare!$B$11
G35: University-paid total incl. contingency | H35: =H33+H34 | K35: =K33+K34
G36: Funding left (negative = over) | H36: =Compare!$B$12-H35 | K36: =Compare!$B$5-K35
G37: Personal costs – team | H37: =SUM(H24:H30) | K37: =SUM(K24:K30)
G38: Out-of-pocket per person (personal + any overrun) | H38: =(H37+MAX(0,-H36))/Compare!$B$6 | K38: =(K37+MAX(0,-K36))/Compare!$B$7
G39: Whole trip cost (university + personal) | H39: =H35+H37 | K39: =K35+K37
G40: Time in planes & trains | H40: =D10+D11+D13+D14 | K40: =D10+D11+D13+D14
A42: Key facts
A43: Contest | B43: Asia Shenyang Regional, 14–15 Nov 2026 (provisional), Northeastern University Nanhu campus
A44: Why this plan | B44: Same rest day and hotel as Shenyang – Comfort, but no overnight train: you sleep in a bed both nights and the evening G-train is cheap (¥268). Fits a late closing ceremony (train 19:51).
A45: Trade-off | B45: Costs a Beijing hotel night and about ₮0.54M more than the hard-sleeper plan (3 ppl); ~9 h 30 min in planes and trains (sleeper plan: 16 h).
A47: Day-by-day plan
A48: Date | B48: Sleep in | C48: What happens
A49: Thu 12 Nov | B49: Shenyang | C49: MIAT OM223 UB 07:30 → Beijing 09:45; taxi PEK → Beijing Chaoyang; G149 12:19 → Shenyang North 14:48; taxi to RiCH Hotel.
A50: Fri 13 Nov | B50: Shenyang | C50: Rest / practice day in Shenyang.
A51: Sat 14 Nov | B51: Shenyang | C51: Registration & practice at NEU Nanhu (walkable from hotel).
A52: Sun 15 Nov | B52: Beijing | C52: SHENYANG REGIONAL contest day. Taxi to Shenyang North; G142 19:51 → Beijing Chaoyang 22:30; walk/taxi to Dequan hotel.
A53: Mon 16 Nov | B53: Home | C53: Taxi Chaoyang → PEK. Air China Beijing Capital 12:55 → UB 15:05 (nonstop).
A55: Door-to-door travel times
A56: Date | B56: Leg | C56: Mode | D56: Expected time | E56: Notes
A57: 12 Nov | B57: Home → Chinggis Khaan airport | C57: Taxi (~50 km) | D57: 0.041666667 | E57: Leave ~04:30 for 07:30 flight
A58: 12 Nov | B58: Ulaanbaatar → Beijing (PEK) | C58: MIAT OM223 07:30–09:45 | D58: 0.09375
A59: 12 Nov | B59: PEK arrival: immigration, bags | C59: — | D59: 0.03125 | E59: Estimate
A60: 12 Nov | B60: PEK → Beijing Chaoyang station | C60: Taxi (~40 km) | D60: 0.034722222 | E60: Estimate; arrive ~11:15 for the 12:19 train
A61: 12 Nov | B61: Beijing Chaoyang → Shenyang North | C61: G149 2nd class | D61: 0.10347222
A62: 12 Nov | B62: Shenyang North → hotel near NEU | C62: Taxi | D62: 0.017361111 | E62: Estimate
A63: 13–15 Nov | B63: Hotel ↔ NEU Nanhu (each way) | C63: Walk | D63: daily | E63: ~18 min walk (RiCH Hotel, 1.3 km)
A64: 15 Nov | B64: NEU Nanhu → Shenyang North | C64: Taxi | D64: 0.017361111
A65: 15 Nov | B65: Shenyang North → Beijing Chaoyang | C65: G142 19:51–22:30 | D65: 0.11041667
A66: 15 Nov | B66: Beijing Chaoyang station → Dequan hotel | C66: Walk / taxi (~1 km) | D66: 0.010416667 | E66: Estimate
A67: 16 Nov | B67: Hotel → PEK | C67: Taxi | D67: 0.034722222 | E67: Be at PEK by ~10:55
A68: 16 Nov | B68: Beijing (PEK) → Ulaanbaatar | C68: Air China 12:55–15:05 | D68: 0.090277778
A69: 16 Nov | B69: Chinggis Khaan airport → home | C69: Taxi | D69: 0.041666667
C71: Total door-to-door | D71: =SUM(D57:D69)

Sheet Shenyang – Sleep first
A1: Shenyang – Sleep first
A2: Sleep first before the contest, cheapest after: no early alarm (Air China 11:50), three nights in the same quiet hotel next to the venue with a bed each; hard-seat night train + cheapest flight home.
A4: Days in destination (meals & local transport) | B4: 4 | C4: 12 Nov afternoon → 16 Nov midday
A5: Shared inputs are on the Compare sheet. Scroll down for the day-by-day plan and door-to-door travel times.
A7: Category | B7: Item | C7: Date | D7: Travel time | E7: Unit cost (3 ppl) | F7: Currency | G7: Qty (3 ppl) | H7: Total MNT – 3 people | I7: Unit cost (4 ppl) | J7: Qty (4 ppl) | K7: Total MNT – 4 people | L7: Source / notes
A8: PAID BY UNIVERSITY
A9: Flights
B10: Air China CA902 Ulaanbaatar 11:50 → Beijing Capital (PEK) 13:55, nonstop, checked bag included | C10: 12 Nov | D10: 0.086805556 | E10: 1291 | F10: CNY | G10: =Compare!$B$6 | H10: =E10*G10*IF(F10="USD",Compare!$B$8,IF(F10="CNY",Compare!$B$9,IF(F10="HKD",Compare!$B$10,1))) | I10: =E10 | J10: =Compare!$B$7 | K10: =I10*J10*IF(F10="USD",Compare!$B$8,IF(F10="CNY",Compare!$B$9,IF(F10="HKD",Compare!$B$10,1))) | L10: Ctrip 22 Oct: ¥1,291 pp incl. tax – cheapest of 5 sources (Kiwi $200, Trip.com $203, SlickTrip $316 on 13 Nov, Google Flights unpriced). MIAT OM223 07:30 is ¥1,096 on Ctrip / $167 Kiwi / $172 Google / $154 SlickTrip but means a ~04:00 wake-up. Ctrip needs a Ctrip account (Alipay or a foreign card); Trip.com $203 is the fallback.
B11: Air China CA955 Beijing Capital (PEK) 12:55 → Ulaanbaatar 15:05, nonstop | C11: 16 Nov | D11: 0.090277778 | E11: 171 | F11: USD | G11: =Compare!$B$6 | H11: =E11*G11*IF(F11="USD",Compare!$B$8,IF(F11="CNY",Compare!$B$9,IF(F11="HKD",Compare!$B$10,1))) | I11: =E11 | J11: =Compare!$B$7 | K11: =I11*J11*IF(F11="USD",Compare!$B$8,IF(F11="CNY",Compare!$B$9,IF(F11="HKD",Compare!$B$10,1))) | L11: Trip.com 22 Oct: US$171 pp, cheapest that day (MIAT OM224 11:30 US$193 on Trip.com / $176 on SlickTrip; Air China 08:25 $215; Capital + Hunnu via Erenhot $196)
A12: Trains
B13: High-speed rail G153 Beijing Chaoyang 17:27 → Shenyang 20:04, 2nd class | C13: 12 Nov (evening) | D13: 0.10902778 | E13: 369 | F13: CNY | G13: =Compare!$B$6 | H13: =E13*G13*IF(F13="USD",Compare!$B$8,IF(F13="CNY",Compare!$B$9,IF(F13="HKD",Compare!$B$10,1))) | I13: =E13 | J13: =Compare!$B$7 | K13: =I13*J13*IF(F13="USD",Compare!$B$8,IF(F13="CNY",Compare!$B$9,IF(F13="HKD",Compare!$B$10,1))) | L13: 12306 (queried 22 Oct for 5 Nov; fares fixed): ¥369. ChinaTicketOnline confirms G153 on 12 Nov, on sale 29 Oct 10:00. Leaves 3 h 30 min after landing; if the flight is on time, change at the station to G141 16:00 → Shenyang North 18:29 (¥369). Later trains: G155 18:35 / G143 18:48 (¥369–383). Ctrip train list (22 Oct, for 12 Nov) shows the same fares; 12go.asia resells at ~$90 for 1st class.
B14: Overnight train K28 Shenyang 22:24 → Beijing 08:40, hard seat (after the contest) | C14: 15 Nov (night) | D14: 0.42777778 | E14: 112 | F14: CNY | G14: =Compare!$B$6 | H14: =E14*G14*IF(F14="USD",Compare!$B$8,IF(F14="CNY",Compare!$B$9,IF(F14="HKD",Compare!$B$10,1))) | I14: =E14 | J14: =Compare!$B$7 | K14: =I14*J14*IF(F14="USD",Compare!$B$8,IF(F14="CNY",Compare!$B$9,IF(F14="HKD",Compare!$B$10,1))) | L14: 12306 (5 Nov query): hard seat ¥112 (hard sleeper ¥194). Cheapest train that still makes the 12:55 flight (K96 23:39 ¥102 arrives 11:19 – too late). Lie-flat upgrade: K54 Shenyang North 22:00 → 06:58 hard sleeper ¥171 (+¥59 pp). On sale 1 Nov 09:30 (ChinaTicketOnline confirms 15 Nov).
A15: Accommodation
B16: NEU International Hotel, 80 Wenti West Rd (~580 m to NEU Nanhu): 2 Superior Twin rooms, 38 m², floors 5–10 – a bed each | C16: 12–15 Nov (3 nights) | E16: 796 | F16: CNY | G16: 3 | H16: =E16*G16*IF(F16="USD",Compare!$B$8,IF(F16="CNY",Compare!$B$9,IF(F16="HKD",Compare!$B$10,1))) | I16: 796 | J16: 3 | K16: =I16*J16*IF(F16="USD",Compare!$B$8,IF(F16="CNY",Compare!$B$9,IF(F16="HKD",Compare!$B$10,1))) | L16: Trip.com 22 Oct: ¥2,388 for 2 rooms × 3 nights incl. taxes, free cancellation, pay at hotel; same price for 3 or 4 adults. 9.7 from 1,998 reviews (no negative review in 2 years; campus/river views). Shown as a 30% 'Surprise Savings' rate (list ¥547 per room-night = ¥3,282) – book soon.
A17: Meals & local transport
B18: Meals | C18: in destination | E18: 80 | F18: CNY | G18: =Compare!$B$6*$B$4 | H18: =E18*G18*IF(F18="USD",Compare!$B$8,IF(F18="CNY",Compare!$B$9,IF(F18="HKD",Compare!$B$10,1))) | I18: =E18 | J18: =Compare!$B$7*$B$4 | K18: =I18*J18*IF(F18="USD",Compare!$B$8,IF(F18="CNY",Compare!$B$9,IF(F18="HKD",Compare!$B$10,1))) | L18: ASSUMPTION 80 CNY/person/day; hosts usually provide some meals on contest days
B19: Local transport (metro, taxis) | C19: in destination | E19: 30 | F19: CNY | G19: =Compare!$B$6*$B$4 | H19: =E19*G19*IF(F19="USD",Compare!$B$8,IF(F19="CNY",Compare!$B$9,IF(F19="HKD",Compare!$B$10,1))) | I19: =E19 | J19: =Compare!$B$7*$B$4 | K19: =I19*J19*IF(F19="USD",Compare!$B$8,IF(F19="CNY",Compare!$B$9,IF(F19="HKD",Compare!$B$10,1))) | L19: ASSUMPTION 30 CNY/person/day
B20: Taxi PEK → Beijing Chaoyang station | C20: 12 Nov | E20: 120 | F20: CNY | G20: 1 | H20: =E20*G20*IF(F20="USD",Compare!$B$8,IF(F20="CNY",Compare!$B$9,IF(F20="HKD",Compare!$B$10,1))) | I20: =E20 | J20: 1 | K20: =I20*J20*IF(F20="USD",Compare!$B$8,IF(F20="CNY",Compare!$B$9,IF(F20="HKD",Compare!$B$10,1))) | L20: ASSUMPTION ~120 CNY per car, ~40 km (4 ppl may need an XL car)
B21: Metro line 2 + Airport Express, Beijing station → PEK T3 | C21: 16 Nov | E21: 30 | F21: CNY | G21: =Compare!$B$6 | H21: =E21*G21*IF(F21="USD",Compare!$B$8,IF(F21="CNY",Compare!$B$9,IF(F21="HKD",Compare!$B$10,1))) | I21: =E21 | J21: =Compare!$B$7 | K21: =I21*J21*IF(F21="USD",Compare!$B$8,IF(F21="CNY",Compare!$B$9,IF(F21="HKD",Compare!$B$10,1))) | L21: ASSUMPTION Airport Express ¥25 + metro ¥4–5 pp
A22: PAID PERSONALLY (university won't cover)
A23: Contest fee
B24: Shenyang regional registration fee (per team) | C24: pay when invited | E24: 1500 | F24: CNY | G24: 1 | H24: =E24*G24*IF(F24="USD",Compare!$B$8,IF(F24="CNY",Compare!$B$9,IF(F24="HKD",Compare!$B$10,1))) | I24: =E24 | J24: 1 | K24: =I24*J24*IF(F24="USD",Compare!$B$8,IF(F24="CNY",Compare!$B$9,IF(F24="HKD",Compare!$B$10,1))) | L24: ASSUMPTION: 1,500 CNY/team like recent EC regionals; the 2026 Shenyang invitation was not found on 22 Oct
A25: Other
B26: Taxi to/from Chinggis Khaan airport (UB), per trip | C26: out & back | D26: 0.041666667 | E26: 100000 | F26: MNT | G26: 2 | H26: =E26*G26*IF(F26="USD",Compare!$B$8,IF(F26="CNY",Compare!$B$9,IF(F26="HKD",Compare!$B$10,1))) | I26: =E26 | J26: 2 | K26: =I26*J26*IF(F26="USD",Compare!$B$8,IF(F26="CNY",Compare!$B$9,IF(F26="HKD",Compare!$B$10,1))) | L26: ASSUMPTION 100k MNT per trip for the group
B27: Travel medical insurance | E27: 30000 | F27: MNT | G27: =Compare!$B$6 | H27: =E27*G27*IF(F27="USD",Compare!$B$8,IF(F27="CNY",Compare!$B$9,IF(F27="HKD",Compare!$B$10,1))) | I27: =E27 | J27: =Compare!$B$7 | K27: =I27*J27*IF(F27="USD",Compare!$B$8,IF(F27="CNY",Compare!$B$9,IF(F27="HKD",Compare!$B$10,1))) | L27: ASSUMPTION ~30k MNT per person, Mongolian insurer
B28: Mobile data eSIM | E28: 10 | F28: USD | G28: =Compare!$B$6 | H28: =E28*G28*IF(F28="USD",Compare!$B$8,IF(F28="CNY",Compare!$B$9,IF(F28="HKD",Compare!$B$10,1))) | I28: =E28 | J28: =Compare!$B$7 | K28: =I28*J28*IF(F28="USD",Compare!$B$8,IF(F28="CNY",Compare!$B$9,IF(F28="HKD",Compare!$B$10,1))) | L28: ASSUMPTION ~$10 pp
B29: Visa | E29: 0 | F29: MNT | G29: =Compare!$B$6 | H29: =E29*G29*IF(F29="USD",Compare!$B$8,IF(F29="CNY",Compare!$B$9,IF(F29="HKD",Compare!$B$10,1))) | I29: =E29 | J29: =Compare!$B$7 | K29: =I29*J29*IF(F29="USD",Compare!$B$8,IF(F29="CNY",Compare!$B$9,IF(F29="HKD",Compare!$B$10,1))) | L29: Mongolian passports: visa-free (mainland China up to 30 days; Hong Kong up to 14 days)
H31: 3 people – UNFUNDED | K31: 4 people – FUNDED ₮12M
G32: University-paid subtotal | H32: =SUM(H9:H21) | K32: =SUM(K9:K21)
G33: Contingency | H33: =H32*Compare!$B$11 | K33: =K32*Compare!$B$11
G34: University-paid total incl. contingency | H34: =H32+H33 | K34: =K32+K33
G35: Funding left (negative = over) | H35: =Compare!$B$12-H34 | K35: =Compare!$B$5-K34
G36: Personal costs – team | H36: =SUM(H23:H29) | K36: =SUM(K23:K29)
G37: Out-of-pocket per person (personal + any overrun) | H37: =(H36+MAX(0,-H35))/Compare!$B$6 | K37: =(K36+MAX(0,-K35))/Compare!$B$7
G38: Whole trip cost (university + personal) | H38: =H34+H36 | K38: =K34+K36
G39: Time in planes & trains | H39: =SUM(D10:D11)+SUM(D13:D14) | K39: =SUM(D10:D11)+SUM(D13:D14)
A41: Key facts
A42: Contest | B42: Asia Shenyang Regional, 14–15 Nov 2026 (provisional; the 2026 invitation was not found on 22 Oct), Northeastern University Nanhu campus (2024 and 2025 venue). Assumed: day 1 registration + practice, contest 15 Nov 09:00–14:00, awards ~17:00.
A43: Why this plan | B43: Sleep quantity: nobody wakes before ~08:00 on any day before the contest (Air China 11:50 instead of MIAT 07:30), and there are three hotel nights before the contest with a free rest day on 13 Nov. Sleep quality: the same room all three nights, two twin rooms so everyone has their own bed, the best-rated hotel next to the campus (9.7), and a 7-minute walk on contest morning.
A44: Trade-off | B44: After the contest it is the cheapest way home: a night sitting up on the K28 (hard sleeper K54 is +¥59 pp) and the cheapest flight. Hotel luggage storage on 15 Nov (check-out before the contest). 'Shenyang – Sleep value' is the same plan with a cheaper twin-room hotel 15 min away.
A45: Book | B45: Air China CA902 on Ctrip now (¥1,291; Trip.com $203 as fallback); hotel now (free cancellation); G153 on 12306 at 10:00 on 29 Oct; K28 at 09:30 on 1 Nov.
A47: Day-by-day plan
A48: Date | B48: Sleep in | C48: What happens
A49: Thu 12 Nov | B49: Shenyang | C49: Wake ~08:00. Air China CA902 UB 11:50 → Beijing Capital 13:55; taxi to Beijing Chaoyang; G153 17:27 → Shenyang 20:04 (G141 16:00 if early); taxi to NEU International Hotel. Bed by ~23:00.
A50: Fri 13 Nov | B50: Shenyang | C50: Free rest day: no alarm, light practice, walk the 7-minute route to the venue.
A51: Sat 14 Nov | B51: Shenyang | C51: Registration, opening and practice at NEU Nanhu. Lights out ~22:30.
A52: Sun 15 Nov | B52: Train (seat) | C52: CONTEST. Wake ~07:00, walk 7 min. Check out before leaving, luggage stored at the hotel. Awards ~17:00; taxi to Shenyang station; K28 22:24 hard seat → Beijing 08:40.
A53: Mon 16 Nov | B53: Home | C53: Metro line 2 + Airport Express to PEK T3 (~1 h). Air China 12:55 → UB 15:05.
A55: Door-to-door travel times
A56: Date | B56: Leg | C56: Mode | D56: Expected time | E56: Notes
A57: 12 Nov | B57: Home → Chinggis Khaan airport | C57: Taxi (~50 km) | D57: 0.041666667 | E57: Leave ~09:15 for the 11:50 flight; wake ~08:00
A58: 12 Nov | B58: Ulaanbaatar → Beijing (PEK) | C58: Air China CA902 11:50–13:55 | D58: 0.086805556
A59: 12 Nov | B59: PEK arrival: immigration, bags | C59: — | D59: 0.03125 | E59: Estimate
A60: 12 Nov | B60: PEK → Beijing Chaoyang station | C60: Taxi (~40 km) | D60: 0.034722222 | E60: Estimate; at the station ~15:30, G153 at 17:27 (or G141 16:00)
A61: 12 Nov | B61: Beijing Chaoyang → Shenyang | C61: G153 2nd class 17:27–20:04 | D61: 0.10902778
A62: 12 Nov | B62: Shenyang station → hotel | C62: Taxi (~4 km) | D62: 0.013888889 | E62: Check in ~20:30
A63: 13–15 Nov | B63: Hotel ↔ NEU Nanhu (each way) | C63: Walk | D63: daily | E63: ~7 min walk (NEU International Hotel, 580 m)
A64: 15 Nov | B64: NEU Nanhu → Shenyang station | C64: Taxi | D64: 0.013888889
A65: 15–16 Nov | B65: Shenyang → Beijing | C65: K28 hard seat 22:24–08:40 | D65: 0.42777778 | E65: Overnight, after the contest
A66: 16 Nov | B66: Beijing station → PEK | C66: Metro line 2 + Airport Express | D66: 0.041666667 | E66: Be at PEK by ~10:55
A67: 16 Nov | B67: Beijing (PEK) → Ulaanbaatar | C67: Air China 12:55–15:05 | D67: 0.090277778
A68: 16 Nov | B68: Chinggis Khaan airport → home | C68: Taxi | D68: 0.041666667
C70: Total door-to-door | D70: =SUM(D57:D68)

Sheet Shenyang – Sleep value
A1: Shenyang – Sleep value
A2: Same sleep-first timing as 'Sleep first' (Air China 11:50, three nights before the contest, a bed each) in a cheaper twin-room hotel ~15 min walk from the venue; hard-seat night train + cheapest flight home.
A4: Days in destination (meals & local transport) | B4: 4 | C4: 12 Nov afternoon → 16 Nov midday
A5: Shared inputs are on the Compare sheet. Scroll down for the day-by-day plan and door-to-door travel times.
A7: Category | B7: Item | C7: Date | D7: Travel time | E7: Unit cost (3 ppl) | F7: Currency | G7: Qty (3 ppl) | H7: Total MNT – 3 people | I7: Unit cost (4 ppl) | J7: Qty (4 ppl) | K7: Total MNT – 4 people | L7: Source / notes
A8: PAID BY UNIVERSITY
A9: Flights
B10: Air China CA902 Ulaanbaatar 11:50 → Beijing Capital (PEK) 13:55, nonstop, checked bag included | C10: 12 Nov | D10: 0.086805556 | E10: 1291 | F10: CNY | G10: =Compare!$B$6 | H10: =E10*G10*IF(F10="USD",Compare!$B$8,IF(F10="CNY",Compare!$B$9,IF(F10="HKD",Compare!$B$10,1))) | I10: =E10 | J10: =Compare!$B$7 | K10: =I10*J10*IF(F10="USD",Compare!$B$8,IF(F10="CNY",Compare!$B$9,IF(F10="HKD",Compare!$B$10,1))) | L10: Ctrip 22 Oct: ¥1,291 pp incl. tax – cheapest of 5 sources (Kiwi $200, Trip.com $203, SlickTrip $316 on 13 Nov, Google Flights unpriced). MIAT OM223 07:30 is ¥1,096 on Ctrip / $167 Kiwi / $172 Google / $154 SlickTrip but means a ~04:00 wake-up. Ctrip needs a Ctrip account (Alipay or a foreign card); Trip.com $203 is the fallback.
B11: Air China CA955 Beijing Capital (PEK) 12:55 → Ulaanbaatar 15:05, nonstop | C11: 16 Nov | D11: 0.090277778 | E11: 171 | F11: USD | G11: =Compare!$B$6 | H11: =E11*G11*IF(F11="USD",Compare!$B$8,IF(F11="CNY",Compare!$B$9,IF(F11="HKD",Compare!$B$10,1))) | I11: =E11 | J11: =Compare!$B$7 | K11: =I11*J11*IF(F11="USD",Compare!$B$8,IF(F11="CNY",Compare!$B$9,IF(F11="HKD",Compare!$B$10,1))) | L11: Trip.com 22 Oct: US$171 pp, cheapest that day (MIAT OM224 11:30 US$193 on Trip.com / $176 on SlickTrip; Air China 08:25 $215; Capital + Hunnu via Erenhot $196)
A12: Trains
B13: High-speed rail G153 Beijing Chaoyang 17:27 → Shenyang 20:04, 2nd class | C13: 12 Nov (evening) | D13: 0.10902778 | E13: 369 | F13: CNY | G13: =Compare!$B$6 | H13: =E13*G13*IF(F13="USD",Compare!$B$8,IF(F13="CNY",Compare!$B$9,IF(F13="HKD",Compare!$B$10,1))) | I13: =E13 | J13: =Compare!$B$7 | K13: =I13*J13*IF(F13="USD",Compare!$B$8,IF(F13="CNY",Compare!$B$9,IF(F13="HKD",Compare!$B$10,1))) | L13: 12306 (queried 22 Oct for 5 Nov; fares fixed): ¥369. ChinaTicketOnline confirms G153 on 12 Nov, on sale 29 Oct 10:00. Leaves 3 h 30 min after landing; if the flight is on time, change at the station to G141 16:00 → Shenyang North 18:29 (¥369). Later trains: G155 18:35 / G143 18:48 (¥369–383). Ctrip train list (22 Oct, for 12 Nov) shows the same fares; 12go.asia resells at ~$90 for 1st class.
B14: Overnight train K28 Shenyang 22:24 → Beijing 08:40, hard seat (after the contest) | C14: 15 Nov (night) | D14: 0.42777778 | E14: 112 | F14: CNY | G14: =Compare!$B$6 | H14: =E14*G14*IF(F14="USD",Compare!$B$8,IF(F14="CNY",Compare!$B$9,IF(F14="HKD",Compare!$B$10,1))) | I14: =E14 | J14: =Compare!$B$7 | K14: =I14*J14*IF(F14="USD",Compare!$B$8,IF(F14="CNY",Compare!$B$9,IF(F14="HKD",Compare!$B$10,1))) | L14: 12306 (5 Nov query): hard seat ¥112 (hard sleeper ¥194). Cheapest train that still makes the 12:55 flight (K96 23:39 ¥102 arrives 11:19 – too late). Lie-flat upgrade: K54 Shenyang North 22:00 → 06:58 hard sleeper ¥171 (+¥59 pp). On sale 1 Nov 09:30 (ChinaTicketOnline confirms 15 Nov).
A15: Accommodation
B16: Ji Hotel Sanhao Street, 55 Sanhao St (~940 m to NEU Nanhu, ~15 min walk): 2 Budget Twin rooms, King Koil mattresses, windows, floors 4–16 – a bed each | C16: 12–15 Nov (3 nights) | E16: 457 | F16: CNY | G16: 3 | H16: =E16*G16*IF(F16="USD",Compare!$B$8,IF(F16="CNY",Compare!$B$9,IF(F16="HKD",Compare!$B$10,1))) | I16: 457 | J16: 3 | K16: =I16*J16*IF(F16="USD",Compare!$B$8,IF(F16="CNY",Compare!$B$9,IF(F16="HKD",Compare!$B$10,1))) | L16: Trip.com 22 Oct: ¥1,371 for 2 rooms × 3 nights incl. taxes, free cancellation until 18:00 on 11 Nov (prepay); same price for 3 or 4 adults. 9.0 from 1,433 reviews; 16 m² rooms high in an office tower, above the street. Breakfast ¥40 optional.
A17: Meals & local transport
B18: Meals | C18: in destination | E18: 80 | F18: CNY | G18: =Compare!$B$6*$B$4 | H18: =E18*G18*IF(F18="USD",Compare!$B$8,IF(F18="CNY",Compare!$B$9,IF(F18="HKD",Compare!$B$10,1))) | I18: =E18 | J18: =Compare!$B$7*$B$4 | K18: =I18*J18*IF(F18="USD",Compare!$B$8,IF(F18="CNY",Compare!$B$9,IF(F18="HKD",Compare!$B$10,1))) | L18: ASSUMPTION 80 CNY/person/day; hosts usually provide some meals on contest days
B19: Local transport (metro, taxis) | C19: in destination | E19: 30 | F19: CNY | G19: =Compare!$B$6*$B$4 | H19: =E19*G19*IF(F19="USD",Compare!$B$8,IF(F19="CNY",Compare!$B$9,IF(F19="HKD",Compare!$B$10,1))) | I19: =E19 | J19: =Compare!$B$7*$B$4 | K19: =I19*J19*IF(F19="USD",Compare!$B$8,IF(F19="CNY",Compare!$B$9,IF(F19="HKD",Compare!$B$10,1))) | L19: ASSUMPTION 30 CNY/person/day
B20: Taxi PEK → Beijing Chaoyang station | C20: 12 Nov | E20: 120 | F20: CNY | G20: 1 | H20: =E20*G20*IF(F20="USD",Compare!$B$8,IF(F20="CNY",Compare!$B$9,IF(F20="HKD",Compare!$B$10,1))) | I20: =E20 | J20: 1 | K20: =I20*J20*IF(F20="USD",Compare!$B$8,IF(F20="CNY",Compare!$B$9,IF(F20="HKD",Compare!$B$10,1))) | L20: ASSUMPTION ~120 CNY per car, ~40 km (4 ppl may need an XL car)
B21: Metro line 2 + Airport Express, Beijing station → PEK T3 | C21: 16 Nov | E21: 30 | F21: CNY | G21: =Compare!$B$6 | H21: =E21*G21*IF(F21="USD",Compare!$B$8,IF(F21="CNY",Compare!$B$9,IF(F21="HKD",Compare!$B$10,1))) | I21: =E21 | J21: =Compare!$B$7 | K21: =I21*J21*IF(F21="USD",Compare!$B$8,IF(F21="CNY",Compare!$B$9,IF(F21="HKD",Compare!$B$10,1))) | L21: ASSUMPTION Airport Express ¥25 + metro ¥4–5 pp
A22: PAID PERSONALLY (university won't cover)
A23: Contest fee
B24: Shenyang regional registration fee (per team) | C24: pay when invited | E24: 1500 | F24: CNY | G24: 1 | H24: =E24*G24*IF(F24="USD",Compare!$B$8,IF(F24="CNY",Compare!$B$9,IF(F24="HKD",Compare!$B$10,1))) | I24: =E24 | J24: 1 | K24: =I24*J24*IF(F24="USD",Compare!$B$8,IF(F24="CNY",Compare!$B$9,IF(F24="HKD",Compare!$B$10,1))) | L24: ASSUMPTION: 1,500 CNY/team like recent EC regionals; the 2026 Shenyang invitation was not found on 22 Oct
A25: Other
B26: Taxi to/from Chinggis Khaan airport (UB), per trip | C26: out & back | D26: 0.041666667 | E26: 100000 | F26: MNT | G26: 2 | H26: =E26*G26*IF(F26="USD",Compare!$B$8,IF(F26="CNY",Compare!$B$9,IF(F26="HKD",Compare!$B$10,1))) | I26: =E26 | J26: 2 | K26: =I26*J26*IF(F26="USD",Compare!$B$8,IF(F26="CNY",Compare!$B$9,IF(F26="HKD",Compare!$B$10,1))) | L26: ASSUMPTION 100k MNT per trip for the group
B27: Travel medical insurance | E27: 30000 | F27: MNT | G27: =Compare!$B$6 | H27: =E27*G27*IF(F27="USD",Compare!$B$8,IF(F27="CNY",Compare!$B$9,IF(F27="HKD",Compare!$B$10,1))) | I27: =E27 | J27: =Compare!$B$7 | K27: =I27*J27*IF(F27="USD",Compare!$B$8,IF(F27="CNY",Compare!$B$9,IF(F27="HKD",Compare!$B$10,1))) | L27: ASSUMPTION ~30k MNT per person, Mongolian insurer
B28: Mobile data eSIM | E28: 10 | F28: USD | G28: =Compare!$B$6 | H28: =E28*G28*IF(F28="USD",Compare!$B$8,IF(F28="CNY",Compare!$B$9,IF(F28="HKD",Compare!$B$10,1))) | I28: =E28 | J28: =Compare!$B$7 | K28: =I28*J28*IF(F28="USD",Compare!$B$8,IF(F28="CNY",Compare!$B$9,IF(F28="HKD",Compare!$B$10,1))) | L28: ASSUMPTION ~$10 pp
B29: Visa | E29: 0 | F29: MNT | G29: =Compare!$B$6 | H29: =E29*G29*IF(F29="USD",Compare!$B$8,IF(F29="CNY",Compare!$B$9,IF(F29="HKD",Compare!$B$10,1))) | I29: =E29 | J29: =Compare!$B$7 | K29: =I29*J29*IF(F29="USD",Compare!$B$8,IF(F29="CNY",Compare!$B$9,IF(F29="HKD",Compare!$B$10,1))) | L29: Mongolian passports: visa-free (mainland China up to 30 days; Hong Kong up to 14 days)
H31: 3 people – UNFUNDED | K31: 4 people – FUNDED ₮12M
G32: University-paid subtotal | H32: =SUM(H9:H21) | K32: =SUM(K9:K21)
G33: Contingency | H33: =H32*Compare!$B$11 | K33: =K32*Compare!$B$11
G34: University-paid total incl. contingency | H34: =H32+H33 | K34: =K32+K33
G35: Funding left (negative = over) | H35: =Compare!$B$12-H34 | K35: =Compare!$B$5-K34
G36: Personal costs – team | H36: =SUM(H23:H29) | K36: =SUM(K23:K29)
G37: Out-of-pocket per person (personal + any overrun) | H37: =(H36+MAX(0,-H35))/Compare!$B$6 | K37: =(K36+MAX(0,-K35))/Compare!$B$7
G38: Whole trip cost (university + personal) | H38: =H34+H36 | K38: =K34+K36
G39: Time in planes & trains | H39: =SUM(D10:D11)+SUM(D13:D14) | K39: =SUM(D10:D11)+SUM(D13:D14)
A41: Key facts
A42: Contest | B42: Asia Shenyang Regional, 14–15 Nov 2026 (provisional; the 2026 invitation was not found on 22 Oct), Northeastern University Nanhu campus (2024 and 2025 venue). Assumed: day 1 registration + practice, contest 15 Nov 09:00–14:00, awards ~17:00.
A43: Why this plan | B43: Same sleep quantity as 'Sleep first' (no alarm before ~08:00, three hotel nights, rest day on 13 Nov) and still a bed each: two twin rooms with King Koil mattresses (Huazhu's Ji Hotel, 9.0 from 1,433 reviews) high in an office tower, for ¥1,017 less than NEU International.
A44: Trade-off | B44: Smaller rooms (16 m² vs 38 m²) and a ~15-minute walk (wake ~06:50 instead of 07:00). After the contest the same cheapest way home: K28 hard seat (K54 hard sleeper +¥59 pp) and Air China 12:55.
A45: Book | B45: Air China CA902 on Ctrip now (¥1,291; Trip.com $203 as fallback); hotel now (free cancellation until 18:00 on 11 Nov, prepaid); G153 on 12306 at 10:00 on 29 Oct; K28 at 09:30 on 1 Nov.
A47: Day-by-day plan
A48: Date | B48: Sleep in | C48: What happens
A49: Thu 12 Nov | B49: Shenyang | C49: Wake ~08:00. Air China CA902 UB 11:50 → Beijing Capital 13:55; taxi to Beijing Chaoyang; G153 17:27 → Shenyang 20:04 (G141 16:00 if early); taxi to Ji Hotel Sanhao Street. Bed by ~23:00.
A50: Fri 13 Nov | B50: Shenyang | C50: Free rest day: no alarm, light practice, walk the ~15-minute route to the venue.
A51: Sat 14 Nov | B51: Shenyang | C51: Registration, opening and practice at NEU Nanhu. Lights out ~22:30.
A52: Sun 15 Nov | B52: Train (seat) | C52: CONTEST. Wake ~06:50, walk ~15 min. Check out before leaving, luggage stored at the hotel. Awards ~17:00; taxi to Shenyang station; K28 22:24 hard seat → Beijing 08:40.
A53: Mon 16 Nov | B53: Home | C53: Metro line 2 + Airport Express to PEK T3 (~1 h). Air China 12:55 → UB 15:05.
A55: Door-to-door travel times
A56: Date | B56: Leg | C56: Mode | D56: Expected time | E56: Notes
A57: 12 Nov | B57: Home → Chinggis Khaan airport | C57: Taxi (~50 km) | D57: 0.041666667 | E57: Leave ~09:15 for the 11:50 flight; wake ~08:00
A58: 12 Nov | B58: Ulaanbaatar → Beijing (PEK) | C58: Air China CA902 11:50–13:55 | D58: 0.086805556
A59: 12 Nov | B59: PEK arrival: immigration, bags | C59: — | D59: 0.03125 | E59: Estimate
A60: 12 Nov | B60: PEK → Beijing Chaoyang station | C60: Taxi (~40 km) | D60: 0.034722222 | E60: Estimate; at the station ~15:30, G153 at 17:27 (or G141 16:00)
A61: 12 Nov | B61: Beijing Chaoyang → Shenyang | C61: G153 2nd class 17:27–20:04 | D61: 0.10902778
A62: 12 Nov | B62: Shenyang station → hotel | C62: Taxi (~4 km) | D62: 0.013888889 | E62: Check in ~20:30
A63: 13–15 Nov | B63: Hotel ↔ NEU Nanhu (each way) | C63: Walk | D63: daily | E63: ~15 min walk (Ji Hotel, 940 m straight line)
A64: 15 Nov | B64: NEU Nanhu → Shenyang station | C64: Taxi | D64: 0.013888889
A65: 15–16 Nov | B65: Shenyang → Beijing | C65: K28 hard seat 22:24–08:40 | D65: 0.42777778 | E65: Overnight, after the contest
A66: 16 Nov | B66: Beijing station → PEK | C66: Metro line 2 + Airport Express | D66: 0.041666667 | E66: Be at PEK by ~10:55
A67: 16 Nov | B67: Beijing (PEK) → Ulaanbaatar | C67: Air China 12:55–15:05 | D67: 0.090277778
A68: 16 Nov | B68: Chinggis Khaan airport → home | C68: Taxi | D68: 0.041666667
C70: Total door-to-door | D70: =SUM(D57:D68)

Sheet Shenyang – Overland home
A1: Shenyang – Overland home
A2: 'Sleep value' out (Air China 11:50, three nights before the contest, a bed each), then the cheapest way home overland: night trains via Hohhot to Erenhot, jeep across the border, UBTZ sleeper to Ulaanbaatar (home 18 Nov).
A4: Days in destination (meals & local transport) | B4: 5.5 | C4: 12 Nov afternoon → 18 Nov morning
A5: Shared inputs are on the Compare sheet. Scroll down for the day-by-day plan and door-to-door travel times.
A7: Category | B7: Item | C7: Date | D7: Travel time | E7: Unit cost (3 ppl) | F7: Currency | G7: Qty (3 ppl) | H7: Total MNT – 3 people | I7: Unit cost (4 ppl) | J7: Qty (4 ppl) | K7: Total MNT – 4 people | L7: Source / notes
A8: PAID BY UNIVERSITY
A9: Flights
B10: Air China CA902 Ulaanbaatar 11:50 → Beijing Capital (PEK) 13:55, nonstop, checked bag included | C10: 12 Nov | D10: 0.086805556 | E10: 1291 | F10: CNY | G10: =Compare!$B$6 | H10: =E10*G10*IF(F10="USD",Compare!$B$8,IF(F10="CNY",Compare!$B$9,IF(F10="HKD",Compare!$B$10,1))) | I10: =E10 | J10: =Compare!$B$7 | K10: =I10*J10*IF(F10="USD",Compare!$B$8,IF(F10="CNY",Compare!$B$9,IF(F10="HKD",Compare!$B$10,1))) | L10: Ctrip 22 Oct: ¥1,291 pp incl. tax – cheapest of 5 sources (Kiwi $200, Trip.com $203, SlickTrip $316 on 13 Nov, Google Flights unpriced). MIAT OM223 07:30 is ¥1,096 on Ctrip / $167 Kiwi / $172 Google / $154 SlickTrip but means a ~04:00 wake-up. Ctrip needs a Ctrip account (Alipay or a foreign card); Trip.com $203 is the fallback.
A11: Trains & border crossing
B12: High-speed rail G153 Beijing Chaoyang 17:27 → Shenyang 20:04, 2nd class | C12: 12 Nov (evening) | D12: 0.10902778 | E12: 369 | F12: CNY | G12: =Compare!$B$6 | H12: =E12*G12*IF(F12="USD",Compare!$B$8,IF(F12="CNY",Compare!$B$9,IF(F12="HKD",Compare!$B$10,1))) | I12: =E12 | J12: =Compare!$B$7 | K12: =I12*J12*IF(F12="USD",Compare!$B$8,IF(F12="CNY",Compare!$B$9,IF(F12="HKD",Compare!$B$10,1))) | L12: 12306 (queried 22 Oct for 5 Nov; fares fixed): ¥369. ChinaTicketOnline confirms G153 on 12 Nov, on sale 29 Oct 10:00. Leaves 3 h 30 min after landing; if the flight is on time, change at the station to G141 16:00 → Shenyang North 18:29 (¥369). Later trains: G155 18:35 / G143 18:48 (¥369–383). Ctrip train list (22 Oct, for 12 Nov) shows the same fares; 12go.asia resells at ~$90 for 1st class.
B13: Overnight train K1568 Shenyang 22:50 → Hohhot 17:02 (+1), hard sleeper (after the contest) | C13: 15–16 Nov | D13: 0.75833333 | E13: 304.5 | F13: CNY | G13: =Compare!$B$6 | H13: =E13*G13*IF(F13="USD",Compare!$B$8,IF(F13="CNY",Compare!$B$9,IF(F13="HKD",Compare!$B$10,1))) | I13: =E13 | J13: =Compare!$B$7 | K13: =I13*J13*IF(F13="USD",Compare!$B$8,IF(F13="CNY",Compare!$B$9,IF(F13="HKD",Compare!$B$10,1))) | L13: 12306 (5 Nov query): hard sleeper ¥304.5, hard seat ¥177.5, soft ¥476.5 (to Hohhot East 16:27: ¥296.5). ChinaTicketOnline confirms 15 Nov, on sale 1 Nov 09:30.
B14: Overnight train 4652 Hohhot 22:50 → Erenhot 06:50, hard sleeper | C14: 16–17 Nov | D14: 0.33333333 | E14: 115 | F14: CNY | G14: =Compare!$B$6 | H14: =E14*G14*IF(F14="USD",Compare!$B$8,IF(F14="CNY",Compare!$B$9,IF(F14="HKD",Compare!$B$10,1))) | I14: =E14 | J14: =Compare!$B$7 | K14: =I14*J14*IF(F14="USD",Compare!$B$8,IF(F14="CNY",Compare!$B$9,IF(F14="HKD",Compare!$B$10,1))) | L14: 12306 (5 Nov query): hard sleeper ¥115, hard seat ¥61. Daily; ChinaTicketOnline confirms 16 Nov, on sale 2 Nov 14:00. ~6 h wait in Hohhot after K1568 (dinner).
B15: Shared jeep Erenhot → Zamyn-Uud across the border | C15: 17 Nov (morning) | D15: 0.125 | E15: 100 | F15: CNY | G15: =Compare!$B$6 | H15: =E15*G15*IF(F15="USD",Compare!$B$8,IF(F15="CNY",Compare!$B$9,IF(F15="HKD",Compare!$B$10,1))) | I15: =E15 | J15: =Compare!$B$7 | K15: =I15*J15*IF(F15="USD",Compare!$B$8,IF(F15="CNY",Compare!$B$9,IF(F15="HKD",Compare!$B$10,1))) | L15: ASSUMPTION ¥50–110 pp (Wikivoyage, travel blogs); jeeps wait near Erenhot station. ~3 h includes both border posts (no visa needed for Mongolian passports). Confirm the border hours.
B16: UBTZ train 275 Zamyn-Uud 18:05 → Ulaanbaatar 09:20, platskart sleeper incl. bedding | C16: 17–18 Nov | D16: 0.63541667 | E16: 51400 | F16: MNT | G16: =Compare!$B$6 | H16: =E16*G16*IF(F16="USD",Compare!$B$8,IF(F16="CNY",Compare!$B$9,IF(F16="HKD",Compare!$B$10,1))) | I16: =E16 | J16: =Compare!$B$7 | K16: =I16*J16*IF(F16="USD",Compare!$B$8,IF(F16="CNY",Compare!$B$9,IF(F16="HKD",Compare!$B$10,1))) | L16: eticket.ubtz.mn 22 Oct: platskart ₮44,000 + bedding ₮7,400 (seat ₮26,000; kupe ₮73,400 + ₮7,400). Daily; 72 platskart berths free on 17 Nov.
A17: Accommodation
B18: Ji Hotel Sanhao Street, 55 Sanhao St (~940 m to NEU Nanhu, ~15 min walk): 2 Budget Twin rooms, King Koil mattresses, windows, floors 4–16 – a bed each | C18: 12–15 Nov (3 nights) | E18: 457 | F18: CNY | G18: 3 | H18: =E18*G18*IF(F18="USD",Compare!$B$8,IF(F18="CNY",Compare!$B$9,IF(F18="HKD",Compare!$B$10,1))) | I18: 457 | J18: 3 | K18: =I18*J18*IF(F18="USD",Compare!$B$8,IF(F18="CNY",Compare!$B$9,IF(F18="HKD",Compare!$B$10,1))) | L18: Trip.com 22 Oct: ¥1,371 for 2 rooms × 3 nights incl. taxes, free cancellation until 18:00 on 11 Nov (prepay); same price for 3 or 4 adults. 9.0 from 1,433 reviews; 16 m² rooms high in an office tower, above the street. Breakfast ¥40 optional.
A19: Meals & local transport
B20: Meals | C20: in destination | E20: 80 | F20: CNY | G20: =Compare!$B$6*$B$4 | H20: =E20*G20*IF(F20="USD",Compare!$B$8,IF(F20="CNY",Compare!$B$9,IF(F20="HKD",Compare!$B$10,1))) | I20: =E20 | J20: =Compare!$B$7*$B$4 | K20: =I20*J20*IF(F20="USD",Compare!$B$8,IF(F20="CNY",Compare!$B$9,IF(F20="HKD",Compare!$B$10,1))) | L20: ASSUMPTION 80 CNY/person/day; hosts usually provide some meals on contest days
B21: Local transport (metro, taxis) | C21: in destination | E21: 30 | F21: CNY | G21: =Compare!$B$6*$B$4 | H21: =E21*G21*IF(F21="USD",Compare!$B$8,IF(F21="CNY",Compare!$B$9,IF(F21="HKD",Compare!$B$10,1))) | I21: =E21 | J21: =Compare!$B$7*$B$4 | K21: =I21*J21*IF(F21="USD",Compare!$B$8,IF(F21="CNY",Compare!$B$9,IF(F21="HKD",Compare!$B$10,1))) | L21: ASSUMPTION 30 CNY/person/day
B22: Taxi PEK → Beijing Chaoyang station | C22: 12 Nov | E22: 120 | F22: CNY | G22: 1 | H22: =E22*G22*IF(F22="USD",Compare!$B$8,IF(F22="CNY",Compare!$B$9,IF(F22="HKD",Compare!$B$10,1))) | I22: =E22 | J22: 1 | K22: =I22*J22*IF(F22="USD",Compare!$B$8,IF(F22="CNY",Compare!$B$9,IF(F22="HKD",Compare!$B$10,1))) | L22: ASSUMPTION ~120 CNY per car, ~40 km (4 ppl may need an XL car)
A23: PAID PERSONALLY (university won't cover)
A24: Contest fee
B25: Shenyang regional registration fee (per team) | C25: pay when invited | E25: 1500 | F25: CNY | G25: 1 | H25: =E25*G25*IF(F25="USD",Compare!$B$8,IF(F25="CNY",Compare!$B$9,IF(F25="HKD",Compare!$B$10,1))) | I25: =E25 | J25: 1 | K25: =I25*J25*IF(F25="USD",Compare!$B$8,IF(F25="CNY",Compare!$B$9,IF(F25="HKD",Compare!$B$10,1))) | L25: ASSUMPTION: 1,500 CNY/team like recent EC regionals; the 2026 Shenyang invitation was not found on 22 Oct
A26: Other
B27: Taxi home → Chinggis Khaan airport (UB) | C27: 12 Nov | D27: 0.041666667 | E27: 100000 | F27: MNT | G27: 1 | H27: =E27*G27*IF(F27="USD",Compare!$B$8,IF(F27="CNY",Compare!$B$9,IF(F27="HKD",Compare!$B$10,1))) | I27: =E27 | J27: 1 | K27: =I27*J27*IF(F27="USD",Compare!$B$8,IF(F27="CNY",Compare!$B$9,IF(F27="HKD",Compare!$B$10,1))) | L27: ASSUMPTION 100k MNT per trip for the group
B28: Taxi Ulaanbaatar railway station → home | C28: 18 Nov | D28: 0.020833333 | E28: 30000 | F28: MNT | G28: 1 | H28: =E28*G28*IF(F28="USD",Compare!$B$8,IF(F28="CNY",Compare!$B$9,IF(F28="HKD",Compare!$B$10,1))) | I28: =E28 | J28: 1 | K28: =I28*J28*IF(F28="USD",Compare!$B$8,IF(F28="CNY",Compare!$B$9,IF(F28="HKD",Compare!$B$10,1))) | L28: ASSUMPTION ~30k MNT for the group (city trip)
B29: Travel medical insurance | E29: 30000 | F29: MNT | G29: =Compare!$B$6 | H29: =E29*G29*IF(F29="USD",Compare!$B$8,IF(F29="CNY",Compare!$B$9,IF(F29="HKD",Compare!$B$10,1))) | I29: =E29 | J29: =Compare!$B$7 | K29: =I29*J29*IF(F29="USD",Compare!$B$8,IF(F29="CNY",Compare!$B$9,IF(F29="HKD",Compare!$B$10,1))) | L29: ASSUMPTION ~30k MNT per person, Mongolian insurer
B30: Mobile data eSIM | E30: 10 | F30: USD | G30: =Compare!$B$6 | H30: =E30*G30*IF(F30="USD",Compare!$B$8,IF(F30="CNY",Compare!$B$9,IF(F30="HKD",Compare!$B$10,1))) | I30: =E30 | J30: =Compare!$B$7 | K30: =I30*J30*IF(F30="USD",Compare!$B$8,IF(F30="CNY",Compare!$B$9,IF(F30="HKD",Compare!$B$10,1))) | L30: ASSUMPTION ~$10 pp
B31: Visa | E31: 0 | F31: MNT | G31: =Compare!$B$6 | H31: =E31*G31*IF(F31="USD",Compare!$B$8,IF(F31="CNY",Compare!$B$9,IF(F31="HKD",Compare!$B$10,1))) | I31: =E31 | J31: =Compare!$B$7 | K31: =I31*J31*IF(F31="USD",Compare!$B$8,IF(F31="CNY",Compare!$B$9,IF(F31="HKD",Compare!$B$10,1))) | L31: Mongolian passports: visa-free (mainland China up to 30 days; Hong Kong up to 14 days)
H33: 3 people – UNFUNDED | K33: 4 people – FUNDED ₮12M
G34: University-paid subtotal | H34: =SUM(H9:H22) | K34: =SUM(K9:K22)
G35: Contingency | H35: =H34*Compare!$B$11 | K35: =K34*Compare!$B$11
G36: University-paid total incl. contingency | H36: =H34+H35 | K36: =K34+K35
G37: Funding left (negative = over) | H37: =Compare!$B$12-H36 | K37: =Compare!$B$5-K36
G38: Personal costs – team | H38: =SUM(H24:H31) | K38: =SUM(K24:K31)
G39: Out-of-pocket per person (personal + any overrun) | H39: =(H38+MAX(0,-H37))/Compare!$B$6 | K39: =(K38+MAX(0,-K37))/Compare!$B$7
G40: Whole trip cost (university + personal) | H40: =H36+H38 | K40: =K36+K38
G41: Time in planes & trains | H41: =SUM(D10:D10)+SUM(D12:D16) | K41: =SUM(D10:D10)+SUM(D12:D16)
A43: Key facts
A44: Contest | B44: Asia Shenyang Regional, 14–15 Nov 2026 (provisional; the 2026 invitation was not found on 22 Oct), Northeastern University Nanhu campus (2024 and 2025 venue). Assumed: day 1 registration + practice, contest 15 Nov 09:00–14:00, awards ~17:00.
A45: Why this plan | B45: Before the contest it is identical to 'Sleep value' (no alarm before ~08:00, three nights in twin rooms). After the contest it skips the Beijing flight: three night trains (two Chinese hard sleepers + a UBTZ platskart berth) cost less than the flight alone, so it is the cheapest sleep-safe plan.
A46: Trade-off | B46: Home on 18 Nov at 09:20 instead of 16 Nov 15:05 (2 more days, 2 more days of meals), ~6 h wait in Hohhot, a cold early-morning border crossing at Erenhot (dress for −15 °C). The jeep fare and border hours are not verified.
A47: Book | B47: Air China CA902 on Ctrip now (¥1,291; Trip.com $203 as fallback); hotel now; G153 on 12306 at 10:00 on 29 Oct; K1568 at 09:30 on 1 Nov; 4652 at 14:00 on 2 Nov; UBTZ 275 on eticket.ubtz.mn (on sale now).
A49: Day-by-day plan
A50: Date | B50: Sleep in | C50: What happens
A51: Thu 12 Nov | B51: Shenyang | C51: Wake ~08:00. Air China CA902 UB 11:50 → Beijing Capital 13:55; taxi to Beijing Chaoyang; G153 17:27 → Shenyang 20:04 (G141 16:00 if early); taxi to Ji Hotel Sanhao Street. Bed by ~23:00.
A52: Fri 13 Nov | B52: Shenyang | C52: Free rest day: no alarm, light practice, walk the ~15-minute route to the venue.
A53: Sat 14 Nov | B53: Shenyang | C53: Registration, opening and practice at NEU Nanhu. Lights out ~22:30.
A54: Sun 15 Nov | B54: Train (hard sleeper) | C54: CONTEST. Wake ~06:50, walk ~15 min. Check out before leaving, luggage stored at the hotel. Awards ~17:00; taxi to Shenyang station; K1568 22:50 hard sleeper → Hohhot.
A55: Mon 16 Nov | B55: Train (hard sleeper) | C55: Arrive Hohhot 17:02; dinner near the station; 4652 22:50 hard sleeper → Erenhot.
A56: Tue 17 Nov | B56: Train (platskart) | C56: Arrive Erenhot 06:50; shared jeep across the border to Zamyn-Uud; UBTZ 275 18:05 → Ulaanbaatar.
A57: Wed 18 Nov | B57: Home | C57: Arrive Ulaanbaatar 09:20; taxi home.
A59: Door-to-door travel times
A60: Date | B60: Leg | C60: Mode | D60: Expected time | E60: Notes
A61: 12 Nov | B61: Home → Chinggis Khaan airport | C61: Taxi (~50 km) | D61: 0.041666667 | E61: Leave ~09:15 for the 11:50 flight; wake ~08:00
A62: 12 Nov | B62: Ulaanbaatar → Beijing (PEK) | C62: Air China CA902 11:50–13:55 | D62: 0.086805556
A63: 12 Nov | B63: PEK arrival: immigration, bags | C63: — | D63: 0.03125 | E63: Estimate
A64: 12 Nov | B64: PEK → Beijing Chaoyang station | C64: Taxi (~40 km) | D64: 0.034722222 | E64: Estimate; at the station ~15:30, G153 at 17:27 (or G141 16:00)
A65: 12 Nov | B65: Beijing Chaoyang → Shenyang | C65: G153 2nd class 17:27–20:04 | D65: 0.10902778
A66: 12 Nov | B66: Shenyang station → hotel | C66: Taxi (~4 km) | D66: 0.013888889 | E66: Check in ~20:30
A67: 13–15 Nov | B67: Hotel ↔ NEU Nanhu (each way) | C67: Walk | D67: daily | E67: ~15 min walk (Ji Hotel, 940 m straight line)
A68: 15 Nov | B68: NEU Nanhu → Shenyang station | C68: Taxi | D68: 0.013888889
A69: 15–16 Nov | B69: Shenyang → Hohhot | C69: K1568 hard sleeper 22:50–17:02 | D69: 0.75833333 | E69: Overnight, after the contest
A70: 16–17 Nov | B70: Hohhot → Erenhot | C70: 4652 hard sleeper 22:50–06:50 | D70: 0.33333333 | E70: ~6 h wait in Hohhot first (not counted)
A71: 17 Nov | B71: Erenhot → Zamyn-Uud (border) | C71: Shared jeep | D71: 0.125 | E71: Estimate incl. both border posts
A72: 17–18 Nov | B72: Zamyn-Uud → Ulaanbaatar | C72: UBTZ 275 platskart 18:05–09:20 | D72: 0.63541667 | E72: Wait in Zamyn-Uud not counted
A73: 18 Nov | B73: Ulaanbaatar station → home | C73: Taxi | D73: 0.020833333
C75: Total door-to-door | D75: =SUM(D61:D73)

Sheet Shenyang – Overland out (seats)
A1: Shenyang – Overland out (seats)
A2: Cheapest way out found: UBTZ train to Zamyn-Uud, jeep across the border, trains via Jining South to Shenyang, all in seats; arrive on day 1 morning, one hotel night; K28 seat + Air China home.
A4: Days in destination (meals & local transport) | B4: 4 | C4: 12 Nov evening → 16 Nov midday
A5: Shared inputs are on the Compare sheet. Scroll down for the day-by-day plan and door-to-door travel times.
A7: Category | B7: Item | C7: Date | D7: Travel time | E7: Unit cost (3 ppl) | F7: Currency | G7: Qty (3 ppl) | H7: Total MNT – 3 people | I7: Unit cost (4 ppl) | J7: Qty (4 ppl) | K7: Total MNT – 4 people | L7: Source / notes
A8: PAID BY UNIVERSITY
A9: Flights
B10: Air China CA955 Beijing Capital (PEK) 12:55 → Ulaanbaatar 15:05, nonstop | C10: 16 Nov | D10: 0.090277778 | E10: 171 | F10: USD | G10: =Compare!$B$6 | H10: =E10*G10*IF(F10="USD",Compare!$B$8,IF(F10="CNY",Compare!$B$9,IF(F10="HKD",Compare!$B$10,1))) | I10: =E10 | J10: =Compare!$B$7 | K10: =I10*J10*IF(F10="USD",Compare!$B$8,IF(F10="CNY",Compare!$B$9,IF(F10="HKD",Compare!$B$10,1))) | L10: Trip.com 22 Oct: US$171 pp, cheapest that day (MIAT OM224 11:30 US$193 on Trip.com / $176 on SlickTrip; Air China 08:25 $215; Capital + Hunnu via Erenhot $196)
A11: Trains & border crossing
B12: UBTZ train 276 Ulaanbaatar 16:40 → Zamyn-Uud 07:20, seat (общий) | C12: 12–13 Nov | D12: 0.61111111 | E12: 26000 | F12: MNT | G12: =Compare!$B$6 | H12: =E12*G12*IF(F12="USD",Compare!$B$8,IF(F12="CNY",Compare!$B$9,IF(F12="HKD",Compare!$B$10,1))) | I12: =E12 | J12: =Compare!$B$7 | K12: =I12*J12*IF(F12="USD",Compare!$B$8,IF(F12="CNY",Compare!$B$9,IF(F12="HKD",Compare!$B$10,1))) | L12: eticket.ubtz.mn 22 Oct: daily; seat ₮26,000 (69 free on 12 Nov); platskart ₮44,000 + bedding ₮7,400; kupe ₮73,400 + ₮7,400. On sale now.
B13: Shared jeep Zamyn-Uud → Erenhot across the border | C13: 13 Nov (morning) | D13: 0.125 | E13: 100 | F13: CNY | G13: =Compare!$B$6 | H13: =E13*G13*IF(F13="USD",Compare!$B$8,IF(F13="CNY",Compare!$B$9,IF(F13="HKD",Compare!$B$10,1))) | I13: =E13 | J13: =Compare!$B$7 | K13: =I13*J13*IF(F13="USD",Compare!$B$8,IF(F13="CNY",Compare!$B$9,IF(F13="HKD",Compare!$B$10,1))) | L13: ASSUMPTION ¥50–110 pp (Wikivoyage, travel blogs); ~3 h with both border posts. Must reach Erenhot station for 12:45 – the next train (6858 13:48) misses T301. Border hours not verified.
B14: Train 4654 Erenhot 12:45 → Jining South 18:11, hard seat | C14: 13 Nov | D14: 0.22638889 | E14: 44.5 | F14: CNY | G14: =Compare!$B$6 | H14: =E14*G14*IF(F14="USD",Compare!$B$8,IF(F14="CNY",Compare!$B$9,IF(F14="HKD",Compare!$B$10,1))) | I14: =E14 | J14: =Compare!$B$7 | K14: =I14*J14*IF(F14="USD",Compare!$B$8,IF(F14="CNY",Compare!$B$9,IF(F14="HKD",Compare!$B$10,1))) | L14: 12306 (5 Nov query): seat ¥44.5, hard sleeper ¥90.5. ChinaTicketOnline confirms 11 and 13 Nov; on sale 30 Oct 15:00 for 13 Nov.
B15: Overnight train T301 Jining South 19:30 → Shenyang 10:16, hard seat | C15: 13–14 Nov | D15: 0.61527778 | E15: 163.5 | F15: CNY | G15: =Compare!$B$6 | H15: =E15*G15*IF(F15="USD",Compare!$B$8,IF(F15="CNY",Compare!$B$9,IF(F15="HKD",Compare!$B$10,1))) | I15: =E15 | J15: =Compare!$B$7 | K15: =I15*J15*IF(F15="USD",Compare!$B$8,IF(F15="CNY",Compare!$B$9,IF(F15="HKD",Compare!$B$10,1))) | L15: 12306 (5 Nov query): seat ¥163.5, hard sleeper ¥280.5, soft ¥438.5; 1 h 19 min change at Jining South. ChinaTicketOnline confirms 13 Nov, on sale 30 Oct 15:00. Also K1567 17:31 → 09:38 (same fares).
B16: Overnight train K28 Shenyang 22:24 → Beijing 08:40, hard seat (after the contest) | C16: 15 Nov (night) | D16: 0.42777778 | E16: 112 | F16: CNY | G16: =Compare!$B$6 | H16: =E16*G16*IF(F16="USD",Compare!$B$8,IF(F16="CNY",Compare!$B$9,IF(F16="HKD",Compare!$B$10,1))) | I16: =E16 | J16: =Compare!$B$7 | K16: =I16*J16*IF(F16="USD",Compare!$B$8,IF(F16="CNY",Compare!$B$9,IF(F16="HKD",Compare!$B$10,1))) | L16: 12306 (5 Nov query): hard seat ¥112 (hard sleeper ¥194). Cheapest train that still makes the 12:55 flight (K96 23:39 ¥102 arrives 11:19 – too late). Lie-flat upgrade: K54 Shenyang North 22:00 → 06:58 hard sleeper ¥171 (+¥59 pp). On sale 1 Nov 09:30 (ChinaTicketOnline confirms 15 Nov).
A17: Accommodation
B18: Ji Hotel Sanhao Street, 55 Sanhao St (~940 m to NEU Nanhu, ~15 min walk): 2 Budget Twin rooms, King Koil mattresses, windows, floors 4–16 – a bed each | C18: 14–15 Nov (1 night) | E18: 457 | F18: CNY | G18: 1 | H18: =E18*G18*IF(F18="USD",Compare!$B$8,IF(F18="CNY",Compare!$B$9,IF(F18="HKD",Compare!$B$10,1))) | I18: 457 | J18: 1 | K18: =I18*J18*IF(F18="USD",Compare!$B$8,IF(F18="CNY",Compare!$B$9,IF(F18="HKD",Compare!$B$10,1))) | L18: Trip.com 22 Oct: ¥457 for 2 Budget Twin rooms × 1 night (14–15 Nov) incl. taxes, free cancellation until 18:00 on 13 Nov; same hotel as 'Sleep value' (9.0, King Koil mattresses).
A19: Meals & local transport
B20: Meals | C20: in destination | E20: 80 | F20: CNY | G20: =Compare!$B$6*$B$4 | H20: =E20*G20*IF(F20="USD",Compare!$B$8,IF(F20="CNY",Compare!$B$9,IF(F20="HKD",Compare!$B$10,1))) | I20: =E20 | J20: =Compare!$B$7*$B$4 | K20: =I20*J20*IF(F20="USD",Compare!$B$8,IF(F20="CNY",Compare!$B$9,IF(F20="HKD",Compare!$B$10,1))) | L20: ASSUMPTION 80 CNY/person/day; hosts usually provide some meals on contest days
B21: Local transport (metro, taxis) | C21: in destination | E21: 30 | F21: CNY | G21: =Compare!$B$6*$B$4 | H21: =E21*G21*IF(F21="USD",Compare!$B$8,IF(F21="CNY",Compare!$B$9,IF(F21="HKD",Compare!$B$10,1))) | I21: =E21 | J21: =Compare!$B$7*$B$4 | K21: =I21*J21*IF(F21="USD",Compare!$B$8,IF(F21="CNY",Compare!$B$9,IF(F21="HKD",Compare!$B$10,1))) | L21: ASSUMPTION 30 CNY/person/day
B22: Metro line 2 + Airport Express, Beijing station → PEK T3 | C22: 16 Nov | E22: 30 | F22: CNY | G22: =Compare!$B$6 | H22: =E22*G22*IF(F22="USD",Compare!$B$8,IF(F22="CNY",Compare!$B$9,IF(F22="HKD",Compare!$B$10,1))) | I22: =E22 | J22: =Compare!$B$7 | K22: =I22*J22*IF(F22="USD",Compare!$B$8,IF(F22="CNY",Compare!$B$9,IF(F22="HKD",Compare!$B$10,1))) | L22: ASSUMPTION Airport Express ¥25 + metro ¥4–5 pp
A23: PAID PERSONALLY (university won't cover)
A24: Contest fee
B25: Shenyang regional registration fee (per team) | C25: pay when invited | E25: 1500 | F25: CNY | G25: 1 | H25: =E25*G25*IF(F25="USD",Compare!$B$8,IF(F25="CNY",Compare!$B$9,IF(F25="HKD",Compare!$B$10,1))) | I25: =E25 | J25: 1 | K25: =I25*J25*IF(F25="USD",Compare!$B$8,IF(F25="CNY",Compare!$B$9,IF(F25="HKD",Compare!$B$10,1))) | L25: ASSUMPTION: 1,500 CNY/team like recent EC regionals; the 2026 Shenyang invitation was not found on 22 Oct
A26: Other
B27: Taxi home → Ulaanbaatar railway station | C27: 12 Nov | D27: 0.020833333 | E27: 30000 | F27: MNT | G27: 1 | H27: =E27*G27*IF(F27="USD",Compare!$B$8,IF(F27="CNY",Compare!$B$9,IF(F27="HKD",Compare!$B$10,1))) | I27: =E27 | J27: 1 | K27: =I27*J27*IF(F27="USD",Compare!$B$8,IF(F27="CNY",Compare!$B$9,IF(F27="HKD",Compare!$B$10,1))) | L27: ASSUMPTION ~30k MNT for the group (city trip)
B28: Taxi Chinggis Khaan airport → home (UB) | C28: 16 Nov | D28: 0.041666667 | E28: 100000 | F28: MNT | G28: 1 | H28: =E28*G28*IF(F28="USD",Compare!$B$8,IF(F28="CNY",Compare!$B$9,IF(F28="HKD",Compare!$B$10,1))) | I28: =E28 | J28: 1 | K28: =I28*J28*IF(F28="USD",Compare!$B$8,IF(F28="CNY",Compare!$B$9,IF(F28="HKD",Compare!$B$10,1))) | L28: ASSUMPTION 100k MNT per trip for the group
B29: Travel medical insurance | E29: 30000 | F29: MNT | G29: =Compare!$B$6 | H29: =E29*G29*IF(F29="USD",Compare!$B$8,IF(F29="CNY",Compare!$B$9,IF(F29="HKD",Compare!$B$10,1))) | I29: =E29 | J29: =Compare!$B$7 | K29: =I29*J29*IF(F29="USD",Compare!$B$8,IF(F29="CNY",Compare!$B$9,IF(F29="HKD",Compare!$B$10,1))) | L29: ASSUMPTION ~30k MNT per person, Mongolian insurer
B30: Mobile data eSIM | E30: 10 | F30: USD | G30: =Compare!$B$6 | H30: =E30*G30*IF(F30="USD",Compare!$B$8,IF(F30="CNY",Compare!$B$9,IF(F30="HKD",Compare!$B$10,1))) | I30: =E30 | J30: =Compare!$B$7 | K30: =I30*J30*IF(F30="USD",Compare!$B$8,IF(F30="CNY",Compare!$B$9,IF(F30="HKD",Compare!$B$10,1))) | L30: ASSUMPTION ~$10 pp
B31: Visa | E31: 0 | F31: MNT | G31: =Compare!$B$6 | H31: =E31*G31*IF(F31="USD",Compare!$B$8,IF(F31="CNY",Compare!$B$9,IF(F31="HKD",Compare!$B$10,1))) | I31: =E31 | J31: =Compare!$B$7 | K31: =I31*J31*IF(F31="USD",Compare!$B$8,IF(F31="CNY",Compare!$B$9,IF(F31="HKD",Compare!$B$10,1))) | L31: Mongolian passports: visa-free (mainland China up to 30 days; Hong Kong up to 14 days)
H33: 3 people – UNFUNDED | K33: 4 people – FUNDED ₮12M
G34: University-paid subtotal | H34: =SUM(H9:H22) | K34: =SUM(K9:K22)
G35: Contingency | H35: =H34*Compare!$B$11 | K35: =K34*Compare!$B$11
G36: University-paid total incl. contingency | H36: =H34+H35 | K36: =K34+K35
G37: Funding left (negative = over) | H37: =Compare!$B$12-H36 | K37: =Compare!$B$5-K36
G38: Personal costs – team | H38: =SUM(H24:H31) | K38: =SUM(K24:K31)
G39: Out-of-pocket per person (personal + any overrun) | H39: =(H38+MAX(0,-H37))/Compare!$B$6 | K39: =(K38+MAX(0,-K37))/Compare!$B$7
G40: Whole trip cost (university + personal) | H40: =H36+H38 | K40: =K36+K38
G41: Time in planes & trains | H41: =SUM(D10:D10)+SUM(D12:D16) | K41: =SUM(D10:D10)+SUM(D12:D16)
A43: Key facts
A44: Contest | B44: Asia Shenyang Regional, 14–15 Nov 2026 (provisional; the 2026 invitation was not found on 22 Oct), Northeastern University Nanhu campus (2024 and 2025 venue). Assumed: day 1 registration + practice, contest 15 Nov 09:00–14:00, awards ~17:00.
A45: Why this plan | B45: No flight on the way out: ~₮0.19M per person to Shenyang, a fifth of the Air China route. Cheaper way out than the Air China + G153 route of 'Sleep value' (₮0.91M per person); the rest of the trip is the same (Ji Hotel twin rooms, K28 hard seat + Air China 12:55 home), with hotel nights set by the arrival time.
A46: Trade-off | B46: Two nights sitting up on trains in a row, right before day 1 (POOR for sleep); arrive 10:16 on registration day. The jeep fare and border hours are not verified, and missing the 12:45 train costs a day. Cold Gobi border in mid-November.
A47: Book | B47: UBTZ 276 on eticket.ubtz.mn (on sale now); 4654 and T301 on 12306 at 15:00 on 30 Oct; K28 on 12306 at 09:30 on 1 Nov; Air China home on Trip.com.
A49: Day-by-day plan
A50: Date | B50: Sleep in | C50: What happens
A51: Thu 12 Nov | B51: Train | C51: Taxi to Ulaanbaatar station; UBTZ 276 16:40 → Zamyn-Uud (overnight).
A52: Fri 13 Nov | B52: Train | C52: Arrive Zamyn-Uud 07:20; shared jeep across the border to Erenhot (at the station by ~12:00); 4654 12:45 → Jining South 18:11; T301 19:30 → Shenyang (overnight).
A53: Sat 14 Nov | B53: Shenyang | C53: Arrive Shenyang 10:16; taxi to NEU Nanhu for registration and practice; check in at Ji Hotel. Lights out ~22:30.
A54: Sun 15 Nov | B54: Train (seat) | C54: CONTEST. Wake ~06:50, walk ~15 min. Check out before leaving, luggage stored at the hotel. Awards ~17:00; taxi to Shenyang station; K28 22:24 hard seat → Beijing 08:40.
A55: Mon 16 Nov | B55: Home | C55: Metro line 2 + Airport Express to PEK T3 (~1 h). Air China 12:55 → UB 15:05.
A57: Door-to-door travel times
A58: Date | B58: Leg | C58: Mode | D58: Expected time | E58: Notes
A59: 12 Nov | B59: Home → Ulaanbaatar railway station | C59: Taxi | D59: 0.020833333 | E59: Leave ~16:00
A60: 12–13 Nov | B60: Ulaanbaatar → Zamyn-Uud | C60: UBTZ 276 16:40–07:20 | D60: 0.61111111 | E60: Overnight
A61: 13 Nov | B61: Zamyn-Uud → Erenhot (border) | C61: Shared jeep | D61: 0.125 | E61: Estimate incl. both border posts
A62: 13 Nov | B62: Erenhot → Jining South | C62: 4654 hard seat 12:45–18:11 | D62: 0.22638889
A63: 13–14 Nov | B63: Jining South → Shenyang | C63: T301 19:30–10:16 | D63: 0.61527778 | E63: 1 h 19 min change; overnight
A64: 14 Nov | B64: Shenyang station → NEU Nanhu | C64: Taxi | D64: 0.013888889 | E64: Registration day
A65: 15 Nov | B65: NEU Nanhu → Shenyang station | C65: Taxi | D65: 0.013888889
A66: 15–16 Nov | B66: Shenyang → Beijing | C66: K28 hard seat 22:24–08:40 | D66: 0.42777778 | E66: Overnight, after the contest
A67: 16 Nov | B67: Beijing station → PEK | C67: Metro line 2 + Airport Express | D67: 0.041666667 | E67: Be at PEK by ~10:55
A68: 16 Nov | B68: Beijing (PEK) → Ulaanbaatar | C68: Air China 12:55–15:05 | D68: 0.090277778
A69: 16 Nov | B69: Chinggis Khaan airport → home | C69: Taxi | D69: 0.041666667
C71: Total door-to-door | D71: =SUM(D59:D69)

Sheet Shenyang – Overland out, berths
A1: Shenyang – Overland out, berths
A2: Same overland way out as 'Overland out (seats)' with a platskart berth to Zamyn-Uud and a hard sleeper on T301; arrive on day 1 morning, one hotel night; K28 seat + Air China home.
A4: Days in destination (meals & local transport) | B4: 4 | C4: 12 Nov evening → 16 Nov midday
A5: Shared inputs are on the Compare sheet. Scroll down for the day-by-day plan and door-to-door travel times.
A7: Category | B7: Item | C7: Date | D7: Travel time | E7: Unit cost (3 ppl) | F7: Currency | G7: Qty (3 ppl) | H7: Total MNT – 3 people | I7: Unit cost (4 ppl) | J7: Qty (4 ppl) | K7: Total MNT – 4 people | L7: Source / notes
A8: PAID BY UNIVERSITY
A9: Flights
B10: Air China CA955 Beijing Capital (PEK) 12:55 → Ulaanbaatar 15:05, nonstop | C10: 16 Nov | D10: 0.090277778 | E10: 171 | F10: USD | G10: =Compare!$B$6 | H10: =E10*G10*IF(F10="USD",Compare!$B$8,IF(F10="CNY",Compare!$B$9,IF(F10="HKD",Compare!$B$10,1))) | I10: =E10 | J10: =Compare!$B$7 | K10: =I10*J10*IF(F10="USD",Compare!$B$8,IF(F10="CNY",Compare!$B$9,IF(F10="HKD",Compare!$B$10,1))) | L10: Trip.com 22 Oct: US$171 pp, cheapest that day (MIAT OM224 11:30 US$193 on Trip.com / $176 on SlickTrip; Air China 08:25 $215; Capital + Hunnu via Erenhot $196)
A11: Trains & border crossing
B12: UBTZ train 276 Ulaanbaatar 16:40 → Zamyn-Uud 07:20, platskart berth incl. bedding | C12: 12–13 Nov | D12: 0.61111111 | E12: 51400 | F12: MNT | G12: =Compare!$B$6 | H12: =E12*G12*IF(F12="USD",Compare!$B$8,IF(F12="CNY",Compare!$B$9,IF(F12="HKD",Compare!$B$10,1))) | I12: =E12 | J12: =Compare!$B$7 | K12: =I12*J12*IF(F12="USD",Compare!$B$8,IF(F12="CNY",Compare!$B$9,IF(F12="HKD",Compare!$B$10,1))) | L12: eticket.ubtz.mn 22 Oct: daily; seat ₮26,000 (69 free on 12 Nov); platskart ₮44,000 + bedding ₮7,400; kupe ₮73,400 + ₮7,400. On sale now.
B13: Shared jeep Zamyn-Uud → Erenhot across the border | C13: 13 Nov (morning) | D13: 0.125 | E13: 100 | F13: CNY | G13: =Compare!$B$6 | H13: =E13*G13*IF(F13="USD",Compare!$B$8,IF(F13="CNY",Compare!$B$9,IF(F13="HKD",Compare!$B$10,1))) | I13: =E13 | J13: =Compare!$B$7 | K13: =I13*J13*IF(F13="USD",Compare!$B$8,IF(F13="CNY",Compare!$B$9,IF(F13="HKD",Compare!$B$10,1))) | L13: ASSUMPTION ¥50–110 pp (Wikivoyage, travel blogs); ~3 h with both border posts. Must reach Erenhot station for 12:45 – the next train (6858 13:48) misses T301. Border hours not verified.
B14: Train 4654 Erenhot 12:45 → Jining South 18:11, hard seat | C14: 13 Nov | D14: 0.22638889 | E14: 44.5 | F14: CNY | G14: =Compare!$B$6 | H14: =E14*G14*IF(F14="USD",Compare!$B$8,IF(F14="CNY",Compare!$B$9,IF(F14="HKD",Compare!$B$10,1))) | I14: =E14 | J14: =Compare!$B$7 | K14: =I14*J14*IF(F14="USD",Compare!$B$8,IF(F14="CNY",Compare!$B$9,IF(F14="HKD",Compare!$B$10,1))) | L14: 12306 (5 Nov query): seat ¥44.5, hard sleeper ¥90.5. ChinaTicketOnline confirms 11 and 13 Nov; on sale 30 Oct 15:00 for 13 Nov.
B15: Overnight train T301 Jining South 19:30 → Shenyang 10:16, hard sleeper | C15: 13–14 Nov | D15: 0.61527778 | E15: 280.5 | F15: CNY | G15: =Compare!$B$6 | H15: =E15*G15*IF(F15="USD",Compare!$B$8,IF(F15="CNY",Compare!$B$9,IF(F15="HKD",Compare!$B$10,1))) | I15: =E15 | J15: =Compare!$B$7 | K15: =I15*J15*IF(F15="USD",Compare!$B$8,IF(F15="CNY",Compare!$B$9,IF(F15="HKD",Compare!$B$10,1))) | L15: 12306 (5 Nov query): seat ¥163.5, hard sleeper ¥280.5, soft ¥438.5; 1 h 19 min change at Jining South. ChinaTicketOnline confirms 13 Nov, on sale 30 Oct 15:00. Also K1567 17:31 → 09:38 (same fares).
B16: Overnight train K28 Shenyang 22:24 → Beijing 08:40, hard seat (after the contest) | C16: 15 Nov (night) | D16: 0.42777778 | E16: 112 | F16: CNY | G16: =Compare!$B$6 | H16: =E16*G16*IF(F16="USD",Compare!$B$8,IF(F16="CNY",Compare!$B$9,IF(F16="HKD",Compare!$B$10,1))) | I16: =E16 | J16: =Compare!$B$7 | K16: =I16*J16*IF(F16="USD",Compare!$B$8,IF(F16="CNY",Compare!$B$9,IF(F16="HKD",Compare!$B$10,1))) | L16: 12306 (5 Nov query): hard seat ¥112 (hard sleeper ¥194). Cheapest train that still makes the 12:55 flight (K96 23:39 ¥102 arrives 11:19 – too late). Lie-flat upgrade: K54 Shenyang North 22:00 → 06:58 hard sleeper ¥171 (+¥59 pp). On sale 1 Nov 09:30 (ChinaTicketOnline confirms 15 Nov).
A17: Accommodation
B18: Ji Hotel Sanhao Street, 55 Sanhao St (~940 m to NEU Nanhu, ~15 min walk): 2 Budget Twin rooms, King Koil mattresses, windows, floors 4–16 – a bed each | C18: 14–15 Nov (1 night) | E18: 457 | F18: CNY | G18: 1 | H18: =E18*G18*IF(F18="USD",Compare!$B$8,IF(F18="CNY",Compare!$B$9,IF(F18="HKD",Compare!$B$10,1))) | I18: 457 | J18: 1 | K18: =I18*J18*IF(F18="USD",Compare!$B$8,IF(F18="CNY",Compare!$B$9,IF(F18="HKD",Compare!$B$10,1))) | L18: Trip.com 22 Oct: ¥457 for 2 Budget Twin rooms × 1 night (14–15 Nov) incl. taxes, free cancellation until 18:00 on 13 Nov; same hotel as 'Sleep value' (9.0, King Koil mattresses).
A19: Meals & local transport
B20: Meals | C20: in destination | E20: 80 | F20: CNY | G20: =Compare!$B$6*$B$4 | H20: =E20*G20*IF(F20="USD",Compare!$B$8,IF(F20="CNY",Compare!$B$9,IF(F20="HKD",Compare!$B$10,1))) | I20: =E20 | J20: =Compare!$B$7*$B$4 | K20: =I20*J20*IF(F20="USD",Compare!$B$8,IF(F20="CNY",Compare!$B$9,IF(F20="HKD",Compare!$B$10,1))) | L20: ASSUMPTION 80 CNY/person/day; hosts usually provide some meals on contest days
B21: Local transport (metro, taxis) | C21: in destination | E21: 30 | F21: CNY | G21: =Compare!$B$6*$B$4 | H21: =E21*G21*IF(F21="USD",Compare!$B$8,IF(F21="CNY",Compare!$B$9,IF(F21="HKD",Compare!$B$10,1))) | I21: =E21 | J21: =Compare!$B$7*$B$4 | K21: =I21*J21*IF(F21="USD",Compare!$B$8,IF(F21="CNY",Compare!$B$9,IF(F21="HKD",Compare!$B$10,1))) | L21: ASSUMPTION 30 CNY/person/day
B22: Metro line 2 + Airport Express, Beijing station → PEK T3 | C22: 16 Nov | E22: 30 | F22: CNY | G22: =Compare!$B$6 | H22: =E22*G22*IF(F22="USD",Compare!$B$8,IF(F22="CNY",Compare!$B$9,IF(F22="HKD",Compare!$B$10,1))) | I22: =E22 | J22: =Compare!$B$7 | K22: =I22*J22*IF(F22="USD",Compare!$B$8,IF(F22="CNY",Compare!$B$9,IF(F22="HKD",Compare!$B$10,1))) | L22: ASSUMPTION Airport Express ¥25 + metro ¥4–5 pp
A23: PAID PERSONALLY (university won't cover)
A24: Contest fee
B25: Shenyang regional registration fee (per team) | C25: pay when invited | E25: 1500 | F25: CNY | G25: 1 | H25: =E25*G25*IF(F25="USD",Compare!$B$8,IF(F25="CNY",Compare!$B$9,IF(F25="HKD",Compare!$B$10,1))) | I25: =E25 | J25: 1 | K25: =I25*J25*IF(F25="USD",Compare!$B$8,IF(F25="CNY",Compare!$B$9,IF(F25="HKD",Compare!$B$10,1))) | L25: ASSUMPTION: 1,500 CNY/team like recent EC regionals; the 2026 Shenyang invitation was not found on 22 Oct
A26: Other
B27: Taxi home → Ulaanbaatar railway station | C27: 12 Nov | D27: 0.020833333 | E27: 30000 | F27: MNT | G27: 1 | H27: =E27*G27*IF(F27="USD",Compare!$B$8,IF(F27="CNY",Compare!$B$9,IF(F27="HKD",Compare!$B$10,1))) | I27: =E27 | J27: 1 | K27: =I27*J27*IF(F27="USD",Compare!$B$8,IF(F27="CNY",Compare!$B$9,IF(F27="HKD",Compare!$B$10,1))) | L27: ASSUMPTION ~30k MNT for the group (city trip)
B28: Taxi Chinggis Khaan airport → home (UB) | C28: 16 Nov | D28: 0.041666667 | E28: 100000 | F28: MNT | G28: 1 | H28: =E28*G28*IF(F28="USD",Compare!$B$8,IF(F28="CNY",Compare!$B$9,IF(F28="HKD",Compare!$B$10,1))) | I28: =E28 | J28: 1 | K28: =I28*J28*IF(F28="USD",Compare!$B$8,IF(F28="CNY",Compare!$B$9,IF(F28="HKD",Compare!$B$10,1))) | L28: ASSUMPTION 100k MNT per trip for the group
B29: Travel medical insurance | E29: 30000 | F29: MNT | G29: =Compare!$B$6 | H29: =E29*G29*IF(F29="USD",Compare!$B$8,IF(F29="CNY",Compare!$B$9,IF(F29="HKD",Compare!$B$10,1))) | I29: =E29 | J29: =Compare!$B$7 | K29: =I29*J29*IF(F29="USD",Compare!$B$8,IF(F29="CNY",Compare!$B$9,IF(F29="HKD",Compare!$B$10,1))) | L29: ASSUMPTION ~30k MNT per person, Mongolian insurer
B30: Mobile data eSIM | E30: 10 | F30: USD | G30: =Compare!$B$6 | H30: =E30*G30*IF(F30="USD",Compare!$B$8,IF(F30="CNY",Compare!$B$9,IF(F30="HKD",Compare!$B$10,1))) | I30: =E30 | J30: =Compare!$B$7 | K30: =I30*J30*IF(F30="USD",Compare!$B$8,IF(F30="CNY",Compare!$B$9,IF(F30="HKD",Compare!$B$10,1))) | L30: ASSUMPTION ~$10 pp
B31: Visa | E31: 0 | F31: MNT | G31: =Compare!$B$6 | H31: =E31*G31*IF(F31="USD",Compare!$B$8,IF(F31="CNY",Compare!$B$9,IF(F31="HKD",Compare!$B$10,1))) | I31: =E31 | J31: =Compare!$B$7 | K31: =I31*J31*IF(F31="USD",Compare!$B$8,IF(F31="CNY",Compare!$B$9,IF(F31="HKD",Compare!$B$10,1))) | L31: Mongolian passports: visa-free (mainland China up to 30 days; Hong Kong up to 14 days)
H33: 3 people – UNFUNDED | K33: 4 people – FUNDED ₮12M
G34: University-paid subtotal | H34: =SUM(H9:H22) | K34: =SUM(K9:K22)
G35: Contingency | H35: =H34*Compare!$B$11 | K35: =K34*Compare!$B$11
G36: University-paid total incl. contingency | H36: =H34+H35 | K36: =K34+K35
G37: Funding left (negative = over) | H37: =Compare!$B$12-H36 | K37: =Compare!$B$5-K36
G38: Personal costs – team | H38: =SUM(H24:H31) | K38: =SUM(K24:K31)
G39: Out-of-pocket per person (personal + any overrun) | H39: =(H38+MAX(0,-H37))/Compare!$B$6 | K39: =(K38+MAX(0,-K37))/Compare!$B$7
G40: Whole trip cost (university + personal) | H40: =H36+H38 | K40: =K36+K38
G41: Time in planes & trains | H41: =SUM(D10:D10)+SUM(D12:D16) | K41: =SUM(D10:D10)+SUM(D12:D16)
A43: Key facts
A44: Contest | B44: Asia Shenyang Regional, 14–15 Nov 2026 (provisional; the 2026 invitation was not found on 22 Oct), Northeastern University Nanhu campus (2024 and 2025 venue). Assumed: day 1 registration + practice, contest 15 Nov 09:00–14:00, awards ~17:00.
A45: Why this plan | B45: Overland for ~₮0.28M per person with a berth both nights. Cheaper way out than the Air China + G153 route of 'Sleep value' (₮0.91M per person); the rest of the trip is the same (Ji Hotel twin rooms, K28 hard seat + Air China 12:55 home), with hotel nights set by the arrival time.
A46: Trade-off | B46: Two nights sitting up on trains in a row, right before day 1 (POOR for sleep); arrive 10:16 on registration day. The jeep fare and border hours are not verified, and missing the 12:45 train costs a day. Cold Gobi border in mid-November.
A47: Book | B47: UBTZ 276 on eticket.ubtz.mn (on sale now); 4654 and T301 on 12306 at 15:00 on 30 Oct; K28 on 12306 at 09:30 on 1 Nov; Air China home on Trip.com.
A49: Day-by-day plan
A50: Date | B50: Sleep in | C50: What happens
A51: Thu 12 Nov | B51: Train | C51: Taxi to Ulaanbaatar station; UBTZ 276 16:40 → Zamyn-Uud (overnight).
A52: Fri 13 Nov | B52: Train | C52: Arrive Zamyn-Uud 07:20; shared jeep across the border to Erenhot (at the station by ~12:00); 4654 12:45 → Jining South 18:11; T301 19:30 → Shenyang (overnight).
A53: Sat 14 Nov | B53: Shenyang | C53: Arrive Shenyang 10:16; taxi to NEU Nanhu for registration and practice; check in at Ji Hotel. Lights out ~22:30.
A54: Sun 15 Nov | B54: Train (seat) | C54: CONTEST. Wake ~06:50, walk ~15 min. Check out before leaving, luggage stored at the hotel. Awards ~17:00; taxi to Shenyang station; K28 22:24 hard seat → Beijing 08:40.
A55: Mon 16 Nov | B55: Home | C55: Metro line 2 + Airport Express to PEK T3 (~1 h). Air China 12:55 → UB 15:05.
A57: Door-to-door travel times
A58: Date | B58: Leg | C58: Mode | D58: Expected time | E58: Notes
A59: 12 Nov | B59: Home → Ulaanbaatar railway station | C59: Taxi | D59: 0.020833333 | E59: Leave ~16:00
A60: 12–13 Nov | B60: Ulaanbaatar → Zamyn-Uud | C60: UBTZ 276 platskart 16:40–07:20 | D60: 0.61111111 | E60: Overnight
A61: 13 Nov | B61: Zamyn-Uud → Erenhot (border) | C61: Shared jeep | D61: 0.125 | E61: Estimate incl. both border posts
A62: 13 Nov | B62: Erenhot → Jining South | C62: 4654 hard seat 12:45–18:11 | D62: 0.22638889
A63: 13–14 Nov | B63: Jining South → Shenyang | C63: T301 hard sleeper 19:30–10:16 | D63: 0.61527778 | E63: 1 h 19 min change; overnight
A64: 14 Nov | B64: Shenyang station → NEU Nanhu | C64: Taxi | D64: 0.013888889 | E64: Registration day
A65: 15 Nov | B65: NEU Nanhu → Shenyang station | C65: Taxi | D65: 0.013888889
A66: 15–16 Nov | B66: Shenyang → Beijing | C66: K28 hard seat 22:24–08:40 | D66: 0.42777778 | E66: Overnight, after the contest
A67: 16 Nov | B67: Beijing station → PEK | C67: Metro line 2 + Airport Express | D67: 0.041666667 | E67: Be at PEK by ~10:55
A68: 16 Nov | B68: Beijing (PEK) → Ulaanbaatar | C68: Air China 12:55–15:05 | D68: 0.090277778
A69: 16 Nov | B69: Chinggis Khaan airport → home | C69: Taxi | D69: 0.041666667
C71: Total door-to-door | D71: =SUM(D59:D69)

Sheet Shenyang – Manzhouli seats
A1: Shenyang – Manzhouli seats
A2: Hunnu Air to Manzhouli (Wed 11 Nov), K7092 overnight to Harbin and K928 to Shenyang, both in hard seats; three hotel nights before the contest; K28 seat + Air China home.
A4: Days in destination (meals & local transport) | B4: 5 | C4: 11 Nov afternoon → 16 Nov midday
A5: Shared inputs are on the Compare sheet. Scroll down for the day-by-day plan and door-to-door travel times.
A7: Category | B7: Item | C7: Date | D7: Travel time | E7: Unit cost (3 ppl) | F7: Currency | G7: Qty (3 ppl) | H7: Total MNT – 3 people | I7: Unit cost (4 ppl) | J7: Qty (4 ppl) | K7: Total MNT – 4 people | L7: Source / notes
A8: PAID BY UNIVERSITY
A9: Flights
B10: Hunnu Air MR881 Ulaanbaatar 13:20 → Manzhouli 15:00, nonstop | C10: Wed 11 Nov | D10: 0.069444444 | E10: 677 | F10: CNY | G10: =Compare!$B$6 | H10: =E10*G10*IF(F10="USD",Compare!$B$8,IF(F10="CNY",Compare!$B$9,IF(F10="HKD",Compare!$B$10,1))) | I10: =E10 | J10: =Compare!$B$7 | K10: =I10*J10*IF(F10="USD",Compare!$B$8,IF(F10="CNY",Compare!$B$9,IF(F10="HKD",Compare!$B$10,1))) | L10: Ctrip 22 Oct: ¥677 (SlickTrip $108). Flies Wed and Sat only. Checked bag ~20 kg per travel guides (not confirmed on hunnuair.com). No same-day flight on to Harbin or Shenyang: Ctrip's connections all stop overnight in Hohhot or Beijing.
B11: Air China CA955 Beijing Capital (PEK) 12:55 → Ulaanbaatar 15:05, nonstop | C11: 16 Nov | D11: 0.090277778 | E11: 171 | F11: USD | G11: =Compare!$B$6 | H11: =E11*G11*IF(F11="USD",Compare!$B$8,IF(F11="CNY",Compare!$B$9,IF(F11="HKD",Compare!$B$10,1))) | I11: =E11 | J11: =Compare!$B$7 | K11: =I11*J11*IF(F11="USD",Compare!$B$8,IF(F11="CNY",Compare!$B$9,IF(F11="HKD",Compare!$B$10,1))) | L11: Trip.com 22 Oct: US$171 pp, cheapest that day (MIAT OM224 11:30 US$193 on Trip.com / $176 on SlickTrip; Air China 08:25 $215; Capital + Hunnu via Erenhot $196)
A12: Trains
B13: Overnight train K7092 Manzhouli 19:17 → Harbin 07:11, hard seat | C13: 11–12 Nov | D13: 0.49583333 | E13: 119 | F13: CNY | G13: =Compare!$B$6 | H13: =E13*G13*IF(F13="USD",Compare!$B$8,IF(F13="CNY",Compare!$B$9,IF(F13="HKD",Compare!$B$10,1))) | I13: =E13 | J13: =Compare!$B$7 | K13: =I13*J13*IF(F13="USD",Compare!$B$8,IF(F13="CNY",Compare!$B$9,IF(F13="HKD",Compare!$B$10,1))) | L13: 12306 (5 Nov query): seat ¥119, hard sleeper ¥207, soft ¥324 (K7090 20:20 → 09:08 same fares). ChinaTicketOnline confirms 11 Nov, on sale 28 Oct 16:00. Direct Manzhouli → Shenyang trains (09:05 / 11:15 / 13:40, 18–21 h) leave before the flight lands.
B14: Train K928 Harbin 07:48 → Shenyang North 14:32, hard seat | C14: 12 Nov | D14: 0.28055556 | E14: 75 | F14: CNY | G14: =Compare!$B$6 | H14: =E14*G14*IF(F14="USD",Compare!$B$8,IF(F14="CNY",Compare!$B$9,IF(F14="HKD",Compare!$B$10,1))) | I14: =E14 | J14: =Compare!$B$7 | K14: =I14*J14*IF(F14="USD",Compare!$B$8,IF(F14="CNY",Compare!$B$9,IF(F14="HKD",Compare!$B$10,1))) | L14: 12306 (5 Nov query): seat ¥75, hard sleeper ¥133; same station as K7092 (37 min). T184 Harbin West 07:10 also ¥75; G1280 09:11 → 11:42 ¥267 is the fast option. On sale 29 Oct 10:00.
B15: Overnight train K28 Shenyang 22:24 → Beijing 08:40, hard seat (after the contest) | C15: 15 Nov (night) | D15: 0.42777778 | E15: 112 | F15: CNY | G15: =Compare!$B$6 | H15: =E15*G15*IF(F15="USD",Compare!$B$8,IF(F15="CNY",Compare!$B$9,IF(F15="HKD",Compare!$B$10,1))) | I15: =E15 | J15: =Compare!$B$7 | K15: =I15*J15*IF(F15="USD",Compare!$B$8,IF(F15="CNY",Compare!$B$9,IF(F15="HKD",Compare!$B$10,1))) | L15: 12306 (5 Nov query): hard seat ¥112 (hard sleeper ¥194). Cheapest train that still makes the 12:55 flight (K96 23:39 ¥102 arrives 11:19 – too late). Lie-flat upgrade: K54 Shenyang North 22:00 → 06:58 hard sleeper ¥171 (+¥59 pp). On sale 1 Nov 09:30 (ChinaTicketOnline confirms 15 Nov).
A16: Accommodation
B17: Ji Hotel Sanhao Street, 55 Sanhao St (~940 m to NEU Nanhu, ~15 min walk): 2 Budget Twin rooms, King Koil mattresses, windows, floors 4–16 – a bed each | C17: 12–15 Nov (3 nights) | E17: 457 | F17: CNY | G17: 3 | H17: =E17*G17*IF(F17="USD",Compare!$B$8,IF(F17="CNY",Compare!$B$9,IF(F17="HKD",Compare!$B$10,1))) | I17: 457 | J17: 3 | K17: =I17*J17*IF(F17="USD",Compare!$B$8,IF(F17="CNY",Compare!$B$9,IF(F17="HKD",Compare!$B$10,1))) | L17: Trip.com 22 Oct: ¥1,371 for 2 rooms × 3 nights incl. taxes, free cancellation until 18:00 on 11 Nov (prepay); same price for 3 or 4 adults. 9.0 from 1,433 reviews; 16 m² rooms high in an office tower, above the street. Breakfast ¥40 optional.
A18: Meals & local transport
B19: Meals | C19: in destination | E19: 80 | F19: CNY | G19: =Compare!$B$6*$B$4 | H19: =E19*G19*IF(F19="USD",Compare!$B$8,IF(F19="CNY",Compare!$B$9,IF(F19="HKD",Compare!$B$10,1))) | I19: =E19 | J19: =Compare!$B$7*$B$4 | K19: =I19*J19*IF(F19="USD",Compare!$B$8,IF(F19="CNY",Compare!$B$9,IF(F19="HKD",Compare!$B$10,1))) | L19: ASSUMPTION 80 CNY/person/day; hosts usually provide some meals on contest days
B20: Local transport (metro, taxis) | C20: in destination | E20: 30 | F20: CNY | G20: =Compare!$B$6*$B$4 | H20: =E20*G20*IF(F20="USD",Compare!$B$8,IF(F20="CNY",Compare!$B$9,IF(F20="HKD",Compare!$B$10,1))) | I20: =E20 | J20: =Compare!$B$7*$B$4 | K20: =I20*J20*IF(F20="USD",Compare!$B$8,IF(F20="CNY",Compare!$B$9,IF(F20="HKD",Compare!$B$10,1))) | L20: ASSUMPTION 30 CNY/person/day
B21: Taxi Manzhouli airport → Manzhouli station | C21: 11 Nov | E21: 30 | F21: CNY | G21: 1 | H21: =E21*G21*IF(F21="USD",Compare!$B$8,IF(F21="CNY",Compare!$B$9,IF(F21="HKD",Compare!$B$10,1))) | I21: =E21 | J21: 1 | K21: =I21*J21*IF(F21="USD",Compare!$B$8,IF(F21="CNY",Compare!$B$9,IF(F21="HKD",Compare!$B$10,1))) | L21: ASSUMPTION ~¥30 per car, ~10 km
B22: Metro line 2 + Airport Express, Beijing station → PEK T3 | C22: 16 Nov | E22: 30 | F22: CNY | G22: =Compare!$B$6 | H22: =E22*G22*IF(F22="USD",Compare!$B$8,IF(F22="CNY",Compare!$B$9,IF(F22="HKD",Compare!$B$10,1))) | I22: =E22 | J22: =Compare!$B$7 | K22: =I22*J22*IF(F22="USD",Compare!$B$8,IF(F22="CNY",Compare!$B$9,IF(F22="HKD",Compare!$B$10,1))) | L22: ASSUMPTION Airport Express ¥25 + metro ¥4–5 pp
A23: PAID PERSONALLY (university won't cover)
A24: Contest fee
B25: Shenyang regional registration fee (per team) | C25: pay when invited | E25: 1500 | F25: CNY | G25: 1 | H25: =E25*G25*IF(F25="USD",Compare!$B$8,IF(F25="CNY",Compare!$B$9,IF(F25="HKD",Compare!$B$10,1))) | I25: =E25 | J25: 1 | K25: =I25*J25*IF(F25="USD",Compare!$B$8,IF(F25="CNY",Compare!$B$9,IF(F25="HKD",Compare!$B$10,1))) | L25: ASSUMPTION: 1,500 CNY/team like recent EC regionals; the 2026 Shenyang invitation was not found on 22 Oct
A26: Other
B27: Taxi to/from Chinggis Khaan airport (UB), per trip | C27: out & back | D27: 0.041666667 | E27: 100000 | F27: MNT | G27: 2 | H27: =E27*G27*IF(F27="USD",Compare!$B$8,IF(F27="CNY",Compare!$B$9,IF(F27="HKD",Compare!$B$10,1))) | I27: =E27 | J27: 2 | K27: =I27*J27*IF(F27="USD",Compare!$B$8,IF(F27="CNY",Compare!$B$9,IF(F27="HKD",Compare!$B$10,1))) | L27: ASSUMPTION 100k MNT per trip for the group
B28: Travel medical insurance | E28: 30000 | F28: MNT | G28: =Compare!$B$6 | H28: =E28*G28*IF(F28="USD",Compare!$B$8,IF(F28="CNY",Compare!$B$9,IF(F28="HKD",Compare!$B$10,1))) | I28: =E28 | J28: =Compare!$B$7 | K28: =I28*J28*IF(F28="USD",Compare!$B$8,IF(F28="CNY",Compare!$B$9,IF(F28="HKD",Compare!$B$10,1))) | L28: ASSUMPTION ~30k MNT per person, Mongolian insurer
B29: Mobile data eSIM | E29: 10 | F29: USD | G29: =Compare!$B$6 | H29: =E29*G29*IF(F29="USD",Compare!$B$8,IF(F29="CNY",Compare!$B$9,IF(F29="HKD",Compare!$B$10,1))) | I29: =E29 | J29: =Compare!$B$7 | K29: =I29*J29*IF(F29="USD",Compare!$B$8,IF(F29="CNY",Compare!$B$9,IF(F29="HKD",Compare!$B$10,1))) | L29: ASSUMPTION ~$10 pp
B30: Visa | E30: 0 | F30: MNT | G30: =Compare!$B$6 | H30: =E30*G30*IF(F30="USD",Compare!$B$8,IF(F30="CNY",Compare!$B$9,IF(F30="HKD",Compare!$B$10,1))) | I30: =E30 | J30: =Compare!$B$7 | K30: =I30*J30*IF(F30="USD",Compare!$B$8,IF(F30="CNY",Compare!$B$9,IF(F30="HKD",Compare!$B$10,1))) | L30: Mongolian passports: visa-free (mainland China up to 30 days; Hong Kong up to 14 days)
H32: 3 people – UNFUNDED | K32: 4 people – FUNDED ₮12M
G33: University-paid subtotal | H33: =SUM(H9:H22) | K33: =SUM(K9:K22)
G34: Contingency | H34: =H33*Compare!$B$11 | K34: =K33*Compare!$B$11
G35: University-paid total incl. contingency | H35: =H33+H34 | K35: =K33+K34
G36: Funding left (negative = over) | H36: =Compare!$B$12-H35 | K36: =Compare!$B$5-K35
G37: Personal costs – team | H37: =SUM(H24:H30) | K37: =SUM(K24:K30)
G38: Out-of-pocket per person (personal + any overrun) | H38: =(H37+MAX(0,-H36))/Compare!$B$6 | K38: =(K37+MAX(0,-K36))/Compare!$B$7
G39: Whole trip cost (university + personal) | H39: =H35+H37 | K39: =K35+K37
G40: Time in planes & trains | H40: =SUM(D10:D11)+SUM(D13:D15) | K40: =SUM(D10:D11)+SUM(D13:D15)
A42: Key facts
A43: Contest | B43: Asia Shenyang Regional, 14–15 Nov 2026 (provisional; the 2026 invitation was not found on 22 Oct), Northeastern University Nanhu campus (2024 and 2025 venue). Assumed: day 1 registration + practice, contest 15 Nov 09:00–14:00, awards ~17:00.
A44: Why this plan | B44: Cheapest way out by air: ~₮0.48M per person (Hunnu ¥677). Arrives 12 Nov, so it keeps the three hotel nights and the rest day of 'Sleep value'. Cheaper way out than the Air China + G153 route of 'Sleep value' (₮0.91M per person); the rest of the trip is the same (Ji Hotel twin rooms, K28 hard seat + Air China 12:55 home), with hotel nights set by the arrival time.
A45: Trade-off | B45: Manzhouli needs an overnight train: there is no same-day flight or fast train on to Harbin or Shenyang. One night sitting up on K7092 (11 Nov), four nights before the contest; hard sleeper ¥207 or soft ¥324 instead of the seat; G1280 (¥267, arrive 11:42) instead of K928 saves 3 h. Hunnu flies only Wed / Sat.
A46: Book | B46: Hunnu on Ctrip now; K7092 on 12306 at 16:00 on 28 Oct; K928 at 10:00 on 29 Oct; K28 on 12306 at 09:30 on 1 Nov; Air China home on Trip.com.
A48: Day-by-day plan
A49: Date | B49: Sleep in | C49: What happens
A50: Wed 11 Nov | B50: Train (seat) | C50: Hunnu MR881 UB 13:20 → Manzhouli 15:00; taxi to Manzhouli station; K7092 19:17 → Harbin (overnight).
A51: Thu 12 Nov | B51: Shenyang | C51: Arrive Harbin 07:11; K928 07:48 → Shenyang North 14:32; taxi to Ji Hotel.
A52: Fri 13 Nov | B52: Shenyang | C52: Free rest day.
A53: Sat 14 Nov | B53: Shenyang | C53: Registration, opening and practice at NEU Nanhu. Lights out ~22:30.
A54: Sun 15 Nov | B54: Train (seat) | C54: CONTEST. Wake ~06:50, walk ~15 min. Check out before leaving, luggage stored at the hotel. Awards ~17:00; taxi to Shenyang station; K28 22:24 hard seat → Beijing 08:40.
A55: Mon 16 Nov | B55: Home | C55: Metro line 2 + Airport Express to PEK T3 (~1 h). Air China 12:55 → UB 15:05.
A57: Door-to-door travel times
A58: Date | B58: Leg | C58: Mode | D58: Expected time | E58: Notes
A59: 11 Nov | B59: Home → Chinggis Khaan airport | C59: Taxi (~50 km) | D59: 0.041666667 | E59: Leave ~10:45
A60: 11 Nov | B60: Ulaanbaatar → Manzhouli | C60: Hunnu MR881 13:20–15:00 | D60: 0.069444444
A61: 11 Nov | B61: Manzhouli arrival + taxi to the station | C61: Taxi | D61: 0.041666667 | E61: Estimate
A62: 11–12 Nov | B62: Manzhouli → Harbin | C62: K7092 hard seat 19:17–07:11 | D62: 0.49583333 | E62: Overnight
A63: 12 Nov | B63: Harbin → Shenyang North | C63: K928 hard seat 07:48–14:32 | D63: 0.28055556 | E63: Same station, 37 min change
A64: 12 Nov | B64: Shenyang North → Ji Hotel | C64: Taxi | D64: 0.017361111
A65: 13–15 Nov | B65: Hotel ↔ NEU Nanhu (each way) | C65: Walk | D65: daily | E65: ~15 min walk
A66: 15 Nov | B66: NEU Nanhu → Shenyang station | C66: Taxi | D66: 0.013888889
A67: 15–16 Nov | B67: Shenyang → Beijing | C67: K28 hard seat 22:24–08:40 | D67: 0.42777778 | E67: Overnight, after the contest
A68: 16 Nov | B68: Beijing station → PEK | C68: Metro line 2 + Airport Express | D68: 0.041666667 | E68: Be at PEK by ~10:55
A69: 16 Nov | B69: Beijing (PEK) → Ulaanbaatar | C69: Air China 12:55–15:05 | D69: 0.090277778
A70: 16 Nov | B70: Chinggis Khaan airport → home | C70: Taxi | D70: 0.041666667
C72: Total door-to-door | D72: =SUM(D59:D70)

Sheet Shenyang – Hunnu Daxing + K341
A1: Shenyang – Hunnu Daxing + K341
A2: Hunnu Air to Beijing Daxing on Fri 13 Nov, K341 overnight to Shenyang in a hard seat; arrive on day 1 morning, one hotel night; K28 seat + Air China home.
A4: Days in destination (meals & local transport) | B4: 3 | C4: 13 Nov evening → 16 Nov midday
A5: Shared inputs are on the Compare sheet. Scroll down for the day-by-day plan and door-to-door travel times.
A7: Category | B7: Item | C7: Date | D7: Travel time | E7: Unit cost (3 ppl) | F7: Currency | G7: Qty (3 ppl) | H7: Total MNT – 3 people | I7: Unit cost (4 ppl) | J7: Qty (4 ppl) | K7: Total MNT – 4 people | L7: Source / notes
A8: PAID BY UNIVERSITY
A9: Flights
B10: Hunnu Air MR801 Ulaanbaatar 17:55 → Beijing Daxing (PKX) 20:15, nonstop | C10: Fri 13 Nov | D10: 0.097222222 | E10: 921 | F10: CNY | G10: =Compare!$B$6 | H10: =E10*G10*IF(F10="USD",Compare!$B$8,IF(F10="CNY",Compare!$B$9,IF(F10="HKD",Compare!$B$10,1))) | I10: =E10 | J10: =Compare!$B$7 | K10: =I10*J10*IF(F10="USD",Compare!$B$8,IF(F10="CNY",Compare!$B$9,IF(F10="HKD",Compare!$B$10,1))) | L10: Ctrip 22 Oct: ¥921 (SlickTrip $186; MIAT 17:15 ¥975, Air China 16:10 ¥1,031 the same day). Checked bag ~20 kg per travel guides (not confirmed).
B11: Air China CA955 Beijing Capital (PEK) 12:55 → Ulaanbaatar 15:05, nonstop | C11: 16 Nov | D11: 0.090277778 | E11: 171 | F11: USD | G11: =Compare!$B$6 | H11: =E11*G11*IF(F11="USD",Compare!$B$8,IF(F11="CNY",Compare!$B$9,IF(F11="HKD",Compare!$B$10,1))) | I11: =E11 | J11: =Compare!$B$7 | K11: =I11*J11*IF(F11="USD",Compare!$B$8,IF(F11="CNY",Compare!$B$9,IF(F11="HKD",Compare!$B$10,1))) | L11: Trip.com 22 Oct: US$171 pp, cheapest that day (MIAT OM224 11:30 US$193 on Trip.com / $176 on SlickTrip; Air China 08:25 $215; Capital + Hunnu via Erenhot $196)
A12: Trains
B13: Overnight train K341 Beijing 23:00 → Shenyang 08:47, hard seat | C13: 13–14 Nov | D13: 0.40763889 | E13: 112 | F13: CNY | G13: =Compare!$B$6 | H13: =E13*G13*IF(F13="USD",Compare!$B$8,IF(F13="CNY",Compare!$B$9,IF(F13="HKD",Compare!$B$10,1))) | I13: =E13 | J13: =Compare!$B$7 | K13: =I13*J13*IF(F13="USD",Compare!$B$8,IF(F13="CNY",Compare!$B$9,IF(F13="HKD",Compare!$B$10,1))) | L13: 12306 (5 Nov query): seat ¥112, hard sleeper ¥194. ChinaTicketOnline confirms 13 Nov, on sale 30 Oct 10:00. Fallback if late: G-trains from Beijing Chaoyang next morning (¥355–369, e.g. G101 08:00).
B14: Overnight train K28 Shenyang 22:24 → Beijing 08:40, hard seat (after the contest) | C14: 15 Nov (night) | D14: 0.42777778 | E14: 112 | F14: CNY | G14: =Compare!$B$6 | H14: =E14*G14*IF(F14="USD",Compare!$B$8,IF(F14="CNY",Compare!$B$9,IF(F14="HKD",Compare!$B$10,1))) | I14: =E14 | J14: =Compare!$B$7 | K14: =I14*J14*IF(F14="USD",Compare!$B$8,IF(F14="CNY",Compare!$B$9,IF(F14="HKD",Compare!$B$10,1))) | L14: 12306 (5 Nov query): hard seat ¥112 (hard sleeper ¥194). Cheapest train that still makes the 12:55 flight (K96 23:39 ¥102 arrives 11:19 – too late). Lie-flat upgrade: K54 Shenyang North 22:00 → 06:58 hard sleeper ¥171 (+¥59 pp). On sale 1 Nov 09:30 (ChinaTicketOnline confirms 15 Nov).
A15: Accommodation
B16: Ji Hotel Sanhao Street, 55 Sanhao St (~940 m to NEU Nanhu, ~15 min walk): 2 Budget Twin rooms, King Koil mattresses, windows, floors 4–16 – a bed each | C16: 14–15 Nov (1 night) | E16: 457 | F16: CNY | G16: 1 | H16: =E16*G16*IF(F16="USD",Compare!$B$8,IF(F16="CNY",Compare!$B$9,IF(F16="HKD",Compare!$B$10,1))) | I16: 457 | J16: 1 | K16: =I16*J16*IF(F16="USD",Compare!$B$8,IF(F16="CNY",Compare!$B$9,IF(F16="HKD",Compare!$B$10,1))) | L16: Trip.com 22 Oct: ¥457 for 2 Budget Twin rooms × 1 night (14–15 Nov) incl. taxes, free cancellation until 18:00 on 13 Nov; same hotel as 'Sleep value' (9.0, King Koil mattresses).
A17: Meals & local transport
B18: Meals | C18: in destination | E18: 80 | F18: CNY | G18: =Compare!$B$6*$B$4 | H18: =E18*G18*IF(F18="USD",Compare!$B$8,IF(F18="CNY",Compare!$B$9,IF(F18="HKD",Compare!$B$10,1))) | I18: =E18 | J18: =Compare!$B$7*$B$4 | K18: =I18*J18*IF(F18="USD",Compare!$B$8,IF(F18="CNY",Compare!$B$9,IF(F18="HKD",Compare!$B$10,1))) | L18: ASSUMPTION 80 CNY/person/day; hosts usually provide some meals on contest days
B19: Local transport (metro, taxis) | C19: in destination | E19: 30 | F19: CNY | G19: =Compare!$B$6*$B$4 | H19: =E19*G19*IF(F19="USD",Compare!$B$8,IF(F19="CNY",Compare!$B$9,IF(F19="HKD",Compare!$B$10,1))) | I19: =E19 | J19: =Compare!$B$7*$B$4 | K19: =I19*J19*IF(F19="USD",Compare!$B$8,IF(F19="CNY",Compare!$B$9,IF(F19="HKD",Compare!$B$10,1))) | L19: ASSUMPTION 30 CNY/person/day
B20: Daxing Airport Express + metro to Beijing station | C20: 13 Nov | E20: 40 | F20: CNY | G20: =Compare!$B$6 | H20: =E20*G20*IF(F20="USD",Compare!$B$8,IF(F20="CNY",Compare!$B$9,IF(F20="HKD",Compare!$B$10,1))) | I20: =E20 | J20: =Compare!$B$7 | K20: =I20*J20*IF(F20="USD",Compare!$B$8,IF(F20="CNY",Compare!$B$9,IF(F20="HKD",Compare!$B$10,1))) | L20: ASSUMPTION ~¥35 + ¥5 pp, ~1 h 15 min
B21: Metro line 2 + Airport Express, Beijing station → PEK T3 | C21: 16 Nov | E21: 30 | F21: CNY | G21: =Compare!$B$6 | H21: =E21*G21*IF(F21="USD",Compare!$B$8,IF(F21="CNY",Compare!$B$9,IF(F21="HKD",Compare!$B$10,1))) | I21: =E21 | J21: =Compare!$B$7 | K21: =I21*J21*IF(F21="USD",Compare!$B$8,IF(F21="CNY",Compare!$B$9,IF(F21="HKD",Compare!$B$10,1))) | L21: ASSUMPTION Airport Express ¥25 + metro ¥4–5 pp
A22: PAID PERSONALLY (university won't cover)
A23: Contest fee
B24: Shenyang regional registration fee (per team) | C24: pay when invited | E24: 1500 | F24: CNY | G24: 1 | H24: =E24*G24*IF(F24="USD",Compare!$B$8,IF(F24="CNY",Compare!$B$9,IF(F24="HKD",Compare!$B$10,1))) | I24: =E24 | J24: 1 | K24: =I24*J24*IF(F24="USD",Compare!$B$8,IF(F24="CNY",Compare!$B$9,IF(F24="HKD",Compare!$B$10,1))) | L24: ASSUMPTION: 1,500 CNY/team like recent EC regionals; the 2026 Shenyang invitation was not found on 22 Oct
A25: Other
B26: Taxi to/from Chinggis Khaan airport (UB), per trip | C26: out & back | D26: 0.041666667 | E26: 100000 | F26: MNT | G26: 2 | H26: =E26*G26*IF(F26="USD",Compare!$B$8,IF(F26="CNY",Compare!$B$9,IF(F26="HKD",Compare!$B$10,1))) | I26: =E26 | J26: 2 | K26: =I26*J26*IF(F26="USD",Compare!$B$8,IF(F26="CNY",Compare!$B$9,IF(F26="HKD",Compare!$B$10,1))) | L26: ASSUMPTION 100k MNT per trip for the group
B27: Travel medical insurance | E27: 30000 | F27: MNT | G27: =Compare!$B$6 | H27: =E27*G27*IF(F27="USD",Compare!$B$8,IF(F27="CNY",Compare!$B$9,IF(F27="HKD",Compare!$B$10,1))) | I27: =E27 | J27: =Compare!$B$7 | K27: =I27*J27*IF(F27="USD",Compare!$B$8,IF(F27="CNY",Compare!$B$9,IF(F27="HKD",Compare!$B$10,1))) | L27: ASSUMPTION ~30k MNT per person, Mongolian insurer
B28: Mobile data eSIM | E28: 10 | F28: USD | G28: =Compare!$B$6 | H28: =E28*G28*IF(F28="USD",Compare!$B$8,IF(F28="CNY",Compare!$B$9,IF(F28="HKD",Compare!$B$10,1))) | I28: =E28 | J28: =Compare!$B$7 | K28: =I28*J28*IF(F28="USD",Compare!$B$8,IF(F28="CNY",Compare!$B$9,IF(F28="HKD",Compare!$B$10,1))) | L28: ASSUMPTION ~$10 pp
B29: Visa | E29: 0 | F29: MNT | G29: =Compare!$B$6 | H29: =E29*G29*IF(F29="USD",Compare!$B$8,IF(F29="CNY",Compare!$B$9,IF(F29="HKD",Compare!$B$10,1))) | I29: =E29 | J29: =Compare!$B$7 | K29: =I29*J29*IF(F29="USD",Compare!$B$8,IF(F29="CNY",Compare!$B$9,IF(F29="HKD",Compare!$B$10,1))) | L29: Mongolian passports: visa-free (mainland China up to 30 days; Hong Kong up to 14 days)
H31: 3 people – UNFUNDED | K31: 4 people – FUNDED ₮12M
G32: University-paid subtotal | H32: =SUM(H9:H21) | K32: =SUM(K9:K21)
G33: Contingency | H33: =H32*Compare!$B$11 | K33: =K32*Compare!$B$11
G34: University-paid total incl. contingency | H34: =H32+H33 | K34: =K32+K33
G35: Funding left (negative = over) | H35: =Compare!$B$12-H34 | K35: =Compare!$B$5-K34
G36: Personal costs – team | H36: =SUM(H23:H29) | K36: =SUM(K23:K29)
G37: Out-of-pocket per person (personal + any overrun) | H37: =(H36+MAX(0,-H35))/Compare!$B$6 | K37: =(K36+MAX(0,-K35))/Compare!$B$7
G38: Whole trip cost (university + personal) | H38: =H34+H36 | K38: =K34+K36
G39: Time in planes & trains | H39: =SUM(D10:D11)+SUM(D13:D14) | K39: =SUM(D10:D11)+SUM(D13:D14)
A41: Key facts
A42: Contest | B42: Asia Shenyang Regional, 14–15 Nov 2026 (provisional; the 2026 invitation was not found on 22 Oct), Northeastern University Nanhu campus (2024 and 2025 venue). Assumed: day 1 registration + practice, contest 15 Nov 09:00–14:00, awards ~17:00.
A43: Why this plan | B43: ~₮0.58M per person to Shenyang and only one hotel night and three days of meals. Cheaper way out than the Air China + G153 route of 'Sleep value' (₮0.91M per person); the rest of the trip is the same (Ji Hotel twin rooms, K28 hard seat + Air China 12:55 home), with hotel nights set by the arrival time.
A44: Trade-off | B44: The night before day 1 is spent sitting up on K341 (POOR for sleep) and you arrive on registration morning. Only 45–60 min between landing and the 23:00 train; if it is missed, take a G-train next morning (¥355–369). Daxing is ~1 h 15 min from Beijing station.
A45: Book | B45: Hunnu on Ctrip now; K341 on 12306 at 10:00 on 30 Oct; K28 on 12306 at 09:30 on 1 Nov; Air China home on Trip.com.
A47: Day-by-day plan
A48: Date | B48: Sleep in | C48: What happens
A49: Fri 13 Nov | B49: Train (seat) | C49: Hunnu MR801 UB 17:55 → Beijing Daxing 20:15; Daxing Airport Express + metro to Beijing station; K341 23:00 → Shenyang (overnight).
A50: Sat 14 Nov | B50: Shenyang | C50: Arrive Shenyang 08:47; taxi to NEU Nanhu for registration and practice; check in at Ji Hotel. Lights out ~22:30.
A51: Sun 15 Nov | B51: Train (seat) | C51: CONTEST. Wake ~06:50, walk ~15 min. Check out before leaving, luggage stored at the hotel. Awards ~17:00; taxi to Shenyang station; K28 22:24 hard seat → Beijing 08:40.
A52: Mon 16 Nov | B52: Home | C52: Metro line 2 + Airport Express to PEK T3 (~1 h). Air China 12:55 → UB 15:05.
A54: Door-to-door travel times
A55: Date | B55: Leg | C55: Mode | D55: Expected time | E55: Notes
A56: 13 Nov | B56: Home → Chinggis Khaan airport | C56: Taxi (~50 km) | D56: 0.041666667 | E56: Leave ~15:00
A57: 13 Nov | B57: Ulaanbaatar → Beijing Daxing | C57: Hunnu MR801 17:55–20:15 | D57: 0.097222222
A58: 13 Nov | B58: PKX arrival: immigration, bags | C58: — | D58: 0.03125 | E58: Estimate
A59: 13 Nov | B59: Daxing → Beijing station | C59: Daxing Airport Express + metro | D59: 0.052083333 | E59: Estimate; ~45 min spare
A60: 13–14 Nov | B60: Beijing → Shenyang | C60: K341 hard seat 23:00–08:47 | D60: 0.40763889 | E60: Overnight
A61: 14 Nov | B61: Shenyang station → NEU Nanhu | C61: Taxi | D61: 0.013888889 | E61: Registration day
A62: 15 Nov | B62: NEU Nanhu → Shenyang station | C62: Taxi | D62: 0.013888889
A63: 15–16 Nov | B63: Shenyang → Beijing | C63: K28 hard seat 22:24–08:40 | D63: 0.42777778 | E63: Overnight, after the contest
A64: 16 Nov | B64: Beijing station → PEK | C64: Metro line 2 + Airport Express | D64: 0.041666667 | E64: Be at PEK by ~10:55
A65: 16 Nov | B65: Beijing (PEK) → Ulaanbaatar | C65: Air China 12:55–15:05 | D65: 0.090277778
A66: 16 Nov | B66: Chinggis Khaan airport → home | C66: Taxi | D66: 0.041666667
C68: Total door-to-door | D68: =SUM(D56:D66)

Sheet Shenyang – MIAT 13 Nov + K341
A1: Shenyang – MIAT 13 Nov + K341
A2: MIAT to Beijing Capital on Fri 13 Nov 17:15, K341 overnight to Shenyang in a hard seat; arrive on day 1 morning, one hotel night; K28 seat + Air China home.
A4: Days in destination (meals & local transport) | B4: 3 | C4: 13 Nov evening → 16 Nov midday
A5: Shared inputs are on the Compare sheet. Scroll down for the day-by-day plan and door-to-door travel times.
A7: Category | B7: Item | C7: Date | D7: Travel time | E7: Unit cost (3 ppl) | F7: Currency | G7: Qty (3 ppl) | H7: Total MNT – 3 people | I7: Unit cost (4 ppl) | J7: Qty (4 ppl) | K7: Total MNT – 4 people | L7: Source / notes
A8: PAID BY UNIVERSITY
A9: Flights
B10: MIAT OM223 Ulaanbaatar 17:15 → Beijing Capital (PEK) 19:30, nonstop | C10: Fri 13 Nov | D10: 0.09375 | E10: 975 | F10: CNY | G10: =Compare!$B$6 | H10: =E10*G10*IF(F10="USD",Compare!$B$8,IF(F10="CNY",Compare!$B$9,IF(F10="HKD",Compare!$B$10,1))) | I10: =E10 | J10: =Compare!$B$7 | K10: =I10*J10*IF(F10="USD",Compare!$B$8,IF(F10="CNY",Compare!$B$9,IF(F10="HKD",Compare!$B$10,1))) | L10: Ctrip 22 Oct: ¥975 (SlickTrip $154; Trip.com $151 on 30 Sep). Checked bag included.
B11: Air China CA955 Beijing Capital (PEK) 12:55 → Ulaanbaatar 15:05, nonstop | C11: 16 Nov | D11: 0.090277778 | E11: 171 | F11: USD | G11: =Compare!$B$6 | H11: =E11*G11*IF(F11="USD",Compare!$B$8,IF(F11="CNY",Compare!$B$9,IF(F11="HKD",Compare!$B$10,1))) | I11: =E11 | J11: =Compare!$B$7 | K11: =I11*J11*IF(F11="USD",Compare!$B$8,IF(F11="CNY",Compare!$B$9,IF(F11="HKD",Compare!$B$10,1))) | L11: Trip.com 22 Oct: US$171 pp, cheapest that day (MIAT OM224 11:30 US$193 on Trip.com / $176 on SlickTrip; Air China 08:25 $215; Capital + Hunnu via Erenhot $196)
A12: Trains
B13: Overnight train K341 Beijing 23:00 → Shenyang 08:47, hard seat | C13: 13–14 Nov | D13: 0.40763889 | E13: 112 | F13: CNY | G13: =Compare!$B$6 | H13: =E13*G13*IF(F13="USD",Compare!$B$8,IF(F13="CNY",Compare!$B$9,IF(F13="HKD",Compare!$B$10,1))) | I13: =E13 | J13: =Compare!$B$7 | K13: =I13*J13*IF(F13="USD",Compare!$B$8,IF(F13="CNY",Compare!$B$9,IF(F13="HKD",Compare!$B$10,1))) | L13: 12306 (5 Nov query): seat ¥112, hard sleeper ¥194. ChinaTicketOnline confirms 13 Nov, on sale 30 Oct 10:00. Fallback if late: G-trains from Beijing Chaoyang next morning (¥355–369, e.g. G101 08:00).
B14: Overnight train K28 Shenyang 22:24 → Beijing 08:40, hard seat (after the contest) | C14: 15 Nov (night) | D14: 0.42777778 | E14: 112 | F14: CNY | G14: =Compare!$B$6 | H14: =E14*G14*IF(F14="USD",Compare!$B$8,IF(F14="CNY",Compare!$B$9,IF(F14="HKD",Compare!$B$10,1))) | I14: =E14 | J14: =Compare!$B$7 | K14: =I14*J14*IF(F14="USD",Compare!$B$8,IF(F14="CNY",Compare!$B$9,IF(F14="HKD",Compare!$B$10,1))) | L14: 12306 (5 Nov query): hard seat ¥112 (hard sleeper ¥194). Cheapest train that still makes the 12:55 flight (K96 23:39 ¥102 arrives 11:19 – too late). Lie-flat upgrade: K54 Shenyang North 22:00 → 06:58 hard sleeper ¥171 (+¥59 pp). On sale 1 Nov 09:30 (ChinaTicketOnline confirms 15 Nov).
A15: Accommodation
B16: Ji Hotel Sanhao Street, 55 Sanhao St (~940 m to NEU Nanhu, ~15 min walk): 2 Budget Twin rooms, King Koil mattresses, windows, floors 4–16 – a bed each | C16: 14–15 Nov (1 night) | E16: 457 | F16: CNY | G16: 1 | H16: =E16*G16*IF(F16="USD",Compare!$B$8,IF(F16="CNY",Compare!$B$9,IF(F16="HKD",Compare!$B$10,1))) | I16: 457 | J16: 1 | K16: =I16*J16*IF(F16="USD",Compare!$B$8,IF(F16="CNY",Compare!$B$9,IF(F16="HKD",Compare!$B$10,1))) | L16: Trip.com 22 Oct: ¥457 for 2 Budget Twin rooms × 1 night (14–15 Nov) incl. taxes, free cancellation until 18:00 on 13 Nov; same hotel as 'Sleep value' (9.0, King Koil mattresses).
A17: Meals & local transport
B18: Meals | C18: in destination | E18: 80 | F18: CNY | G18: =Compare!$B$6*$B$4 | H18: =E18*G18*IF(F18="USD",Compare!$B$8,IF(F18="CNY",Compare!$B$9,IF(F18="HKD",Compare!$B$10,1))) | I18: =E18 | J18: =Compare!$B$7*$B$4 | K18: =I18*J18*IF(F18="USD",Compare!$B$8,IF(F18="CNY",Compare!$B$9,IF(F18="HKD",Compare!$B$10,1))) | L18: ASSUMPTION 80 CNY/person/day; hosts usually provide some meals on contest days
B19: Local transport (metro, taxis) | C19: in destination | E19: 30 | F19: CNY | G19: =Compare!$B$6*$B$4 | H19: =E19*G19*IF(F19="USD",Compare!$B$8,IF(F19="CNY",Compare!$B$9,IF(F19="HKD",Compare!$B$10,1))) | I19: =E19 | J19: =Compare!$B$7*$B$4 | K19: =I19*J19*IF(F19="USD",Compare!$B$8,IF(F19="CNY",Compare!$B$9,IF(F19="HKD",Compare!$B$10,1))) | L19: ASSUMPTION 30 CNY/person/day
B20: Airport Express + metro line 2, PEK → Beijing station | C20: 13 Nov | E20: 30 | F20: CNY | G20: =Compare!$B$6 | H20: =E20*G20*IF(F20="USD",Compare!$B$8,IF(F20="CNY",Compare!$B$9,IF(F20="HKD",Compare!$B$10,1))) | I20: =E20 | J20: =Compare!$B$7 | K20: =I20*J20*IF(F20="USD",Compare!$B$8,IF(F20="CNY",Compare!$B$9,IF(F20="HKD",Compare!$B$10,1))) | L20: ASSUMPTION Airport Express ¥25 + metro ¥4–5 pp, ~1 h
B21: Metro line 2 + Airport Express, Beijing station → PEK T3 | C21: 16 Nov | E21: 30 | F21: CNY | G21: =Compare!$B$6 | H21: =E21*G21*IF(F21="USD",Compare!$B$8,IF(F21="CNY",Compare!$B$9,IF(F21="HKD",Compare!$B$10,1))) | I21: =E21 | J21: =Compare!$B$7 | K21: =I21*J21*IF(F21="USD",Compare!$B$8,IF(F21="CNY",Compare!$B$9,IF(F21="HKD",Compare!$B$10,1))) | L21: ASSUMPTION Airport Express ¥25 + metro ¥4–5 pp
A22: PAID PERSONALLY (university won't cover)
A23: Contest fee
B24: Shenyang regional registration fee (per team) | C24: pay when invited | E24: 1500 | F24: CNY | G24: 1 | H24: =E24*G24*IF(F24="USD",Compare!$B$8,IF(F24="CNY",Compare!$B$9,IF(F24="HKD",Compare!$B$10,1))) | I24: =E24 | J24: 1 | K24: =I24*J24*IF(F24="USD",Compare!$B$8,IF(F24="CNY",Compare!$B$9,IF(F24="HKD",Compare!$B$10,1))) | L24: ASSUMPTION: 1,500 CNY/team like recent EC regionals; the 2026 Shenyang invitation was not found on 22 Oct
A25: Other
B26: Taxi to/from Chinggis Khaan airport (UB), per trip | C26: out & back | D26: 0.041666667 | E26: 100000 | F26: MNT | G26: 2 | H26: =E26*G26*IF(F26="USD",Compare!$B$8,IF(F26="CNY",Compare!$B$9,IF(F26="HKD",Compare!$B$10,1))) | I26: =E26 | J26: 2 | K26: =I26*J26*IF(F26="USD",Compare!$B$8,IF(F26="CNY",Compare!$B$9,IF(F26="HKD",Compare!$B$10,1))) | L26: ASSUMPTION 100k MNT per trip for the group
B27: Travel medical insurance | E27: 30000 | F27: MNT | G27: =Compare!$B$6 | H27: =E27*G27*IF(F27="USD",Compare!$B$8,IF(F27="CNY",Compare!$B$9,IF(F27="HKD",Compare!$B$10,1))) | I27: =E27 | J27: =Compare!$B$7 | K27: =I27*J27*IF(F27="USD",Compare!$B$8,IF(F27="CNY",Compare!$B$9,IF(F27="HKD",Compare!$B$10,1))) | L27: ASSUMPTION ~30k MNT per person, Mongolian insurer
B28: Mobile data eSIM | E28: 10 | F28: USD | G28: =Compare!$B$6 | H28: =E28*G28*IF(F28="USD",Compare!$B$8,IF(F28="CNY",Compare!$B$9,IF(F28="HKD",Compare!$B$10,1))) | I28: =E28 | J28: =Compare!$B$7 | K28: =I28*J28*IF(F28="USD",Compare!$B$8,IF(F28="CNY",Compare!$B$9,IF(F28="HKD",Compare!$B$10,1))) | L28: ASSUMPTION ~$10 pp
B29: Visa | E29: 0 | F29: MNT | G29: =Compare!$B$6 | H29: =E29*G29*IF(F29="USD",Compare!$B$8,IF(F29="CNY",Compare!$B$9,IF(F29="HKD",Compare!$B$10,1))) | I29: =E29 | J29: =Compare!$B$7 | K29: =I29*J29*IF(F29="USD",Compare!$B$8,IF(F29="CNY",Compare!$B$9,IF(F29="HKD",Compare!$B$10,1))) | L29: Mongolian passports: visa-free (mainland China up to 30 days; Hong Kong up to 14 days)
H31: 3 people – UNFUNDED | K31: 4 people – FUNDED ₮12M
G32: University-paid subtotal | H32: =SUM(H9:H21) | K32: =SUM(K9:K21)
G33: Contingency | H33: =H32*Compare!$B$11 | K33: =K32*Compare!$B$11
G34: University-paid total incl. contingency | H34: =H32+H33 | K34: =K32+K33
G35: Funding left (negative = over) | H35: =Compare!$B$12-H34 | K35: =Compare!$B$5-K34
G36: Personal costs – team | H36: =SUM(H23:H29) | K36: =SUM(K23:K29)
G37: Out-of-pocket per person (personal + any overrun) | H37: =(H36+MAX(0,-H35))/Compare!$B$6 | K37: =(K36+MAX(0,-K35))/Compare!$B$7
G38: Whole trip cost (university + personal) | H38: =H34+H36 | K38: =K34+K36
G39: Time in planes & trains | H39: =SUM(D10:D11)+SUM(D13:D14) | K39: =SUM(D10:D11)+SUM(D13:D14)
A41: Key facts
A42: Contest | B42: Asia Shenyang Regional, 14–15 Nov 2026 (provisional; the 2026 invitation was not found on 22 Oct), Northeastern University Nanhu campus (2024 and 2025 venue). Assumed: day 1 registration + practice, contest 15 Nov 09:00–14:00, awards ~17:00.
A43: Why this plan | B43: ~₮0.60M per person to Shenyang; Beijing Capital is closer to the station than Daxing. Cheaper way out than the Air China + G153 route of 'Sleep value' (₮0.91M per person); the rest of the trip is the same (Ji Hotel twin rooms, K28 hard seat + Air China 12:55 home), with hotel nights set by the arrival time.
A44: Trade-off | B44: The night before day 1 is spent sitting up on K341 (POOR for sleep) and you arrive on registration morning. Only 45–60 min between landing and the 23:00 train; if it is missed, take a G-train next morning (¥355–369).
A45: Book | B45: MIAT on Ctrip now; K341 on 12306 at 10:00 on 30 Oct; K28 on 12306 at 09:30 on 1 Nov; Air China home on Trip.com.
A47: Day-by-day plan
A48: Date | B48: Sleep in | C48: What happens
A49: Fri 13 Nov | B49: Train (seat) | C49: MIAT OM223 UB 17:15 → Beijing Capital 19:30; Airport Express + metro to Beijing station; K341 23:00 → Shenyang (overnight).
A50: Sat 14 Nov | B50: Shenyang | C50: Arrive Shenyang 08:47; taxi to NEU Nanhu for registration and practice; check in at Ji Hotel. Lights out ~22:30.
A51: Sun 15 Nov | B51: Train (seat) | C51: CONTEST. Wake ~06:50, walk ~15 min. Check out before leaving, luggage stored at the hotel. Awards ~17:00; taxi to Shenyang station; K28 22:24 hard seat → Beijing 08:40.
A52: Mon 16 Nov | B52: Home | C52: Metro line 2 + Airport Express to PEK T3 (~1 h). Air China 12:55 → UB 15:05.
A54: Door-to-door travel times
A55: Date | B55: Leg | C55: Mode | D55: Expected time | E55: Notes
A56: 13 Nov | B56: Home → Chinggis Khaan airport | C56: Taxi (~50 km) | D56: 0.041666667 | E56: Leave ~14:15
A57: 13 Nov | B57: Ulaanbaatar → Beijing (PEK) | C57: MIAT OM223 17:15–19:30 | D57: 0.09375
A58: 13 Nov | B58: PEK arrival: immigration, bags | C58: — | D58: 0.03125 | E58: Estimate
A59: 13 Nov | B59: PEK → Beijing station | C59: Airport Express + metro line 2 | D59: 0.041666667 | E59: Estimate
A60: 13–14 Nov | B60: Beijing → Shenyang | C60: K341 hard seat 23:00–08:47 | D60: 0.40763889 | E60: Overnight
A61: 14 Nov | B61: Shenyang station → NEU Nanhu | C61: Taxi | D61: 0.013888889 | E61: Registration day
A62: 15 Nov | B62: NEU Nanhu → Shenyang station | C62: Taxi | D62: 0.013888889
A63: 15–16 Nov | B63: Shenyang → Beijing | C63: K28 hard seat 22:24–08:40 | D63: 0.42777778 | E63: Overnight, after the contest
A64: 16 Nov | B64: Beijing station → PEK | C64: Metro line 2 + Airport Express | D64: 0.041666667 | E64: Be at PEK by ~10:55
A65: 16 Nov | B65: Beijing (PEK) → Ulaanbaatar | C65: Air China 12:55–15:05 | D65: 0.090277778
A66: 16 Nov | B66: Chinggis Khaan airport → home | C66: Taxi | D66: 0.041666667
C68: Total door-to-door | D68: =SUM(D56:D66)

Sheet Shenyang – Hunnu Erenhot
A1: Shenyang – Hunnu Erenhot
A2: Hunnu Air to Erenhot on Fri 13 Nov, then 4654 and the T301 overnight in hard seats; arrive on day 1 morning, one hotel night; K28 seat + Air China home.
A4: Days in destination (meals & local transport) | B4: 3.5 | C4: 13 Nov morning → 16 Nov midday
A5: Shared inputs are on the Compare sheet. Scroll down for the day-by-day plan and door-to-door travel times.
A7: Category | B7: Item | C7: Date | D7: Travel time | E7: Unit cost (3 ppl) | F7: Currency | G7: Qty (3 ppl) | H7: Total MNT – 3 people | I7: Unit cost (4 ppl) | J7: Qty (4 ppl) | K7: Total MNT – 4 people | L7: Source / notes
A8: PAID BY UNIVERSITY
A9: Flights
B10: Hunnu Air MR861 Ulaanbaatar 08:45 → Erenhot 10:00, nonstop | C10: Fri 13 Nov | D10: 0.052083333 | E10: 136 | F10: USD | G10: =Compare!$B$6 | H10: =E10*G10*IF(F10="USD",Compare!$B$8,IF(F10="CNY",Compare!$B$9,IF(F10="HKD",Compare!$B$10,1))) | I10: =E10 | J10: =Compare!$B$7 | K10: =I10*J10*IF(F10="USD",Compare!$B$8,IF(F10="CNY",Compare!$B$9,IF(F10="HKD",Compare!$B$10,1))) | L10: SlickTrip 22 Oct: $136 on 11, 12 and 13 Nov (usual $120–140). Checked bag ~20 kg per travel guides (not confirmed).
B11: Air China CA955 Beijing Capital (PEK) 12:55 → Ulaanbaatar 15:05, nonstop | C11: 16 Nov | D11: 0.090277778 | E11: 171 | F11: USD | G11: =Compare!$B$6 | H11: =E11*G11*IF(F11="USD",Compare!$B$8,IF(F11="CNY",Compare!$B$9,IF(F11="HKD",Compare!$B$10,1))) | I11: =E11 | J11: =Compare!$B$7 | K11: =I11*J11*IF(F11="USD",Compare!$B$8,IF(F11="CNY",Compare!$B$9,IF(F11="HKD",Compare!$B$10,1))) | L11: Trip.com 22 Oct: US$171 pp, cheapest that day (MIAT OM224 11:30 US$193 on Trip.com / $176 on SlickTrip; Air China 08:25 $215; Capital + Hunnu via Erenhot $196)
A12: Trains & border crossing
B13: Train 4654 Erenhot 12:45 → Jining South 18:11, hard seat | C13: 13 Nov | D13: 0.22638889 | E13: 44.5 | F13: CNY | G13: =Compare!$B$6 | H13: =E13*G13*IF(F13="USD",Compare!$B$8,IF(F13="CNY",Compare!$B$9,IF(F13="HKD",Compare!$B$10,1))) | I13: =E13 | J13: =Compare!$B$7 | K13: =I13*J13*IF(F13="USD",Compare!$B$8,IF(F13="CNY",Compare!$B$9,IF(F13="HKD",Compare!$B$10,1))) | L13: 12306 (5 Nov query): seat ¥44.5, hard sleeper ¥90.5. ChinaTicketOnline confirms 11 and 13 Nov; on sale 30 Oct 15:00 for 13 Nov.
B14: Overnight train T301 Jining South 19:30 → Shenyang 10:16, hard seat | C14: 13–14 Nov | D14: 0.61527778 | E14: 163.5 | F14: CNY | G14: =Compare!$B$6 | H14: =E14*G14*IF(F14="USD",Compare!$B$8,IF(F14="CNY",Compare!$B$9,IF(F14="HKD",Compare!$B$10,1))) | I14: =E14 | J14: =Compare!$B$7 | K14: =I14*J14*IF(F14="USD",Compare!$B$8,IF(F14="CNY",Compare!$B$9,IF(F14="HKD",Compare!$B$10,1))) | L14: 12306 (5 Nov query): seat ¥163.5, hard sleeper ¥280.5, soft ¥438.5; 1 h 19 min change at Jining South. ChinaTicketOnline confirms 13 Nov, on sale 30 Oct 15:00. Also K1567 17:31 → 09:38 (same fares).
B15: Overnight train K28 Shenyang 22:24 → Beijing 08:40, hard seat (after the contest) | C15: 15 Nov (night) | D15: 0.42777778 | E15: 112 | F15: CNY | G15: =Compare!$B$6 | H15: =E15*G15*IF(F15="USD",Compare!$B$8,IF(F15="CNY",Compare!$B$9,IF(F15="HKD",Compare!$B$10,1))) | I15: =E15 | J15: =Compare!$B$7 | K15: =I15*J15*IF(F15="USD",Compare!$B$8,IF(F15="CNY",Compare!$B$9,IF(F15="HKD",Compare!$B$10,1))) | L15: 12306 (5 Nov query): hard seat ¥112 (hard sleeper ¥194). Cheapest train that still makes the 12:55 flight (K96 23:39 ¥102 arrives 11:19 – too late). Lie-flat upgrade: K54 Shenyang North 22:00 → 06:58 hard sleeper ¥171 (+¥59 pp). On sale 1 Nov 09:30 (ChinaTicketOnline confirms 15 Nov).
A16: Accommodation
B17: Ji Hotel Sanhao Street, 55 Sanhao St (~940 m to NEU Nanhu, ~15 min walk): 2 Budget Twin rooms, King Koil mattresses, windows, floors 4–16 – a bed each | C17: 14–15 Nov (1 night) | E17: 457 | F17: CNY | G17: 1 | H17: =E17*G17*IF(F17="USD",Compare!$B$8,IF(F17="CNY",Compare!$B$9,IF(F17="HKD",Compare!$B$10,1))) | I17: 457 | J17: 1 | K17: =I17*J17*IF(F17="USD",Compare!$B$8,IF(F17="CNY",Compare!$B$9,IF(F17="HKD",Compare!$B$10,1))) | L17: Trip.com 22 Oct: ¥457 for 2 Budget Twin rooms × 1 night (14–15 Nov) incl. taxes, free cancellation until 18:00 on 13 Nov; same hotel as 'Sleep value' (9.0, King Koil mattresses).
A18: Meals & local transport
B19: Meals | C19: in destination | E19: 80 | F19: CNY | G19: =Compare!$B$6*$B$4 | H19: =E19*G19*IF(F19="USD",Compare!$B$8,IF(F19="CNY",Compare!$B$9,IF(F19="HKD",Compare!$B$10,1))) | I19: =E19 | J19: =Compare!$B$7*$B$4 | K19: =I19*J19*IF(F19="USD",Compare!$B$8,IF(F19="CNY",Compare!$B$9,IF(F19="HKD",Compare!$B$10,1))) | L19: ASSUMPTION 80 CNY/person/day; hosts usually provide some meals on contest days
B20: Local transport (metro, taxis) | C20: in destination | E20: 30 | F20: CNY | G20: =Compare!$B$6*$B$4 | H20: =E20*G20*IF(F20="USD",Compare!$B$8,IF(F20="CNY",Compare!$B$9,IF(F20="HKD",Compare!$B$10,1))) | I20: =E20 | J20: =Compare!$B$7*$B$4 | K20: =I20*J20*IF(F20="USD",Compare!$B$8,IF(F20="CNY",Compare!$B$9,IF(F20="HKD",Compare!$B$10,1))) | L20: ASSUMPTION 30 CNY/person/day
B21: Taxi Erenhot airport → Erenhot station | C21: 13 Nov | E21: 30 | F21: CNY | G21: 1 | H21: =E21*G21*IF(F21="USD",Compare!$B$8,IF(F21="CNY",Compare!$B$9,IF(F21="HKD",Compare!$B$10,1))) | I21: =E21 | J21: 1 | K21: =I21*J21*IF(F21="USD",Compare!$B$8,IF(F21="CNY",Compare!$B$9,IF(F21="HKD",Compare!$B$10,1))) | L21: ASSUMPTION ~¥30 per car
B22: Metro line 2 + Airport Express, Beijing station → PEK T3 | C22: 16 Nov | E22: 30 | F22: CNY | G22: =Compare!$B$6 | H22: =E22*G22*IF(F22="USD",Compare!$B$8,IF(F22="CNY",Compare!$B$9,IF(F22="HKD",Compare!$B$10,1))) | I22: =E22 | J22: =Compare!$B$7 | K22: =I22*J22*IF(F22="USD",Compare!$B$8,IF(F22="CNY",Compare!$B$9,IF(F22="HKD",Compare!$B$10,1))) | L22: ASSUMPTION Airport Express ¥25 + metro ¥4–5 pp
A23: PAID PERSONALLY (university won't cover)
A24: Contest fee
B25: Shenyang regional registration fee (per team) | C25: pay when invited | E25: 1500 | F25: CNY | G25: 1 | H25: =E25*G25*IF(F25="USD",Compare!$B$8,IF(F25="CNY",Compare!$B$9,IF(F25="HKD",Compare!$B$10,1))) | I25: =E25 | J25: 1 | K25: =I25*J25*IF(F25="USD",Compare!$B$8,IF(F25="CNY",Compare!$B$9,IF(F25="HKD",Compare!$B$10,1))) | L25: ASSUMPTION: 1,500 CNY/team like recent EC regionals; the 2026 Shenyang invitation was not found on 22 Oct
A26: Other
B27: Taxi to/from Chinggis Khaan airport (UB), per trip | C27: out & back | D27: 0.041666667 | E27: 100000 | F27: MNT | G27: 2 | H27: =E27*G27*IF(F27="USD",Compare!$B$8,IF(F27="CNY",Compare!$B$9,IF(F27="HKD",Compare!$B$10,1))) | I27: =E27 | J27: 2 | K27: =I27*J27*IF(F27="USD",Compare!$B$8,IF(F27="CNY",Compare!$B$9,IF(F27="HKD",Compare!$B$10,1))) | L27: ASSUMPTION 100k MNT per trip for the group
B28: Travel medical insurance | E28: 30000 | F28: MNT | G28: =Compare!$B$6 | H28: =E28*G28*IF(F28="USD",Compare!$B$8,IF(F28="CNY",Compare!$B$9,IF(F28="HKD",Compare!$B$10,1))) | I28: =E28 | J28: =Compare!$B$7 | K28: =I28*J28*IF(F28="USD",Compare!$B$8,IF(F28="CNY",Compare!$B$9,IF(F28="HKD",Compare!$B$10,1))) | L28: ASSUMPTION ~30k MNT per person, Mongolian insurer
B29: Mobile data eSIM | E29: 10 | F29: USD | G29: =Compare!$B$6 | H29: =E29*G29*IF(F29="USD",Compare!$B$8,IF(F29="CNY",Compare!$B$9,IF(F29="HKD",Compare!$B$10,1))) | I29: =E29 | J29: =Compare!$B$7 | K29: =I29*J29*IF(F29="USD",Compare!$B$8,IF(F29="CNY",Compare!$B$9,IF(F29="HKD",Compare!$B$10,1))) | L29: ASSUMPTION ~$10 pp
B30: Visa | E30: 0 | F30: MNT | G30: =Compare!$B$6 | H30: =E30*G30*IF(F30="USD",Compare!$B$8,IF(F30="CNY",Compare!$B$9,IF(F30="HKD",Compare!$B$10,1))) | I30: =E30 | J30: =Compare!$B$7 | K30: =I30*J30*IF(F30="USD",Compare!$B$8,IF(F30="CNY",Compare!$B$9,IF(F30="HKD",Compare!$B$10,1))) | L30: Mongolian passports: visa-free (mainland China up to 30 days; Hong Kong up to 14 days)
H32: 3 people – UNFUNDED | K32: 4 people – FUNDED ₮12M
G33: University-paid subtotal | H33: =SUM(H9:H22) | K33: =SUM(K9:K22)
G34: Contingency | H34: =H33*Compare!$B$11 | K34: =K33*Compare!$B$11
G35: University-paid total incl. contingency | H35: =H33+H34 | K35: =K33+K34
G36: Funding left (negative = over) | H36: =Compare!$B$12-H35 | K36: =Compare!$B$5-K35
G37: Personal costs – team | H37: =SUM(H24:H30) | K37: =SUM(K24:K30)
G38: Out-of-pocket per person (personal + any overrun) | H38: =(H37+MAX(0,-H36))/Compare!$B$6 | K38: =(K37+MAX(0,-K36))/Compare!$B$7
G39: Whole trip cost (university + personal) | H39: =H35+H37 | K39: =K35+K37
G40: Time in planes & trains | H40: =SUM(D10:D11)+SUM(D13:D15) | K40: =SUM(D10:D11)+SUM(D13:D15)
A42: Key facts
A43: Contest | B43: Asia Shenyang Regional, 14–15 Nov 2026 (provisional; the 2026 invitation was not found on 22 Oct), Northeastern University Nanhu campus (2024 and 2025 venue). Assumed: day 1 registration + practice, contest 15 Nov 09:00–14:00, awards ~17:00.
A44: Why this plan | B44: Flies over the border instead of the jeep: ~₮0.61M per person, the same trains as the overland plans. Cheaper way out than the Air China + G153 route of 'Sleep value' (₮0.91M per person); the rest of the trip is the same (Ji Hotel twin rooms, K28 hard seat + Air China 12:55 home), with hotel nights set by the arrival time.
A45: Trade-off | B45: Wake ~05:30 for the 08:45 flight, then a seated night on T301 before day 1 (POOR for sleep). Costs ~₮0.42M pp more than the overland seats for a safer border crossing.
A46: Book | B46: Hunnu on SlickTrip / Ctrip now; 4654 and T301 on 12306 at 15:00 on 30 Oct; K28 on 12306 at 09:30 on 1 Nov; Air China home on Trip.com.
A48: Day-by-day plan
A49: Date | B49: Sleep in | C49: What happens
A50: Fri 13 Nov | B50: Train (seat) | C50: Hunnu MR861 UB 08:45 → Erenhot 10:00; taxi to Erenhot station; 4654 12:45 → Jining South 18:11; T301 19:30 → Shenyang (overnight).
A51: Sat 14 Nov | B51: Shenyang | C51: Taxi from the station to NEU Nanhu for registration and practice; check in at Ji Hotel (twin rooms). Lights out ~22:30.
A52: Sun 15 Nov | B52: Train (seat) | C52: CONTEST. Wake ~06:50, walk ~15 min. Check out before leaving, luggage stored at the hotel. Awards ~17:00; taxi to Shenyang station; K28 22:24 hard seat → Beijing 08:40.
A53: Mon 16 Nov | B53: Home | C53: Metro line 2 + Airport Express to PEK T3 (~1 h). Air China 12:55 → UB 15:05.
A55: Door-to-door travel times
A56: Date | B56: Leg | C56: Mode | D56: Expected time | E56: Notes
A57: 13 Nov | B57: Home → Chinggis Khaan airport | C57: Taxi (~50 km) | D57: 0.041666667 | E57: Leave ~06:15
A58: 13 Nov | B58: Ulaanbaatar → Erenhot | C58: Hunnu MR861 08:45–10:00 | D58: 0.052083333
A59: 13 Nov | B59: Erenhot arrival + taxi to the station | C59: Taxi | D59: 0.03125 | E59: Estimate
A60: 13 Nov | B60: Erenhot → Jining South | C60: 4654 hard seat 12:45–18:11 | D60: 0.22638889
A61: 13–14 Nov | B61: Jining South → Shenyang | C61: T301 hard seat 19:30–10:16 | D61: 0.61527778 | E61: Overnight
A62: 14 Nov | B62: Shenyang station → NEU Nanhu | C62: Taxi | D62: 0.013888889 | E62: Registration day
A63: 15 Nov | B63: NEU Nanhu → Shenyang station | C63: Taxi | D63: 0.013888889
A64: 15–16 Nov | B64: Shenyang → Beijing | C64: K28 hard seat 22:24–08:40 | D64: 0.42777778 | E64: Overnight, after the contest
A65: 16 Nov | B65: Beijing station → PEK | C65: Metro line 2 + Airport Express | D65: 0.041666667 | E65: Be at PEK by ~10:55
A66: 16 Nov | B66: Beijing (PEK) → Ulaanbaatar | C66: Air China 12:55–15:05 | D66: 0.090277778
A67: 16 Nov | B67: Chinggis Khaan airport → home | C67: Taxi | D67: 0.041666667
C69: Total door-to-door | D69: =SUM(D57:D67)

Sheet Shenyang – Hohhot red-eye
A1: Shenyang – Hohhot red-eye
A2: MIAT red-eye to Hohhot (Wed 11 Nov 22:25), a short hotel night, T304 overnight to Shenyang in a hard seat; two hotel nights before the contest; K28 seat + Air China home.
A4: Days in destination (meals & local transport) | B4: 4.5 | C4: 12 Nov → 16 Nov midday
A5: Shared inputs are on the Compare sheet. Scroll down for the day-by-day plan and door-to-door travel times.
A7: Category | B7: Item | C7: Date | D7: Travel time | E7: Unit cost (3 ppl) | F7: Currency | G7: Qty (3 ppl) | H7: Total MNT – 3 people | I7: Unit cost (4 ppl) | J7: Qty (4 ppl) | K7: Total MNT – 4 people | L7: Source / notes
A8: PAID BY UNIVERSITY
A9: Flights
B10: MIAT OM257 Ulaanbaatar 22:25 → Hohhot 00:15 (+1), nonstop (red-eye) | C10: Wed 11 Nov | D10: 0.076388889 | E10: 946 | F10: CNY | G10: =Compare!$B$6 | H10: =E10*G10*IF(F10="USD",Compare!$B$8,IF(F10="CNY",Compare!$B$9,IF(F10="HKD",Compare!$B$10,1))) | I10: =E10 | J10: =Compare!$B$7 | K10: =I10*J10*IF(F10="USD",Compare!$B$8,IF(F10="CNY",Compare!$B$9,IF(F10="HKD",Compare!$B$10,1))) | L10: Ctrip 22 Oct: ¥946 on 11 and 13 Nov (SlickTrip $148). Air China CA758 13:00 is ¥1,011.
B11: Air China CA955 Beijing Capital (PEK) 12:55 → Ulaanbaatar 15:05, nonstop | C11: 16 Nov | D11: 0.090277778 | E11: 171 | F11: USD | G11: =Compare!$B$6 | H11: =E11*G11*IF(F11="USD",Compare!$B$8,IF(F11="CNY",Compare!$B$9,IF(F11="HKD",Compare!$B$10,1))) | I11: =E11 | J11: =Compare!$B$7 | K11: =I11*J11*IF(F11="USD",Compare!$B$8,IF(F11="CNY",Compare!$B$9,IF(F11="HKD",Compare!$B$10,1))) | L11: Trip.com 22 Oct: US$171 pp, cheapest that day (MIAT OM224 11:30 US$193 on Trip.com / $176 on SlickTrip; Air China 08:25 $215; Capital + Hunnu via Erenhot $196)
A12: Trains
B13: Overnight train T304 Hohhot East 17:36 → Shenyang 10:16, hard seat | C13: 12–13 Nov | D13: 0.69444444 | E13: 173.5 | F13: CNY | G13: =Compare!$B$6 | H13: =E13*G13*IF(F13="USD",Compare!$B$8,IF(F13="CNY",Compare!$B$9,IF(F13="HKD",Compare!$B$10,1))) | I13: =E13 | J13: =Compare!$B$7 | K13: =I13*J13*IF(F13="USD",Compare!$B$8,IF(F13="CNY",Compare!$B$9,IF(F13="HKD",Compare!$B$10,1))) | L13: 12306 (5 Nov query): seat ¥173.5, hard sleeper ¥296.5, soft ¥464.5. ChinaTicketOnline confirms 12 Nov, on sale 29 Oct 14:00.
B14: Overnight train K28 Shenyang 22:24 → Beijing 08:40, hard seat (after the contest) | C14: 15 Nov (night) | D14: 0.42777778 | E14: 112 | F14: CNY | G14: =Compare!$B$6 | H14: =E14*G14*IF(F14="USD",Compare!$B$8,IF(F14="CNY",Compare!$B$9,IF(F14="HKD",Compare!$B$10,1))) | I14: =E14 | J14: =Compare!$B$7 | K14: =I14*J14*IF(F14="USD",Compare!$B$8,IF(F14="CNY",Compare!$B$9,IF(F14="HKD",Compare!$B$10,1))) | L14: 12306 (5 Nov query): hard seat ¥112 (hard sleeper ¥194). Cheapest train that still makes the 12:55 flight (K96 23:39 ¥102 arrives 11:19 – too late). Lie-flat upgrade: K54 Shenyang North 22:00 → 06:58 hard sleeper ¥171 (+¥59 pp). On sale 1 Nov 09:30 (ChinaTicketOnline confirms 15 Nov).
A15: Accommodation
B16: Budget hotel in Hohhot for the rest of the night after the red-eye | C16: 12 Nov (00:30–noon) | E16: 200 | F16: CNY | G16: 1 | H16: =E16*G16*IF(F16="USD",Compare!$B$8,IF(F16="CNY",Compare!$B$9,IF(F16="HKD",Compare!$B$10,1))) | I16: 200 | J16: 2 | K16: =I16*J16*IF(F16="USD",Compare!$B$8,IF(F16="CNY",Compare!$B$9,IF(F16="HKD",Compare!$B$10,1))) | L16: ASSUMPTION ~¥200 per room (1 room for 3, 2 rooms for 4); not searched
B17: Ji Hotel Sanhao Street, 55 Sanhao St (~940 m to NEU Nanhu, ~15 min walk): 2 Budget Twin rooms, King Koil mattresses, windows, floors 4–16 – a bed each | C17: 13–15 Nov (2 nights) | E17: 457 | F17: CNY | G17: 2 | H17: =E17*G17*IF(F17="USD",Compare!$B$8,IF(F17="CNY",Compare!$B$9,IF(F17="HKD",Compare!$B$10,1))) | I17: 457 | J17: 2 | K17: =I17*J17*IF(F17="USD",Compare!$B$8,IF(F17="CNY",Compare!$B$9,IF(F17="HKD",Compare!$B$10,1))) | L17: ASSUMPTION 2 nights at ¥457 per night for 2 Budget Twin rooms (Trip.com 22 Oct: ¥457 for 14–15 Nov, ¥1,371 for 12–15 Nov).
A18: Meals & local transport
B19: Meals | C19: in destination | E19: 80 | F19: CNY | G19: =Compare!$B$6*$B$4 | H19: =E19*G19*IF(F19="USD",Compare!$B$8,IF(F19="CNY",Compare!$B$9,IF(F19="HKD",Compare!$B$10,1))) | I19: =E19 | J19: =Compare!$B$7*$B$4 | K19: =I19*J19*IF(F19="USD",Compare!$B$8,IF(F19="CNY",Compare!$B$9,IF(F19="HKD",Compare!$B$10,1))) | L19: ASSUMPTION 80 CNY/person/day; hosts usually provide some meals on contest days
B20: Local transport (metro, taxis) | C20: in destination | E20: 30 | F20: CNY | G20: =Compare!$B$6*$B$4 | H20: =E20*G20*IF(F20="USD",Compare!$B$8,IF(F20="CNY",Compare!$B$9,IF(F20="HKD",Compare!$B$10,1))) | I20: =E20 | J20: =Compare!$B$7*$B$4 | K20: =I20*J20*IF(F20="USD",Compare!$B$8,IF(F20="CNY",Compare!$B$9,IF(F20="HKD",Compare!$B$10,1))) | L20: ASSUMPTION 30 CNY/person/day
B21: Taxis Hohhot airport → hotel → Hohhot East station | C21: 12 Nov | E21: 60 | F21: CNY | G21: 1 | H21: =E21*G21*IF(F21="USD",Compare!$B$8,IF(F21="CNY",Compare!$B$9,IF(F21="HKD",Compare!$B$10,1))) | I21: =E21 | J21: 1 | K21: =I21*J21*IF(F21="USD",Compare!$B$8,IF(F21="CNY",Compare!$B$9,IF(F21="HKD",Compare!$B$10,1))) | L21: ASSUMPTION ~¥60 per car for both rides
B22: Metro line 2 + Airport Express, Beijing station → PEK T3 | C22: 16 Nov | E22: 30 | F22: CNY | G22: =Compare!$B$6 | H22: =E22*G22*IF(F22="USD",Compare!$B$8,IF(F22="CNY",Compare!$B$9,IF(F22="HKD",Compare!$B$10,1))) | I22: =E22 | J22: =Compare!$B$7 | K22: =I22*J22*IF(F22="USD",Compare!$B$8,IF(F22="CNY",Compare!$B$9,IF(F22="HKD",Compare!$B$10,1))) | L22: ASSUMPTION Airport Express ¥25 + metro ¥4–5 pp
A23: PAID PERSONALLY (university won't cover)
A24: Contest fee
B25: Shenyang regional registration fee (per team) | C25: pay when invited | E25: 1500 | F25: CNY | G25: 1 | H25: =E25*G25*IF(F25="USD",Compare!$B$8,IF(F25="CNY",Compare!$B$9,IF(F25="HKD",Compare!$B$10,1))) | I25: =E25 | J25: 1 | K25: =I25*J25*IF(F25="USD",Compare!$B$8,IF(F25="CNY",Compare!$B$9,IF(F25="HKD",Compare!$B$10,1))) | L25: ASSUMPTION: 1,500 CNY/team like recent EC regionals; the 2026 Shenyang invitation was not found on 22 Oct
A26: Other
B27: Taxi to/from Chinggis Khaan airport (UB), per trip | C27: out & back | D27: 0.041666667 | E27: 100000 | F27: MNT | G27: 2 | H27: =E27*G27*IF(F27="USD",Compare!$B$8,IF(F27="CNY",Compare!$B$9,IF(F27="HKD",Compare!$B$10,1))) | I27: =E27 | J27: 2 | K27: =I27*J27*IF(F27="USD",Compare!$B$8,IF(F27="CNY",Compare!$B$9,IF(F27="HKD",Compare!$B$10,1))) | L27: ASSUMPTION 100k MNT per trip for the group
B28: Travel medical insurance | E28: 30000 | F28: MNT | G28: =Compare!$B$6 | H28: =E28*G28*IF(F28="USD",Compare!$B$8,IF(F28="CNY",Compare!$B$9,IF(F28="HKD",Compare!$B$10,1))) | I28: =E28 | J28: =Compare!$B$7 | K28: =I28*J28*IF(F28="USD",Compare!$B$8,IF(F28="CNY",Compare!$B$9,IF(F28="HKD",Compare!$B$10,1))) | L28: ASSUMPTION ~30k MNT per person, Mongolian insurer
B29: Mobile data eSIM | E29: 10 | F29: USD | G29: =Compare!$B$6 | H29: =E29*G29*IF(F29="USD",Compare!$B$8,IF(F29="CNY",Compare!$B$9,IF(F29="HKD",Compare!$B$10,1))) | I29: =E29 | J29: =Compare!$B$7 | K29: =I29*J29*IF(F29="USD",Compare!$B$8,IF(F29="CNY",Compare!$B$9,IF(F29="HKD",Compare!$B$10,1))) | L29: ASSUMPTION ~$10 pp
B30: Visa | E30: 0 | F30: MNT | G30: =Compare!$B$6 | H30: =E30*G30*IF(F30="USD",Compare!$B$8,IF(F30="CNY",Compare!$B$9,IF(F30="HKD",Compare!$B$10,1))) | I30: =E30 | J30: =Compare!$B$7 | K30: =I30*J30*IF(F30="USD",Compare!$B$8,IF(F30="CNY",Compare!$B$9,IF(F30="HKD",Compare!$B$10,1))) | L30: Mongolian passports: visa-free (mainland China up to 30 days; Hong Kong up to 14 days)
H32: 3 people – UNFUNDED | K32: 4 people – FUNDED ₮12M
G33: University-paid subtotal | H33: =SUM(H9:H22) | K33: =SUM(K9:K22)
G34: Contingency | H34: =H33*Compare!$B$11 | K34: =K33*Compare!$B$11
G35: University-paid total incl. contingency | H35: =H33+H34 | K35: =K33+K34
G36: Funding left (negative = over) | H36: =Compare!$B$12-H35 | K36: =Compare!$B$5-K35
G37: Personal costs – team | H37: =SUM(H24:H30) | K37: =SUM(K24:K30)
G38: Out-of-pocket per person (personal + any overrun) | H38: =(H37+MAX(0,-H36))/Compare!$B$6 | K38: =(K37+MAX(0,-K36))/Compare!$B$7
G39: Whole trip cost (university + personal) | H39: =H35+H37 | K39: =K35+K37
G40: Time in planes & trains | H40: =SUM(D10:D11)+SUM(D13:D14) | K40: =SUM(D10:D11)+SUM(D13:D14)
A42: Key facts
A43: Contest | B43: Asia Shenyang Regional, 14–15 Nov 2026 (provisional; the 2026 invitation was not found on 22 Oct), Northeastern University Nanhu campus (2024 and 2025 venue). Assumed: day 1 registration + practice, contest 15 Nov 09:00–14:00, awards ~17:00.
A44: Why this plan | B44: ~₮0.61M per person to Shenyang by the cheapest flight into Hohhot. Cheaper way out than the Air China + G153 route of 'Sleep value' (₮0.91M per person); the rest of the trip is the same (Ji Hotel twin rooms, K28 hard seat + Air China 12:55 home), with hotel nights set by the arrival time.
A45: Trade-off | B45: Red-eye landing at 00:15 (bed ~01:30) and a seated night on T304 three nights before the contest; two hotel nights after it. Hohhot hotel price is a guess.
A46: Book | B46: MIAT on Ctrip now; T304 on 12306 at 14:00 on 29 Oct; K28 on 12306 at 09:30 on 1 Nov; Air China home on Trip.com.
A48: Day-by-day plan
A49: Date | B49: Sleep in | C49: What happens
A50: Wed 11 Nov | B50: Hohhot (budget hotel) | C50: MIAT OM257 UB 22:25 → Hohhot 00:15; taxi to a budget hotel; bed ~01:30.
A51: Thu 12 Nov | B51: Train (seat) | C51: Late morning in Hohhot; taxi to Hohhot East; T304 17:36 → Shenyang (overnight).
A52: Fri 13 Nov | B52: Shenyang | C52: Arrive Shenyang 10:16; taxi to Ji Hotel; rest.
A53: Sat 14 Nov | B53: Shenyang | C53: Registration, opening and practice at NEU Nanhu. Lights out ~22:30.
A54: Sun 15 Nov | B54: Train (seat) | C54: CONTEST. Wake ~06:50, walk ~15 min. Check out before leaving, luggage stored at the hotel. Awards ~17:00; taxi to Shenyang station; K28 22:24 hard seat → Beijing 08:40.
A55: Mon 16 Nov | B55: Home | C55: Metro line 2 + Airport Express to PEK T3 (~1 h). Air China 12:55 → UB 15:05.
A57: Door-to-door travel times
A58: Date | B58: Leg | C58: Mode | D58: Expected time | E58: Notes
A59: 11 Nov | B59: Home → Chinggis Khaan airport | C59: Taxi (~50 km) | D59: 0.041666667 | E59: Leave ~19:30
A60: 11–12 Nov | B60: Ulaanbaatar → Hohhot | C60: MIAT OM257 22:25–00:15 | D60: 0.076388889 | E60: Red-eye
A61: 12 Nov | B61: HET arrival + taxi to a hotel | C61: Taxi | D61: 0.041666667 | E61: Estimate
A62: 12 Nov | B62: Hotel → Hohhot East station | C62: Taxi | D62: 0.020833333 | E62: Estimate
A63: 12–13 Nov | B63: Hohhot East → Shenyang | C63: T304 hard seat 17:36–10:16 | D63: 0.69444444 | E63: Overnight
A64: 13 Nov | B64: Shenyang station → Ji Hotel | C64: Taxi | D64: 0.013888889
A65: 14–15 Nov | B65: Hotel ↔ NEU Nanhu (each way) | C65: Walk | D65: daily | E65: ~15 min walk
A66: 15 Nov | B66: NEU Nanhu → Shenyang station | C66: Taxi | D66: 0.013888889
A67: 15–16 Nov | B67: Shenyang → Beijing | C67: K28 hard seat 22:24–08:40 | D67: 0.42777778 | E67: Overnight, after the contest
A68: 16 Nov | B68: Beijing station → PEK | C68: Metro line 2 + Airport Express | D68: 0.041666667 | E68: Be at PEK by ~10:55
A69: 16 Nov | B69: Beijing (PEK) → Ulaanbaatar | C69: Air China 12:55–15:05 | D69: 0.090277778
A70: 16 Nov | B70: Chinggis Khaan airport → home | C70: Taxi | D70: 0.041666667
C72: Total door-to-door | D72: =SUM(D59:D70)

Sheet Shenyang – Hohhot + Spring
A1: Shenyang – Hohhot + Spring
A2: No early alarm and no night train, like 'Sleep value', but cheaper: Air China to Hohhot and a ¥360 Spring flight to Shenyang (¥220 + taxes, two tickets); three nights in Ji Hotel twin rooms; K28 seat + Air China home.
A4: Days in destination (meals & local transport) | B4: 4 | C4: 12 Nov afternoon → 16 Nov midday
A5: Shared inputs are on the Compare sheet. Scroll down for the day-by-day plan and door-to-door travel times.
A7: Category | B7: Item | C7: Date | D7: Travel time | E7: Unit cost (3 ppl) | F7: Currency | G7: Qty (3 ppl) | H7: Total MNT – 3 people | I7: Unit cost (4 ppl) | J7: Qty (4 ppl) | K7: Total MNT – 4 people | L7: Source / notes
A8: PAID BY UNIVERSITY
A9: Flights
B10: Air China CA758 Ulaanbaatar 13:00 → Hohhot 14:40, nonstop, checked bag included | C10: Thu 12 Nov | D10: 0.069444444 | E10: 1011 | F10: CNY | G10: =Compare!$B$6 | H10: =E10*G10*IF(F10="USD",Compare!$B$8,IF(F10="CNY",Compare!$B$9,IF(F10="HKD",Compare!$B$10,1))) | I10: =E10 | J10: =Compare!$B$7 | K10: =I10*J10*IF(F10="USD",Compare!$B$8,IF(F10="CNY",Compare!$B$9,IF(F10="HKD",Compare!$B$10,1))) | L10: Ctrip 27 Oct: ¥1,011 incl. taxes on every day 10–13 Nov (Trip.com ¥1,009; 22 Oct also ¥1,011; SlickTrip $268). Separate ticket from the Spring flight: a 4 h 25 min self-transfer in Hohhot (immigration, collect bags, check in again).
B11: Spring Airlines 9C6782 Hohhot 19:05 → Shenyang Taoxian 21:15, nonstop (A320) | C11: Thu 12 Nov | D11: 0.090277778 | E11: 360 | F11: CNY | G11: =Compare!$B$6 | H11: =E11*G11*IF(F11="USD",Compare!$B$8,IF(F11="CNY",Compare!$B$9,IF(F11="HKD",Compare!$B$10,1))) | I11: =E11 | J11: =Compare!$B$7 | K11: =I11*J11*IF(F11="USD",Compare!$B$8,IF(F11="CNY",Compare!$B$9,IF(F11="HKD",Compare!$B$10,1))) | L11: Ctrip 27 Oct: fare ¥220 (10 and 12 Nov; 11 / 13 Nov ¥400) + ¥50 airport fee + ¥90 fuel surcharge (domestic > 800 km from 10 Oct 2026) = ¥360. Trip.com shows CNY 360 incl. taxes on 10 Nov (12 Nov only a CNY 520 bundle). The 22 Oct ¥290 left the taxes out. Only a 7 kg cabin bag (20×30×40 cm). Booked apart from CA758 – one ticket UB → SHE is ¥1,531 on Ctrip / ¥1,528 on Trip.com (12 Nov).
B12: Spring checked bag, one per person (bought online with the ticket) | C12: Thu 12 Nov | E12: 120 | F12: CNY | G12: =Compare!$B$6 | H12: =E12*G12*IF(F12="USD",Compare!$B$8,IF(F12="CNY",Compare!$B$9,IF(F12="HKD",Compare!$B$10,1))) | I12: =E12 | J12: =Compare!$B$7 | K12: =I12*J12*IF(F12="USD",Compare!$B$8,IF(F12="CNY",Compare!$B$9,IF(F12="HKD",Compare!$B$10,1))) | L12: Ctrip 27 Oct: the 9C6782 fare with a 20 kg checked bag is ¥340 vs ¥220 without (+¥120, same taxes). Only people who check a bag need it.
B13: Air China CA955 Beijing Capital (PEK) 12:55 → Ulaanbaatar 15:05, nonstop | C13: 16 Nov | D13: 0.090277778 | E13: 171 | F13: USD | G13: =Compare!$B$6 | H13: =E13*G13*IF(F13="USD",Compare!$B$8,IF(F13="CNY",Compare!$B$9,IF(F13="HKD",Compare!$B$10,1))) | I13: =E13 | J13: =Compare!$B$7 | K13: =I13*J13*IF(F13="USD",Compare!$B$8,IF(F13="CNY",Compare!$B$9,IF(F13="HKD",Compare!$B$10,1))) | L13: Trip.com 22 Oct: US$171 pp, cheapest that day (MIAT OM224 11:30 US$193 on Trip.com / $176 on SlickTrip; Air China 08:25 $215; Capital + Hunnu via Erenhot $196)
A14: Trains
B15: Overnight train K28 Shenyang 22:24 → Beijing 08:40, hard seat (after the contest) | C15: 15 Nov (night) | D15: 0.42777778 | E15: 112 | F15: CNY | G15: =Compare!$B$6 | H15: =E15*G15*IF(F15="USD",Compare!$B$8,IF(F15="CNY",Compare!$B$9,IF(F15="HKD",Compare!$B$10,1))) | I15: =E15 | J15: =Compare!$B$7 | K15: =I15*J15*IF(F15="USD",Compare!$B$8,IF(F15="CNY",Compare!$B$9,IF(F15="HKD",Compare!$B$10,1))) | L15: 12306 (5 Nov query): hard seat ¥112 (hard sleeper ¥194). Cheapest train that still makes the 12:55 flight (K96 23:39 ¥102 arrives 11:19 – too late). Lie-flat upgrade: K54 Shenyang North 22:00 → 06:58 hard sleeper ¥171 (+¥59 pp). On sale 1 Nov 09:30 (ChinaTicketOnline confirms 15 Nov).
A16: Accommodation
B17: Ji Hotel Sanhao Street, 55 Sanhao St (~940 m to NEU Nanhu, ~15 min walk): 2 Budget Twin rooms, King Koil mattresses, windows, floors 4–16 – a bed each | C17: 12–15 Nov (3 nights) | E17: 457 | F17: CNY | G17: 3 | H17: =E17*G17*IF(F17="USD",Compare!$B$8,IF(F17="CNY",Compare!$B$9,IF(F17="HKD",Compare!$B$10,1))) | I17: 457 | J17: 3 | K17: =I17*J17*IF(F17="USD",Compare!$B$8,IF(F17="CNY",Compare!$B$9,IF(F17="HKD",Compare!$B$10,1))) | L17: Trip.com 22 Oct: ¥1,371 for 2 rooms × 3 nights incl. taxes, free cancellation until 18:00 on 11 Nov (prepay); same price for 3 or 4 adults. 9.0 from 1,433 reviews; 16 m² rooms high in an office tower, above the street. Breakfast ¥40 optional.
A18: Meals & local transport
B19: Meals | C19: in destination | E19: 80 | F19: CNY | G19: =Compare!$B$6*$B$4 | H19: =E19*G19*IF(F19="USD",Compare!$B$8,IF(F19="CNY",Compare!$B$9,IF(F19="HKD",Compare!$B$10,1))) | I19: =E19 | J19: =Compare!$B$7*$B$4 | K19: =I19*J19*IF(F19="USD",Compare!$B$8,IF(F19="CNY",Compare!$B$9,IF(F19="HKD",Compare!$B$10,1))) | L19: ASSUMPTION 80 CNY/person/day; hosts usually provide some meals on contest days
B20: Local transport (metro, taxis) | C20: in destination | E20: 30 | F20: CNY | G20: =Compare!$B$6*$B$4 | H20: =E20*G20*IF(F20="USD",Compare!$B$8,IF(F20="CNY",Compare!$B$9,IF(F20="HKD",Compare!$B$10,1))) | I20: =E20 | J20: =Compare!$B$7*$B$4 | K20: =I20*J20*IF(F20="USD",Compare!$B$8,IF(F20="CNY",Compare!$B$9,IF(F20="HKD",Compare!$B$10,1))) | L20: ASSUMPTION 30 CNY/person/day
B21: Taxi Shenyang Taoxian airport → Ji Hotel | C21: 12 Nov | E21: 90 | F21: CNY | G21: 1 | H21: =E21*G21*IF(F21="USD",Compare!$B$8,IF(F21="CNY",Compare!$B$9,IF(F21="HKD",Compare!$B$10,1))) | I21: =E21 | J21: 1 | K21: =I21*J21*IF(F21="USD",Compare!$B$8,IF(F21="CNY",Compare!$B$9,IF(F21="HKD",Compare!$B$10,1))) | L21: ASSUMPTION ~¥90 per car, ~25 km, ~40 min
B22: Metro line 2 + Airport Express, Beijing station → PEK T3 | C22: 16 Nov | E22: 30 | F22: CNY | G22: =Compare!$B$6 | H22: =E22*G22*IF(F22="USD",Compare!$B$8,IF(F22="CNY",Compare!$B$9,IF(F22="HKD",Compare!$B$10,1))) | I22: =E22 | J22: =Compare!$B$7 | K22: =I22*J22*IF(F22="USD",Compare!$B$8,IF(F22="CNY",Compare!$B$9,IF(F22="HKD",Compare!$B$10,1))) | L22: ASSUMPTION Airport Express ¥25 + metro ¥4–5 pp
A23: PAID PERSONALLY (university won't cover)
A24: Contest fee
B25: Shenyang regional registration fee (per team) | C25: pay when invited | E25: 1500 | F25: CNY | G25: 1 | H25: =E25*G25*IF(F25="USD",Compare!$B$8,IF(F25="CNY",Compare!$B$9,IF(F25="HKD",Compare!$B$10,1))) | I25: =E25 | J25: 1 | K25: =I25*J25*IF(F25="USD",Compare!$B$8,IF(F25="CNY",Compare!$B$9,IF(F25="HKD",Compare!$B$10,1))) | L25: ASSUMPTION: 1,500 CNY/team like recent EC regionals; the 2026 Shenyang invitation was not found on 22 Oct
A26: Other
B27: Taxi to/from Chinggis Khaan airport (UB), per trip | C27: out & back | D27: 0.041666667 | E27: 100000 | F27: MNT | G27: 2 | H27: =E27*G27*IF(F27="USD",Compare!$B$8,IF(F27="CNY",Compare!$B$9,IF(F27="HKD",Compare!$B$10,1))) | I27: =E27 | J27: 2 | K27: =I27*J27*IF(F27="USD",Compare!$B$8,IF(F27="CNY",Compare!$B$9,IF(F27="HKD",Compare!$B$10,1))) | L27: ASSUMPTION 100k MNT per trip for the group
B28: Travel medical insurance | E28: 30000 | F28: MNT | G28: =Compare!$B$6 | H28: =E28*G28*IF(F28="USD",Compare!$B$8,IF(F28="CNY",Compare!$B$9,IF(F28="HKD",Compare!$B$10,1))) | I28: =E28 | J28: =Compare!$B$7 | K28: =I28*J28*IF(F28="USD",Compare!$B$8,IF(F28="CNY",Compare!$B$9,IF(F28="HKD",Compare!$B$10,1))) | L28: ASSUMPTION ~30k MNT per person, Mongolian insurer
B29: Mobile data eSIM | E29: 10 | F29: USD | G29: =Compare!$B$6 | H29: =E29*G29*IF(F29="USD",Compare!$B$8,IF(F29="CNY",Compare!$B$9,IF(F29="HKD",Compare!$B$10,1))) | I29: =E29 | J29: =Compare!$B$7 | K29: =I29*J29*IF(F29="USD",Compare!$B$8,IF(F29="CNY",Compare!$B$9,IF(F29="HKD",Compare!$B$10,1))) | L29: ASSUMPTION ~$10 pp
